Workbook
Name QF_M_ClientID: Lists!$M$1
Name QF_M_ClientName: Lists!$M$2
Name QF_M_Version: Lists!$M$3
Name QF_M_ExportedAt: Lists!$M$4
Name QF_M_ExportedBy: Lists!$M$5
Name QF_M_TemplateVersion: Lists!$M$6
Name QF_Client: Inputs!$C$8
Name QF_First: Inputs!$C$9
Name QF_Adviser: Inputs!$C$10
Name QF_Date: Inputs!$C$11
Name QF_AsAt: Inputs!$C$12
Name QF_Marital: Inputs!$C$13
Name QF_Residue: Inputs!$C$14
Name QF_Wishes: Inputs!$C$15
Name QF_TI: Inputs!$C$16
Name QF_TINote: Inputs!$C$17
Name QF_K_assets: Inputs!$B$20:$I$20
Name QF_T_assets: Inputs!$B$22:$I$39
Name QF_K_debts: Inputs!$B$43:$I$43
Name QF_T_debts: Inputs!$B$45:$I$54
Name QF_K_cover: Inputs!$B$57:$I$57
Name QF_T_cover: Inputs!$B$59:$I$70
Name QF_K_funds: Inputs!$B$74:$I$74
Name QF_T_funds: Inputs!$B$76:$I$83
Name QF_K_deps: Inputs!$B$87:$I$87
Name QF_T_deps: Inputs!$B$89:$I$94
Name QF_L_whom: Inputs!$Z$88:$Z$94
Name QF_KidsShare: Inputs!$C$95
Name QF_QuoteNo: Inputs!$C$99
Name QF_CLFee: Inputs!$C$100
Name QF_CLConv: Inputs!$C$101
Name QF_CLPays: Inputs!$C$102
Name QF_CLLimit: Inputs!$C$103
Name QF_CLPrem: Inputs!$C$104
Name QF_A_ExecFee: Inputs!$C$108
Name QF_A_VAT: Inputs!$C$109
Name QF_A_Master: Inputs!$C$110
Name QF_A_Funeral: Inputs!$C$111
Name QF_A_Sundries: Inputs!$C$112
Name QF_A_PropCost: Inputs!$C$113
Name QF_A_Agent: Inputs!$C$114
Name QF_A_Abatement: Inputs!$C$115
Name QF_A_DutyRate: Inputs!$C$116
Name QF_A_DutyBand: Inputs!$C$117
Name QF_A_DutyHigh: Inputs!$C$118
Name QF_A_CGTExcl: Inputs!$C$119
Name QF_A_Inclusion: Inputs!$C$120
Name QF_A_PRExcl: Inputs!$C$121
Name QF_A_Gross: Inputs!$C$122
Name QF_A_TrustFee: Inputs!$H$108
Name QF_A_Threshold: Inputs!$H$109
Name QF_A_Interest: Inputs!$H$110
Name QF_A_Dividends: Inputs!$H$111
Name QF_A_Growth: Inputs!$H$112
Name QF_A_DivTax: Inputs!$H$113
Name QF_A_CPI: Inputs!$H$114
Name QF_A_LAMin: Inputs!$H$115
Name QF_A_LAMax: Inputs!$H$116
Name QF_A_Rebate1: Inputs!$H$117
Name QF_A_Rebate2: Inputs!$H$118

Sheet Lists
A1: kind | B1: passes | C1: paidTo | D1: yesno | E1: residue | F1: rel | G1: kidsShare | H1: potShare | I1: closeWith | J1: marital | L1: ClientID
A2: Property | B2: Estate (residue) | C2: Estate | D2: Yes | E2: Heirs (people) | F2: Spouse | G2: In equal shares | H2: Equal shares | I2: Nothing | J2: Single | L2: ClientName
A3: Cash and deposits | B3: Spouse | C3: Spouse | D3: No | E3: Spouse | F3: Child | G3: As one family pot | H3: One family pot | I3: New life cover | J3: Engaged | L3: Version | M3: 2.0
A4: Shares and unit trusts | B4: Named heir | C4: Named person | F4: Other | G4: Not to the dependants | I4: Part of a nomination | J4: Married - ANC with accrual | L4: ExportedAt
A5: Other investment | I5: All of a nomination | J5: Married - ANC without accrual | L5: ExportedBy
A6: Tax-free investment | J6: Married in COP | L6: TemplateVersion | M6: 2.0
A7: Loan account | J7: Life partner
A8: Vehicle or contents | J8: Divorced
A9: Business interest | J9: Widowed
J10: Married
J11: Civil Union
J12: Co-Habitation

Sheet Inputs
B1: Duwalcoe Financial Consultants CC
B2: FSP 9978 | clinton@duwalcoe.co.za | 083 608 5617
B4: Inputs: check the yellow cells
B5: The CRM fills this sheet from the client's record. Yellow cells are yours to change; everything else works itself out.
B7: 1. The client
B8: Client
B9: First name, for the wording
B10: Prepared by
B11: Date of this FNA
B12: Values as at
B13: Marital status
B14: Who inherits the residue
... B19: 2. What they own (in the estate)
B20: name | C20: kind | D20: value | E20: base | F20: home | G20: passes | H20: sold | I20: notes
B21: Asset | C21: Kind | D21: Value (R) | E21: Base cost (R) | F21: Main home? | G21: Passes to | H21: Executor sells or cashes it? | I21: Notes | J21: Gain for capital gains tax
J22: =IF(L22=1,M22-N22,"") | L22: =IF(AND(OR(C22="Property",C22="Shares and unit trusts",C22="Other investment",C22="Business interest"),NOT(OR(G22="Spouse",AND(G22="Estate (residue)",'Inputs'!$C$14="Spouse")))),1,0) | M22: =IF(L22=1,N(D22)-N(E22),0) | N22: =IF(AND(L22=1,F22="Yes",M22>0),MIN(M22,'Inputs'!$C$121),0) | O22: =IF(OR(C22="Cash and deposits",H22="Yes"),N(D22),0) | P22: =IF(C22="Property",ROUND('Inputs'!$C$113/100*N(D22),2),0) | Q22: =IF(AND(C22="Property",H22="Yes"),ROUND('Inputs'!$C$114/100*(1+'Inputs'!$C$109/100)*N(D22),2),0) | R22: =IF(G22="Spouse",N(D22),0) | S22: =IF(G22="Named heir",N(D22),0) | T22: =IF(AND(L22=1,N(D22)>0,E22=""),1,0) | U22: =ROUND('Workings'!$C$37*S22,2) | V22: =ROUND('Workings'!$D$37*S22,2) | W22: =IF(AND(B22="",N(D22)=0),0,IF(OR(C22="",G22=""),1,0)) | X22: =IF(S22>0,COUNTIF(S$22:S22,">0"),0) | Y22: =IF(AND(G22="Estate (residue)",H22<>"Yes",OR(C22="Shares and unit trusts",C22="Other investment",C22="Tax-free investment")),N(D22),0)
J23: =IF(L23=1,M23-N23,"") | L23: =IF(AND(OR(C23="Property",C23="Shares and unit trusts",C23="Other investment",C23="Business interest"),NOT(OR(G23="Spouse",AND(G23="Estate (residue)",'Inputs'!$C$14="Spouse")))),1,0) | M23: =IF(L23=1,N(D23)-N(E23),0) | N23: =IF(AND(L23=1,F23="Yes",M23>0),MIN(M23,'Inputs'!$C$121),0) | O23: =IF(OR(C23="Cash and deposits",H23="Yes"),N(D23),0) | P23: =IF(C23="Property",ROUND('Inputs'!$C$113/100*N(D23),2),0) | Q23: =IF(AND(C23="Property",H23="Yes"),ROUND('Inputs'!$C$114/100*(1+'Inputs'!$C$109/100)*N(D23),2),0) | R23: =IF(G23="Spouse",N(D23),0) | S23: =IF(G23="Named heir",N(D23),0) | T23: =IF(AND(L23=1,N(D23)>0,E23=""),1,0) | U23: =ROUND('Workings'!$C$37*S23,2) | V23: =ROUND('Workings'!$D$37*S23,2) | W23: =IF(AND(B23="",N(D23)=0),0,IF(OR(C23="",G23=""),1,0)) | X23: =IF(S23>0,COUNTIF(S$22:S23,">0"),0) | Y23: =IF(AND(G23="Estate (residue)",H23<>"Yes",OR(C23="Shares and unit trusts",C23="Other investment",C23="Tax-free investment")),N(D23),0)
J24: =IF(L24=1,M24-N24,"") | L24: =IF(AND(OR(C24="Property",C24="Shares and unit trusts",C24="Other investment",C24="Business interest"),NOT(OR(G24="Spouse",AND(G24="Estate (residue)",'Inputs'!$C$14="Spouse")))),1,0) | M24: =IF(L24=1,N(D24)-N(E24),0) | N24: =IF(AND(L24=1,F24="Yes",M24>0),MIN(M24,'Inputs'!$C$121),0) | O24: =IF(OR(C24="Cash and deposits",H24="Yes"),N(D24),0) | P24: =IF(C24="Property",ROUND('Inputs'!$C$113/100*N(D24),2),0) | Q24: =IF(AND(C24="Property",H24="Yes"),ROUND('Inputs'!$C$114/100*(1+'Inputs'!$C$109/100)*N(D24),2),0) | R24: =IF(G24="Spouse",N(D24),0) | S24: =IF(G24="Named heir",N(D24),0) | T24: =IF(AND(L24=1,N(D24)>0,E24=""),1,0) | U24: =ROUND('Workings'!$C$37*S24,2) | V24: =ROUND('Workings'!$D$37*S24,2) | W24: =IF(AND(B24="",N(D24)=0),0,IF(OR(C24="",G24=""),1,0)) | X24: =IF(S24>0,COUNTIF(S$22:S24,">0"),0) | Y24: =IF(AND(G24="Estate (residue)",H24<>"Yes",OR(C24="Shares and unit trusts",C24="Other investment",C24="Tax-free investment")),N(D24),0)
J25: =IF(L25=1,M25-N25,"") | L25: =IF(AND(OR(C25="Property",C25="Shares and unit trusts",C25="Other investment",C25="Business interest"),NOT(OR(G25="Spouse",AND(G25="Estate (residue)",'Inputs'!$C$14="Spouse")))),1,0) | M25: =IF(L25=1,N(D25)-N(E25),0) | N25: =IF(AND(L25=1,F25="Yes",M25>0),MIN(M25,'Inputs'!$C$121),0) | O25: =IF(OR(C25="Cash and deposits",H25="Yes"),N(D25),0) | P25: =IF(C25="Property",ROUND('Inputs'!$C$113/100*N(D25),2),0) | Q25: =IF(AND(C25="Property",H25="Yes"),ROUND('Inputs'!$C$114/100*(1+'Inputs'!$C$109/100)*N(D25),2),0) | R25: =IF(G25="Spouse",N(D25),0) | S25: =IF(G25="Named heir",N(D25),0) | T25: =IF(AND(L25=1,N(D25)>0,E25=""),1,0) | U25: =ROUND('Workings'!$C$37*S25,2) | V25: =ROUND('Workings'!$D$37*S25,2) | W25: =IF(AND(B25="",N(D25)=0),0,IF(OR(C25="",G25=""),1,0)) | X25: =IF(S25>0,COUNTIF(S$22:S25,">0"),0) | Y25: =IF(AND(G25="Estate (residue)",H25<>"Yes",OR(C25="Shares and unit trusts",C25="Other investment",C25="Tax-free investment")),N(D25),0)
J26: =IF(L26=1,M26-N26,"") | L26: =IF(AND(OR(C26="Property",C26="Shares and unit trusts",C26="Other investment",C26="Business interest"),NOT(OR(G26="Spouse",AND(G26="Estate (residue)",'Inputs'!$C$14="Spouse")))),1,0) | M26: =IF(L26=1,N(D26)-N(E26),0) | N26: =IF(AND(L26=1,F26="Yes",M26>0),MIN(M26,'Inputs'!$C$121),0) | O26: =IF(OR(C26="Cash and deposits",H26="Yes"),N(D26),0) | P26: =IF(C26="Property",ROUND('Inputs'!$C$113/100*N(D26),2),0) | Q26: =IF(AND(C26="Property",H26="Yes"),ROUND('Inputs'!$C$114/100*(1+'Inputs'!$C$109/100)*N(D26),2),0) | R26: =IF(G26="Spouse",N(D26),0) | S26: =IF(G26="Named heir",N(D26),0) | T26: =IF(AND(L26=1,N(D26)>0,E26=""),1,0) | U26: =ROUND('Workings'!$C$37*S26,2) | V26: =ROUND('Workings'!$D$37*S26,2) | W26: =IF(AND(B26="",N(D26)=0),0,IF(OR(C26="",G26=""),1,0)) | X26: =IF(S26>0,COUNTIF(S$22:S26,">0"),0) | Y26: =IF(AND(G26="Estate (residue)",H26<>"Yes",OR(C26="Shares and unit trusts",C26="Other investment",C26="Tax-free investment")),N(D26),0)
J27: =IF(L27=1,M27-N27,"") | L27: =IF(AND(OR(C27="Property",C27="Shares and unit trusts",C27="Other investment",C27="Business interest"),NOT(OR(G27="Spouse",AND(G27="Estate (residue)",'Inputs'!$C$14="Spouse")))),1,0) | M27: =IF(L27=1,N(D27)-N(E27),0) | N27: =IF(AND(L27=1,F27="Yes",M27>0),MIN(M27,'Inputs'!$C$121),0) | O27: =IF(OR(C27="Cash and deposits",H27="Yes"),N(D27),0) | P27: =IF(C27="Property",ROUND('Inputs'!$C$113/100*N(D27),2),0) | Q27: =IF(AND(C27="Property",H27="Yes"),ROUND('Inputs'!$C$114/100*(1+'Inputs'!$C$109/100)*N(D27),2),0) | R27: =IF(G27="Spouse",N(D27),0) | S27: =IF(G27="Named heir",N(D27),0) | T27: =IF(AND(L27=1,N(D27)>0,E27=""),1,0) | U27: =ROUND('Workings'!$C$37*S27,2) | V27: =ROUND('Workings'!$D$37*S27,2) | W27: =IF(AND(B27="",N(D27)=0),0,IF(OR(C27="",G27=""),1,0)) | X27: =IF(S27>0,COUNTIF(S$22:S27,">0"),0) | Y27: =IF(AND(G27="Estate (residue)",H27<>"Yes",OR(C27="Shares and unit trusts",C27="Other investment",C27="Tax-free investment")),N(D27),0)
J28: =IF(L28=1,M28-N28,"") | L28: =IF(AND(OR(C28="Property",C28="Shares and unit trusts",C28="Other investment",C28="Business interest"),NOT(OR(G28="Spouse",AND(G28="Estate (residue)",'Inputs'!$C$14="Spouse")))),1,0) | M28: =IF(L28=1,N(D28)-N(E28),0) | N28: =IF(AND(L28=1,F28="Yes",M28>0),MIN(M28,'Inputs'!$C$121),0) | O28: =IF(OR(C28="Cash and deposits",H28="Yes"),N(D28),0) | P28: =IF(C28="Property",ROUND('Inputs'!$C$113/100*N(D28),2),0) | Q28: =IF(AND(C28="Property",H28="Yes"),ROUND('Inputs'!$C$114/100*(1+'Inputs'!$C$109/100)*N(D28),2),0) | R28: =IF(G28="Spouse",N(D28),0) | S28: =IF(G28="Named heir",N(D28),0) | T28: =IF(AND(L28=1,N(D28)>0,E28=""),1,0) | U28: =ROUND('Workings'!$C$37*S28,2) | V28: =ROUND('Workings'!$D$37*S28,2) | W28: =IF(AND(B28="",N(D28)=0),0,IF(OR(C28="",G28=""),1,0)) | X28: =IF(S28>0,COUNTIF(S$22:S28,">0"),0) | Y28: =IF(AND(G28="Estate (residue)",H28<>"Yes",OR(C28="Shares and unit trusts",C28="Other investment",C28="Tax-free investment")),N(D28),0)
J29: =IF(L29=1,M29-N29,"") | L29: =IF(AND(OR(C29="Property",C29="Shares and unit trusts",C29="Other investment",C29="Business interest"),NOT(OR(G29="Spouse",AND(G29="Estate (residue)",'Inputs'!$C$14="Spouse")))),1,0) | M29: =IF(L29=1,N(D29)-N(E29),0) | N29: =IF(AND(L29=1,F29="Yes",M29>0),MIN(M29,'Inputs'!$C$121),0) | O29: =IF(OR(C29="Cash and deposits",H29="Yes"),N(D29),0) | P29: =IF(C29="Property",ROUND('Inputs'!$C$113/100*N(D29),2),0) | Q29: =IF(AND(C29="Property",H29="Yes"),ROUND('Inputs'!$C$114/100*(1+'Inputs'!$C$109/100)*N(D29),2),0) | R29: =IF(G29="Spouse",N(D29),0) | S29: =IF(G29="Named heir",N(D29),0) | T29: =IF(AND(L29=1,N(D29)>0,E29=""),1,0) | U29: =ROUND('Workings'!$C$37*S29,2) | V29: =ROUND('Workings'!$D$37*S29,2) | W29: =IF(AND(B29="",N(D29)=0),0,IF(OR(C29="",G29=""),1,0)) | X29: =IF(S29>0,COUNTIF(S$22:S29,">0"),0) | Y29: =IF(AND(G29="Estate (residue)",H29<>"Yes",OR(C29="Shares and unit trusts",C29="Other investment",C29="Tax-free investment")),N(D29),0)
J30: =IF(L30=1,M30-N30,"") | L30: =IF(AND(OR(C30="Property",C30="Shares and unit trusts",C30="Other investment",C30="Business interest"),NOT(OR(G30="Spouse",AND(G30="Estate (residue)",'Inputs'!$C$14="Spouse")))),1,0) | M30: =IF(L30=1,N(D30)-N(E30),0) | N30: =IF(AND(L30=1,F30="Yes",M30>0),MIN(M30,'Inputs'!$C$121),0) | O30: =IF(OR(C30="Cash and deposits",H30="Yes"),N(D30),0) | P30: =IF(C30="Property",ROUND('Inputs'!$C$113/100*N(D30),2),0) | Q30: =IF(AND(C30="Property",H30="Yes"),ROUND('Inputs'!$C$114/100*(1+'Inputs'!$C$109/100)*N(D30),2),0) | R30: =IF(G30="Spouse",N(D30),0) | S30: =IF(G30="Named heir",N(D30),0) | T30: =IF(AND(L30=1,N(D30)>0,E30=""),1,0) | U30: =ROUND('Workings'!$C$37*S30,2) | V30: =ROUND('Workings'!$D$37*S30,2) | W30: =IF(AND(B30="",N(D30)=0),0,IF(OR(C30="",G30=""),1,0)) | X30: =IF(S30>0,COUNTIF(S$22:S30,">0"),0) | Y30: =IF(AND(G30="Estate (residue)",H30<>"Yes",OR(C30="Shares and unit trusts",C30="Other investment",C30="Tax-free investment")),N(D30),0)
J31: =IF(L31=1,M31-N31,"") | L31: =IF(AND(OR(C31="Property",C31="Shares and unit trusts",C31="Other investment",C31="Business interest"),NOT(OR(G31="Spouse",AND(G31="Estate (residue)",'Inputs'!$C$14="Spouse")))),1,0) | M31: =IF(L31=1,N(D31)-N(E31),0) | N31: =IF(AND(L31=1,F31="Yes",M31>0),MIN(M31,'Inputs'!$C$121),0) | O31: =IF(OR(C31="Cash and deposits",H31="Yes"),N(D31),0) | P31: =IF(C31="Property",ROUND('Inputs'!$C$113/100*N(D31),2),0) | Q31: =IF(AND(C31="Property",H31="Yes"),ROUND('Inputs'!$C$114/100*(1+'Inputs'!$C$109/100)*N(D31),2),0) | R31: =IF(G31="Spouse",N(D31),0) | S31: =IF(G31="Named heir",N(D31),0) | T31: =IF(AND(L31=1,N(D31)>0,E31=""),1,0) | U31: =ROUND('Workings'!$C$37*S31,2) | V31: =ROUND('Workings'!$D$37*S31,2) | W31: =IF(AND(B31="",N(D31)=0),0,IF(OR(C31="",G31=""),1,0)) | X31: =IF(S31>0,COUNTIF(S$22:S31,">0"),0) | Y31: =IF(AND(G31="Estate (residue)",H31<>"Yes",OR(C31="Shares and unit trusts",C31="Other investment",C31="Tax-free investment")),N(D31),0)
J32: =IF(L32=1,M32-N32,"") | L32: =IF(AND(OR(C32="Property",C32="Shares and unit trusts",C32="Other investment",C32="Business interest"),NOT(OR(G32="Spouse",AND(G32="Estate (residue)",'Inputs'!$C$14="Spouse")))),1,0) | M32: =IF(L32=1,N(D32)-N(E32),0) | N32: =IF(AND(L32=1,F32="Yes",M32>0),MIN(M32,'Inputs'!$C$121),0) | O32: =IF(OR(C32="Cash and deposits",H32="Yes"),N(D32),0) | P32: =IF(C32="Property",ROUND('Inputs'!$C$113/100*N(D32),2),0) | Q32: =IF(AND(C32="Property",H32="Yes"),ROUND('Inputs'!$C$114/100*(1+'Inputs'!$C$109/100)*N(D32),2),0) | R32: =IF(G32="Spouse",N(D32),0) | S32: =IF(G32="Named heir",N(D32),0) | T32: =IF(AND(L32=1,N(D32)>0,E32=""),1,0) | U32: =ROUND('Workings'!$C$37*S32,2) | V32: =ROUND('Workings'!$D$37*S32,2) | W32: =IF(AND(B32="",N(D32)=0),0,IF(OR(C32="",G32=""),1,0)) | X32: =IF(S32>0,COUNTIF(S$22:S32,">0"),0) | Y32: =IF(AND(G32="Estate (residue)",H32<>"Yes",OR(C32="Shares and unit trusts",C32="Other investment",C32="Tax-free investment")),N(D32),0)
J33: =IF(L33=1,M33-N33,"") | L33: =IF(AND(OR(C33="Property",C33="Shares and unit trusts",C33="Other investment",C33="Business interest"),NOT(OR(G33="Spouse",AND(G33="Estate (residue)",'Inputs'!$C$14="Spouse")))),1,0) | M33: =IF(L33=1,N(D33)-N(E33),0) | N33: =IF(AND(L33=1,F33="Yes",M33>0),MIN(M33,'Inputs'!$C$121),0) | O33: =IF(OR(C33="Cash and deposits",H33="Yes"),N(D33),0) | P33: =IF(C33="Property",ROUND('Inputs'!$C$113/100*N(D33),2),0) | Q33: =IF(AND(C33="Property",H33="Yes"),ROUND('Inputs'!$C$114/100*(1+'Inputs'!$C$109/100)*N(D33),2),0) | R33: =IF(G33="Spouse",N(D33),0) | S33: =IF(G33="Named heir",N(D33),0) | T33: =IF(AND(L33=1,N(D33)>0,E33=""),1,0) | U33: =ROUND('Workings'!$C$37*S33,2) | V33: =ROUND('Workings'!$D$37*S33,2) | W33: =IF(AND(B33="",N(D33)=0),0,IF(OR(C33="",G33=""),1,0)) | X33: =IF(S33>0,COUNTIF(S$22:S33,">0"),0) | Y33: =IF(AND(G33="Estate (residue)",H33<>"Yes",OR(C33="Shares and unit trusts",C33="Other investment",C33="Tax-free investment")),N(D33),0)
... J39: =IF(L39=1,M39-N39,"") | L39: =IF(AND(OR(C39="Property",C39="Shares and unit trusts",C39="Other investment",C39="Business interest"),NOT(OR(G39="Spouse",AND(G39="Estate (residue)",'Inputs'!$C$14="Spouse")))),1,0) | M39: =IF(L39=1,N(D39)-N(E39),0) | N39: =IF(AND(L39=1,F39="Yes",M39>0),MIN(M39,'Inputs'!$C$121),0) | O39: =IF(OR(C39="Cash and deposits",H39="Yes"),N(D39),0) | P39: =IF(C39="Property",ROUND('Inputs'!$C$113/100*N(D39),2),0) | Q39: =IF(AND(C39="Property",H39="Yes"),ROUND('Inputs'!$C$114/100*(1+'Inputs'!$C$109/100)*N(D39),2),0) | R39: =IF(G39="Spouse",N(D39),0) | S39: =IF(G39="Named heir",N(D39),0) | T39: =IF(AND(L39=1,N(D39)>0,E39=""),1,0) | U39: =ROUND('Workings'!$C$37*S39,2) | V39: =ROUND('Workings'!$D$37*S39,2) | W39: =IF(AND(B39="",N(D39)=0),0,IF(OR(C39="",G39=""),1,0)) | X39: =IF(S39>0,COUNTIF(S$22:S39,">0"),0) | Y39: =IF(AND(G39="Estate (residue)",H39<>"Yes",OR(C39="Shares and unit trusts",C39="Other investment",C39="Tax-free investment")),N(D39),0)
B40: Base cost: leave it blank only if it is not known; capital gains tax is then worked out on the full value (the worst case) and flagged below. Joint assets: enter your client's share.
B42: 3. Debts
B43: name | D43: amount | I43: notes
B44: Debt | D44: Amount (R) | I44: Notes
B56: 4. Life cover and policies paid out at death
B57: name | C57: paidTo | D57: amount | E57: counted | F57: forWhom | I57: notes
B58: Policy | C58: Paid to | D58: Paid at death (R) | E58: Counted for estate duty? | F58: For whom (a dependant in section 6, or the children's trust) | I58: Notes
L59: =IF(AND(C59="Named person",E59<>"No"),N(D59),0) | M59: =ROUND('Workings'!$C$37*L59,2) | N59: =ROUND('Workings'!$D$37*L59,2) | O59: =IF(L59>0,COUNTIF(S$22:S$39,">0")+COUNTIF(L$59:L59,">0"),0) | P59: 1 | Q59: =IF(AND(F59="The children's trust",C59<>"Estate",C59<>""),1,0) | R59: =IF(L59>0,1,0)
L60: =IF(AND(C60="Named person",E60<>"No"),N(D60),0) | M60: =ROUND('Workings'!$C$37*L60,2) | N60: =ROUND('Workings'!$D$37*L60,2) | O60: =IF(L60>0,COUNTIF(S$22:S$39,">0")+COUNTIF(L$59:L60,">0"),0) | P60: 2 | Q60: =IF(AND(F60="The children's trust",C60<>"Estate",C60<>""),1,0) | R60: =IF(L60>0,1,0)
L61: =IF(AND(C61="Named person",E61<>"No"),N(D61),0) | M61: =ROUND('Workings'!$C$37*L61,2) | N61: =ROUND('Workings'!$D$37*L61,2) | O61: =IF(L61>0,COUNTIF(S$22:S$39,">0")+COUNTIF(L$59:L61,">0"),0) | P61: 3 | Q61: =IF(AND(F61="The children's trust",C61<>"Estate",C61<>""),1,0) | R61: =IF(L61>0,1,0)
L62: =IF(AND(C62="Named person",E62<>"No"),N(D62),0) | M62: =ROUND('Workings'!$C$37*L62,2) | N62: =ROUND('Workings'!$D$37*L62,2) | O62: =IF(L62>0,COUNTIF(S$22:S$39,">0")+COUNTIF(L$59:L62,">0"),0) | P62: 4 | Q62: =IF(AND(F62="The children's trust",C62<>"Estate",C62<>""),1,0) | R62: =IF(L62>0,1,0)
L63: =IF(AND(C63="Named person",E63<>"No"),N(D63),0) | M63: =ROUND('Workings'!$C$37*L63,2) | N63: =ROUND('Workings'!$D$37*L63,2) | O63: =IF(L63>0,COUNTIF(S$22:S$39,">0")+COUNTIF(L$59:L63,">0"),0) | P63: 5 | Q63: =IF(AND(F63="The children's trust",C63<>"Estate",C63<>""),1,0) | R63: =IF(L63>0,1,0)
L64: =IF(AND(C64="Named person",E64<>"No"),N(D64),0) | M64: =ROUND('Workings'!$C$37*L64,2) | N64: =ROUND('Workings'!$D$37*L64,2) | O64: =IF(L64>0,COUNTIF(S$22:S$39,">0")+COUNTIF(L$59:L64,">0"),0) | P64: 6 | Q64: =IF(AND(F64="The children's trust",C64<>"Estate",C64<>""),1,0) | R64: =IF(L64>0,1,0)
L65: =IF(AND(C65="Named person",E65<>"No"),N(D65),0) | M65: =ROUND('Workings'!$C$37*L65,2) | N65: =ROUND('Workings'!$D$37*L65,2) | O65: =IF(L65>0,COUNTIF(S$22:S$39,">0")+COUNTIF(L$59:L65,">0"),0) | P65: 7 | Q65: =IF(AND(F65="The children's trust",C65<>"Estate",C65<>""),1,0) | R65: =IF(L65>0,1,0)
L66: =IF(AND(C66="Named person",E66<>"No"),N(D66),0) | M66: =ROUND('Workings'!$C$37*L66,2) | N66: =ROUND('Workings'!$D$37*L66,2) | O66: =IF(L66>0,COUNTIF(S$22:S$39,">0")+COUNTIF(L$59:L66,">0"),0) | P66: 8 | Q66: =IF(AND(F66="The children's trust",C66<>"Estate",C66<>""),1,0) | R66: =IF(L66>0,1,0)
L67: =IF(AND(C67="Named person",E67<>"No"),N(D67),0) | M67: =ROUND('Workings'!$C$37*L67,2) | N67: =ROUND('Workings'!$D$37*L67,2) | O67: =IF(L67>0,COUNTIF(S$22:S$39,">0")+COUNTIF(L$59:L67,">0"),0) | P67: 9 | Q67: =IF(AND(F67="The children's trust",C67<>"Estate",C67<>""),1,0) | R67: =IF(L67>0,1,0)
L68: =IF(AND(C68="Named person",E68<>"No"),N(D68),0) | M68: =ROUND('Workings'!$C$37*L68,2) | N68: =ROUND('Workings'!$D$37*L68,2) | O68: =IF(L68>0,COUNTIF(S$22:S$39,">0")+COUNTIF(L$59:L68,">0"),0) | P68: 10 | Q68: =IF(AND(F68="The children's trust",C68<>"Estate",C68<>""),1,0) | R68: =IF(L68>0,1,0)
L69: =IF(AND(C69="Named person",E69<>"No"),N(D69),0) | M69: =ROUND('Workings'!$C$37*L69,2) | N69: =ROUND('Workings'!$D$37*L69,2) | O69: =IF(L69>0,COUNTIF(S$22:S$39,">0")+COUNTIF(L$59:L69,">0"),0) | P69: 11 | Q69: =IF(AND(F69="The children's trust",C69<>"Estate",C69<>""),1,0) | R69: =IF(L69>0,1,0)
L70: =IF(AND(C70="Named person",E70<>"No"),N(D70),0) | M70: =ROUND('Workings'!$C$37*L70,2) | N70: =ROUND('Workings'!$D$37*L70,2) | O70: =IF(L70>0,COUNTIF(S$22:S$39,">0")+COUNTIF(L$59:L70,">0"),0) | P70: 12 | Q70: =IF(AND(F70="The children's trust",C70<>"Estate",C70<>""),1,0) | R70: =IF(L70>0,1,0)
B71: Paid to Estate: paid into the estate, so the executor can use it, and executor's fees are charged on it. Spouse or Named person: paid to them directly. Counted for estate duty: No only for approved group life inside a pension or provident fund. For whom: the dependant it is meant for, or the children's trust (shared like the residue); blank when the person it is paid to is not a dependant. Paid to the estate needs nothing: it reaches them through the residue.
B73: 5. Retirement funds and annuities (not in the estate, no estate duty)
B74: name | D74: value | F74: creditTo | I74: notes
B75: Retirement fund or annuity | D75: Value (R) | F75: Credited to (the fund trustees decide, s.37C) | I75: Notes | J75: To the trust, after lump sum tax
J76: =IF(F76="The children's trust",N(D76)-IF(SUMIFS('Inputs'!$D$76:$D$83,'Inputs'!$F$76:$F$83,"The children's trust")>0,ROUND((INDEX('Inputs'!$H$125:$H$128,MATCH(SUMIFS('Inputs'!$D$76:$D$83,'Inputs'!$F$76:$F$83,"The children's trust"),'Inputs'!$G$125:$G$128,1))+INDEX('Inputs'!$I$125:$I$128,MATCH(SUMIFS('Inputs'!$D$76:$D$83,'Inputs'!$F$76:$F$83,"The children's trust"),'Inputs'!$G$125:$G$128,1))/100*((SUMIFS('Inputs'!$D$76:$D$83,'Inputs'!$F$76:$F$83,"The children's trust"))-INDEX('Inputs'!$G$125:$G$128,MATCH(SUMIFS('Inputs'!$D$76:$D$83,'Inputs'!$F$76:$F$83,"The children's trust"),'Inputs'!$G$125:$G$128,1))))*N(D76)/SUMIFS('Inputs'!$D$76:$D$83,'Inputs'!$F$76:$F$83,"The children's trust"),2),0),0)
J77: =IF(F77="The children's trust",N(D77)-IF(SUMIFS('Inputs'!$D$76:$D$83,'Inputs'!$F$76:$F$83,"The children's trust")>0,ROUND((INDEX('Inputs'!$H$125:$H$128,MATCH(SUMIFS('Inputs'!$D$76:$D$83,'Inputs'!$F$76:$F$83,"The children's trust"),'Inputs'!$G$125:$G$128,1))+INDEX('Inputs'!$I$125:$I$128,MATCH(SUMIFS('Inputs'!$D$76:$D$83,'Inputs'!$F$76:$F$83,"The children's trust"),'Inputs'!$G$125:$G$128,1))/100*((SUMIFS('Inputs'!$D$76:$D$83,'Inputs'!$F$76:$F$83,"The children's trust"))-INDEX('Inputs'!$G$125:$G$128,MATCH(SUMIFS('Inputs'!$D$76:$D$83,'Inputs'!$F$76:$F$83,"The children's trust"),'Inputs'!$G$125:$G$128,1))))*N(D77)/SUMIFS('Inputs'!$D$76:$D$83,'Inputs'!$F$76:$F$83,"The children's trust"),2),0),0)
J78: =IF(F78="The children's trust",N(D78)-IF(SUMIFS('Inputs'!$D$76:$D$83,'Inputs'!$F$76:$F$83,"The children's trust")>0,ROUND((INDEX('Inputs'!$H$125:$H$128,MATCH(SUMIFS('Inputs'!$D$76:$D$83,'Inputs'!$F$76:$F$83,"The children's trust"),'Inputs'!$G$125:$G$128,1))+INDEX('Inputs'!$I$125:$I$128,MATCH(SUMIFS('Inputs'!$D$76:$D$83,'Inputs'!$F$76:$F$83,"The children's trust"),'Inputs'!$G$125:$G$128,1))/100*((SUMIFS('Inputs'!$D$76:$D$83,'Inputs'!$F$76:$F$83,"The children's trust"))-INDEX('Inputs'!$G$125:$G$128,MATCH(SUMIFS('Inputs'!$D$76:$D$83,'Inputs'!$F$76:$F$83,"The children's trust"),'Inputs'!$G$125:$G$128,1))))*N(D78)/SUMIFS('Inputs'!$D$76:$D$83,'Inputs'!$F$76:$F$83,"The children's trust"),2),0),0)
J79: =IF(F79="The children's trust",N(D79)-IF(SUMIFS('Inputs'!$D$76:$D$83,'Inputs'!$F$76:$F$83,"The children's trust")>0,ROUND((INDEX('Inputs'!$H$125:$H$128,MATCH(SUMIFS('Inputs'!$D$76:$D$83,'Inputs'!$F$76:$F$83,"The children's trust"),'Inputs'!$G$125:$G$128,1))+INDEX('Inputs'!$I$125:$I$128,MATCH(SUMIFS('Inputs'!$D$76:$D$83,'Inputs'!$F$76:$F$83,"The children's trust"),'Inputs'!$G$125:$G$128,1))/100*((SUMIFS('Inputs'!$D$76:$D$83,'Inputs'!$F$76:$F$83,"The children's trust"))-INDEX('Inputs'!$G$125:$G$128,MATCH(SUMIFS('Inputs'!$D$76:$D$83,'Inputs'!$F$76:$F$83,"The children's trust"),'Inputs'!$G$125:$G$128,1))))*N(D79)/SUMIFS('Inputs'!$D$76:$D$83,'Inputs'!$F$76:$F$83,"The children's trust"),2),0),0)
J80: =IF(F80="The children's trust",N(D80)-IF(SUMIFS('Inputs'!$D$76:$D$83,'Inputs'!$F$76:$F$83,"The children's trust")>0,ROUND((INDEX('Inputs'!$H$125:$H$128,MATCH(SUMIFS('Inputs'!$D$76:$D$83,'Inputs'!$F$76:$F$83,"The children's trust"),'Inputs'!$G$125:$G$128,1))+INDEX('Inputs'!$I$125:$I$128,MATCH(SUMIFS('Inputs'!$D$76:$D$83,'Inputs'!$F$76:$F$83,"The children's trust"),'Inputs'!$G$125:$G$128,1))/100*((SUMIFS('Inputs'!$D$76:$D$83,'Inputs'!$F$76:$F$83,"The children's trust"))-INDEX('Inputs'!$G$125:$G$128,MATCH(SUMIFS('Inputs'!$D$76:$D$83,'Inputs'!$F$76:$F$83,"The children's trust"),'Inputs'!$G$125:$G$128,1))))*N(D80)/SUMIFS('Inputs'!$D$76:$D$83,'Inputs'!$F$76:$F$83,"The children's trust"),2),0),0)
J81: =IF(F81="The children's trust",N(D81)-IF(SUMIFS('Inputs'!$D$76:$D$83,'Inputs'!$F$76:$F$83,"The children's trust")>0,ROUND((INDEX('Inputs'!$H$125:$H$128,MATCH(SUMIFS('Inputs'!$D$76:$D$83,'Inputs'!$F$76:$F$83,"The children's trust"),'Inputs'!$G$125:$G$128,1))+INDEX('Inputs'!$I$125:$I$128,MATCH(SUMIFS('Inputs'!$D$76:$D$83,'Inputs'!$F$76:$F$83,"The children's trust"),'Inputs'!$G$125:$G$128,1))/100*((SUMIFS('Inputs'!$D$76:$D$83,'Inputs'!$F$76:$F$83,"The children's trust"))-INDEX('Inputs'!$G$125:$G$128,MATCH(SUMIFS('Inputs'!$D$76:$D$83,'Inputs'!$F$76:$F$83,"The children's trust"),'Inputs'!$G$125:$G$128,1))))*N(D81)/SUMIFS('Inputs'!$D$76:$D$83,'Inputs'!$F$76:$F$83,"The children's trust"),2),0),0)
J82: =IF(F82="The children's trust",N(D82)-IF(SUMIFS('Inputs'!$D$76:$D$83,'Inputs'!$F$76:$F$83,"The children's trust")>0,ROUND((INDEX('Inputs'!$H$125:$H$128,MATCH(SUMIFS('Inputs'!$D$76:$D$83,'Inputs'!$F$76:$F$83,"The children's trust"),'Inputs'!$G$125:$G$128,1))+INDEX('Inputs'!$I$125:$I$128,MATCH(SUMIFS('Inputs'!$D$76:$D$83,'Inputs'!$F$76:$F$83,"The children's trust"),'Inputs'!$G$125:$G$128,1))/100*((SUMIFS('Inputs'!$D$76:$D$83,'Inputs'!$F$76:$F$83,"The children's trust"))-INDEX('Inputs'!$G$125:$G$128,MATCH(SUMIFS('Inputs'!$D$76:$D$83,'Inputs'!$F$76:$F$83,"The children's trust"),'Inputs'!$G$125:$G$128,1))))*N(D82)/SUMIFS('Inputs'!$D$76:$D$83,'Inputs'!$F$76:$F$83,"The children's trust"),2),0),0)
J83: =IF(F83="The children's trust",N(D83)-IF(SUMIFS('Inputs'!$D$76:$D$83,'Inputs'!$F$76:$F$83,"The children's trust")>0,ROUND((INDEX('Inputs'!$H$125:$H$128,MATCH(SUMIFS('Inputs'!$D$76:$D$83,'Inputs'!$F$76:$F$83,"The children's trust"),'Inputs'!$G$125:$G$128,1))+INDEX('Inputs'!$I$125:$I$128,MATCH(SUMIFS('Inputs'!$D$76:$D$83,'Inputs'!$F$76:$F$83,"The children's trust"),'Inputs'!$G$125:$G$128,1))/100*((SUMIFS('Inputs'!$D$76:$D$83,'Inputs'!$F$76:$F$83,"The children's trust"))-INDEX('Inputs'!$G$125:$G$128,MATCH(SUMIFS('Inputs'!$D$76:$D$83,'Inputs'!$F$76:$F$83,"The children's trust"),'Inputs'!$G$125:$G$128,1))))*N(D83)/SUMIFS('Inputs'!$D$76:$D$83,'Inputs'!$F$76:$F$83,"The children's trust"),2),0),0)
B84: Credited to: who the fund trustees are expected to pay. They must look after dependants first (s.37C), so where the nominee is not a dependant the CRM proposes the children. Blank: not counted for any dependant.
B86: 6. The people who depend on your client
B87: name | C87: rel | D87: age | E87: needPM | F87: years | G87: esc | H87: trust | I87: other
B88: Name | C88: Relationship | D88: Age | E88: Needs a month from this money (R, after tax) | F88: For how many years | G88: Rising each year by (%, blank: inflation) | H88: Held in a trust? | I88: Their own taxable income (R a year) | Z88: The children's trust
L89: =IF(AND(B89<>"",C89="Child"),1,0) | M89: =IF(L89=1,SUM(L$89:L89),0) | N89: =IF(AND(L89=1,M89=SUM(L$89:L$94)),1,0) | O89: =IF(AND(B89<>"",C89="Spouse",COUNTIF(C$89:C89,"Spouse")=1),1,0) | P89: =IF(B89="",0,IF(OR(C89="",N(E89)<=0,N(F89)<=0),1,0)) | Q89: =IF(AND(L89=1,H89="Yes"),1,0) | R89: =IF(Q89=1,SUM(Q$89:Q89),0) | S89: =IF(AND(Q89=1,R89=SUM(Q$89:Q$94)),1,0) | Z89: =IF(B89="","",B89)
L90: =IF(AND(B90<>"",C90="Child"),1,0) | M90: =IF(L90=1,SUM(L$89:L90),0) | N90: =IF(AND(L90=1,M90=SUM(L$89:L$94)),1,0) | O90: =IF(AND(B90<>"",C90="Spouse",COUNTIF(C$89:C90,"Spouse")=1),1,0) | P90: =IF(B90="",0,IF(OR(C90="",N(E90)<=0,N(F90)<=0),1,0)) | Q90: =IF(AND(L90=1,H90="Yes"),1,0) | R90: =IF(Q90=1,SUM(Q$89:Q90),0) | S90: =IF(AND(Q90=1,R90=SUM(Q$89:Q$94)),1,0) | Z90: =IF(B90="","",B90)
L91: =IF(AND(B91<>"",C91="Child"),1,0) | M91: =IF(L91=1,SUM(L$89:L91),0) | N91: =IF(AND(L91=1,M91=SUM(L$89:L$94)),1,0) | O91: =IF(AND(B91<>"",C91="Spouse",COUNTIF(C$89:C91,"Spouse")=1),1,0) | P91: =IF(B91="",0,IF(OR(C91="",N(E91)<=0,N(F91)<=0),1,0)) | Q91: =IF(AND(L91=1,H91="Yes"),1,0) | R91: =IF(Q91=1,SUM(Q$89:Q91),0) | S91: =IF(AND(Q91=1,R91=SUM(Q$89:Q$94)),1,0) | Z91: =IF(B91="","",B91)
L92: =IF(AND(B92<>"",C92="Child"),1,0) | M92: =IF(L92=1,SUM(L$89:L92),0) | N92: =IF(AND(L92=1,M92=SUM(L$89:L$94)),1,0) | O92: =IF(AND(B92<>"",C92="Spouse",COUNTIF(C$89:C92,"Spouse")=1),1,0) | P92: =IF(B92="",0,IF(OR(C92="",N(E92)<=0,N(F92)<=0),1,0)) | Q92: =IF(AND(L92=1,H92="Yes"),1,0) | R92: =IF(Q92=1,SUM(Q$89:Q92),0) | S92: =IF(AND(Q92=1,R92=SUM(Q$89:Q$94)),1,0) | Z92: =IF(B92="","",B92)
L93: =IF(AND(B93<>"",C93="Child"),1,0) | M93: =IF(L93=1,SUM(L$89:L93),0) | N93: =IF(AND(L93=1,M93=SUM(L$89:L$94)),1,0) | O93: =IF(AND(B93<>"",C93="Spouse",COUNTIF(C$89:C93,"Spouse")=1),1,0) | P93: =IF(B93="",0,IF(OR(C93="",N(E93)<=0,N(F93)<=0),1,0)) | Q93: =IF(AND(L93=1,H93="Yes"),1,0) | R93: =IF(Q93=1,SUM(Q$89:Q93),0) | S93: =IF(AND(Q93=1,R93=SUM(Q$89:Q$94)),1,0) | Z93: =IF(B93="","",B93)
L94: =IF(AND(B94<>"",C94="Child"),1,0) | M94: =IF(L94=1,SUM(L$89:L94),0) | N94: =IF(AND(L94=1,M94=SUM(L$89:L$94)),1,0) | O94: =IF(AND(B94<>"",C94="Spouse",COUNTIF(C$89:C94,"Spouse")=1),1,0) | P94: =IF(B94="",0,IF(OR(C94="",N(E94)<=0,N(F94)<=0),1,0)) | Q94: =IF(AND(L94=1,H94="Yes"),1,0) | R94: =IF(Q94=1,SUM(Q$89:Q94),0) | S94: =IF(AND(Q94=1,R94=SUM(Q$89:Q$94)),1,0) | Z94: =IF(B94="","",B94)
B95: When the residue goes to heirs (not the spouse), the children receive it
B96: Needs a month: what must come from this money, after tax. If they earn, enter only the part their own income does not cover; their own income is used for the tax on what the capital earns. The children share the residue and anything for the children's trust in the order listed (the youngest last gets the odd cent). A spouse receives the residue when it goes to the spouse.
B98: 7. Capital Legacy quote (the second column)
B99: Quote number
B100: Capital Legacy executor's fee, before VAT (%)
B101: Conveyancing estimate (R)
B102: The plan pays (% of the fees)
B103: Limit the plan pays today (R)
B104: Premium, first year (R a month)
B105: Leave the quote blank and the second column stays empty. The plan pays its share of Capital Legacy's executor's fee and the conveyancing, up to the limit; it does not pay capital gains tax or estate duty.
B107: 8. Standard assumptions (change them only for this client)
B108: Executor's fee, before VAT (%) | C108: 3.5 | E108: Trustee fees while in a trust (% a year) | H108: 2
B109: VAT (%) | C109: 15 | E109: Tax threshold, under 65 (R) | H109: 99000
B110: Master's fees (R) | C110: 7000 | E110: Unit trust return: interest part (%) | H110: 52.5
B111: Funeral (R) | C111: 50000 | E111: Unit trust return: dividends part (%) | H111: 11.25
B112: Estate sundries (R) | C112: 8000 | E112: Unit trust return: growth part (%) | H112: 36.25
B113: Property transfer costs (% of value) | C113: 1 | E113: Dividends tax (%) | H113: 20
B114: Agent's commission on a property sold, before VAT (%) | C114: 7.5 | E114: Inflation, when a need gives no increase (%) | H114: 4
B115: Estate duty abatement (R) | C115: 3500000 | E115: Living annuity: lowest drawdown (% a year) | H115: 2.5
B116: Estate duty rate (%) | C116: 20 | E116: Living annuity: highest drawdown (% a year) | H116: 17.5
B117: Higher rate applies above (R) | C117: 30000000 | E117: Primary rebate (R) | H117: 17820
B118: Higher estate duty rate (%) | C118: 25 | E118: Secondary rebate, 65 and older (R) | H118: 9765
B119: Capital gains exclusion in the year of death (R) | C119: 440000 | E119: Tertiary rebate, 75 and older (R) | H119: 3249
... B121: Primary residence exclusion (R) | C121: 3000000 | E121: Tax threshold, 75 and older (R) | H121: 171300
B122: Return on capital, after fees, before tax (%) | C122: 7
B124: Income tax table, 2027 tax year | C124: Taxable income over (R) | D124: Tax on that (R) | E124: Rate above it (%) | G124: Lump sum table, death benefits
C125: 0 | D125: 0 | E125: 18 | G125: 0 | H125: 0 | I125: 0
C126: 245100 | D126: 44118 | E126: 26 | G126: 550000 | H126: 0 | I126: 18
C127: 383100 | D127: 79998 | E127: 31 | G127: 770000 | H127: 39600 | I127: 27
C128: 530200 | D128: 125599 | E128: 36 | G128: 1155000 | H128: 143550 | I128: 36
C129: 695800 | D129: 185215 | E129: 39
...

Sheet Summary
B1: Duwalcoe Financial Consultants CC
B2: FSP 9978 | clinton@duwalcoe.co.za | 083 608 5617
B3: =IF(OR(COUNTIF('Inputs'!$B$143:$B$156,"✗ Full FNA*")>0,LEFT('Inputs'!$B$138,1)="✗"),"NOT FOR THE CLIENT: this case needs the full FNA (see Checks on Inputs)","")
B4: Cost of dying
B5: ="Prepared for "&'Inputs'!$C$8&" by "&'Inputs'!$C$10&" · "&IF(ISNUMBER('Inputs'!$C$11),FIXED(DAY('Inputs'!$C$11),0)&" "&CHOOSE(MONTH('Inputs'!$C$11),"January","February","March","April","May","June","July","August","September","October","November","December")&" "&FIXED(YEAR('Inputs'!$C$11),0,TRUE),"")
B7: =IF('Inputs'!$C$15<>"",TRIM('Inputs'!$C$15)&" ","")&"If you died today, winding up your estate would cost about R "&FIXED(('Workings'!$C$56)/1000000,2)&" million"&IF('Workings'!$C$59>0,", and your debts of R "&FIXED(('Workings'!$C$59)/1000000,2)&" million have to be paid too","")&". Your executor would have R "&FIXED(('Workings'!$C$63)/1000000,2)&" million in cash, so "&IF('Workings'!$C$64>0,"would be short by about R "&FIXED(('Workings'!$C$64)/1000000,2)&" million.","would have enough, with about R "&FIXED(ROUND('Workings'!$C$65,-3),0)&" left over.")
B8: =IF(AND(ISNUMBER('Inputs'!$C$100),'Inputs'!$C$100>0),"With a Capital Legacy will and the Legacy Protection Plan, the plan pays about R "&FIXED(ROUND(-'Workings'!$D$57,-3),0)&" of the executor's and conveyancing fees, "&IF('Workings'!$D$64=0,IF('Workings'!$C$64>0,"the shortfall disappears","your executor still has enough"),"the shortfall falls to about R "&FIXED(ROUND('Workings'!$D$64,-3),0))&", and your heirs receive about R "&FIXED(('Workings'!$D$66-'Workings'!$C$66)/1000000,2)&" million more.","")
B10: =IF('Workings'!$C$64>0,"YOUR EXECUTOR'S CASH SHORTFALL TODAY","CASH LEFT OVER FOR YOUR EXECUTOR TODAY")
B11: ="R "&FIXED(ROUND(IF('Workings'!$C$64>0,'Workings'!$C$64,'Workings'!$C$65),-3),0)
B12: =IF('Workings'!$C$64>0,"the cash that has to be found before your estate can be wound up","what is left once the costs are paid")
C14: Today | D14: =IF(AND(ISNUMBER('Inputs'!$C$100),'Inputs'!$C$100>0),"With a Capital Legacy will and the Legacy Protection Plan","Capital Legacy column: enter the quote on Inputs")
B15: Estate duty | C15: ='Workings'!$C$55 | D15: =IF(AND(ISNUMBER('Inputs'!$C$100),'Inputs'!$C$100>0),'Workings'!$D$55,"")
B16: Capital gains tax | C16: ='Workings'!$C$54 | D16: =IF(AND(ISNUMBER('Inputs'!$C$100),'Inputs'!$C$100>0),'Workings'!$D$54,"")
B17: ="Executor's fees"&CHAR(10)&IF(ROUND('Inputs'!$C$108,0)='Inputs'!$C$108,FIXED('Inputs'!$C$108,0),IF(ROUND('Inputs'!$C$108,1)='Inputs'!$C$108,FIXED('Inputs'!$C$108,1),FIXED('Inputs'!$C$108,2)))&"%"&" plus VAT"&IF(AND(ISNUMBER('Inputs'!$C$100),'Inputs'!$C$100>0)," / Capital Legacy "&IF(ROUND('Inputs'!$C$100,0)='Inputs'!$C$100,FIXED('Inputs'!$C$100,0),IF(ROUND('Inputs'!$C$100,1)='Inputs'!$C$100,FIXED('Inputs'!$C$100,1),FIXED('Inputs'!$C$100,2)))&"%"&" plus VAT","") | C17: ='Workings'!$C$51 | D17: =IF(AND(ISNUMBER('Inputs'!$C$100),'Inputs'!$C$100>0),'Workings'!$D$51,"")
B18: ="Property transfer and conveyancing"&CHAR(10)&IF(ROUND('Inputs'!$C$113,0)='Inputs'!$C$113,FIXED('Inputs'!$C$113,0),IF(ROUND('Inputs'!$C$113,1)='Inputs'!$C$113,FIXED('Inputs'!$C$113,1),FIXED('Inputs'!$C$113,2)))&"%"&" of value"&IF(AND(ISNUMBER('Inputs'!$C$100),'Inputs'!$C$100>0)," / Capital Legacy's estimate","") | C18: ='Workings'!$C$52 | D18: =IF(AND(ISNUMBER('Inputs'!$C$100),'Inputs'!$C$100>0),'Workings'!$D$52,"")
B19: Agent's commission | C19: ='Workings'!$C$53 | D19: =IF(AND(ISNUMBER('Inputs'!$C$100),'Inputs'!$C$100>0),'Workings'!$D$53,"")
B20: Funeral, Master's fees and sundries | C20: ='Workings'!$C$50 | D20: =IF(AND(ISNUMBER('Inputs'!$C$100),'Inputs'!$C$100>0),'Workings'!$D$50,"")
B21: Cost of winding up | C21: ='Workings'!$C$56 | D21: =IF(AND(ISNUMBER('Inputs'!$C$100),'Inputs'!$C$100>0),'Workings'!$D$56,"")
B22: Paid by the Legacy plan | C22: =-'Workings'!$C$57 | D22: =IF(AND(ISNUMBER('Inputs'!$C$100),'Inputs'!$C$100>0),-'Workings'!$D$57,"")
B23: Paid by your estate | C23: ='Workings'!$C$58 | D23: =IF(AND(ISNUMBER('Inputs'!$C$100),'Inputs'!$C$100>0),'Workings'!$D$58,"")
B24: Debts | C24: ='Workings'!$C$59 | D24: =IF(AND(ISNUMBER('Inputs'!$C$100),'Inputs'!$C$100>0),'Workings'!$D$59,"")
B25: ="Cash your executor has"&CHAR(10)&"bank accounts, deposits and investments cashed in" | C25: ='Workings'!$C$63 | D25: =IF(AND(ISNUMBER('Inputs'!$C$100),'Inputs'!$C$100>0),'Workings'!$D$63,"")
B26: Shortfall, or cash left over | C26: =IF('Workings'!$C$64>0,"Short R "&FIXED(ROUND('Workings'!$C$64,-3),0),"Covered: R "&FIXED(ROUND('Workings'!$C$65,-3),0)&" left over") | D26: =IF(AND(ISNUMBER('Inputs'!$C$100),'Inputs'!$C$100>0),IF('Workings'!$D$64>0,"Short R "&FIXED(ROUND('Workings'!$D$64,-3),0),"Covered: R "&FIXED(ROUND('Workings'!$D$65,-3),0)&" left over"),"")
B27: =IF(OR(SUM('Inputs'!$R$22:$R$39)>0,'Inputs'!$C$14="Spouse"),"Left for your spouse and heirs","Left for your heirs")&CHAR(10)&"if they pay any shortfall in" | C27: ='Workings'!$C$66 | D27: =IF(AND(ISNUMBER('Inputs'!$C$100),'Inputs'!$C$100>0),'Workings'!$D$66,"")
B28: Cost to you | C28: None | D28: =IF(AND(ISNUMBER('Inputs'!$C$100),'Inputs'!$C$100>0),IF(ISNUMBER('Inputs'!$C$104),"From R "&FIXED('Inputs'!$C$104,2)&" a month","Premium: enter it on Inputs"),"")
B29: =IF('Workings'!$C$45<0,"The people you leave policies or bequests to directly pay R "&FIXED(-'Workings'!$C$45,0)&" of the estate duty themselves; your executor recovers it from them and it is not in the cost above. If it cannot be recovered, your estate pays it.","")
B31: Next steps to discuss
B32: ="1. Sign a new will that says what you want"&IF(AND(ISNUMBER('Inputs'!$C$100),'Inputs'!$C$100>0),", with Capital Legacy as your executor","")&". Until you do, your current will, or the law if you have none, decides who inherits."
B33: ="2. "&IF('Workings'!$C$64>0,"Decide how your executor will find the cash: "&IF(AND(ISNUMBER('Inputs'!$C$100),'Inputs'!$C$100>0),"the Legacy Protection Plan, ","")&"a property sold, or your heirs paying it in.","Keep enough cash for your executor: today there is enough, with about R "&FIXED(ROUND('Workings'!$C$65,-3),0)&" to spare.")
B34: ="3. Remember that your savings are your executor's cash. Every R 1 spent from them "&IF('Workings'!$C$64>0,"adds about "&ROUND(100*(1-'Inputs'!$C$108/100*(1+'Inputs'!$C$109/100))*IF('Workings'!$C$35>0,1-'Inputs'!$C$116/100,1),0)&" cents to the shortfall.","takes about "&ROUND(100*(1-'Inputs'!$C$108/100*(1+'Inputs'!$C$109/100))*IF('Workings'!$C$35>0,1-'Inputs'!$C$116/100,1),0)&" cents off what your executor has spare.")
B36: ="Basis: indicative and worst case, based on your instructed wishes, not a signed will, and on the values you gave us"&IF(ISNUMBER('Inputs'!$C$12)," on "&FIXED(DAY('Inputs'!$C$12),0)&" "&CHOOSE(MONTH('Inputs'!$C$12),"January","February","March","April","May","June","July","August","September","October","November","December")&" "&FIXED(YEAR('Inputs'!$C$12),0,TRUE),"")&". Our standard assumptions are on the Workings page."&IF(AND(ISNUMBER('Inputs'!$C$100),'Inputs'!$C$100>0)," Capital Legacy quote "&'Inputs'!$C$99&"; premiums rise each year and are not guaranteed.","")&" Figures are for your death today. Not legal or tax advice; the executor's actual costs may differ."

Sheet Life cover need
B1: Duwalcoe Financial Consultants CC
B2: FSP 9978 | clinton@duwalcoe.co.za | 083 608 5617
B3: =IF(OR(COUNTIF('Inputs'!$B$143:$B$156,"✗ Full FNA*")>0,LEFT('Inputs'!$B$138,1)="✗"),"NOT FOR THE CLIENT: this case needs the full FNA (see Checks on Inputs)","")
B4: Life cover need
B5: ="Prepared for "&'Inputs'!$C$8&" by "&'Inputs'!$C$10&" · "&IF(ISNUMBER('Inputs'!$C$11),FIXED(DAY('Inputs'!$C$11),0)&" "&CHOOSE(MONTH('Inputs'!$C$11),"January","February","March","April","May","June","July","August","September","October","November","December")&" "&FIXED(YEAR('Inputs'!$C$11),0,TRUE),"")
B7: =IF(COUNTIF('Inputs'!$B$89:$B$94,"?*")=0,"No one who depends on you is recorded, so there is no income need to cover.","If you died today, "&IF((('Needs calc'!$C$51>0)+('Needs calc'!$C$58>0)+('Needs calc'!$C$65>0)+('Needs calc'!$C$72>0)+('Needs calc'!$C$79>0)+('Needs calc'!$C$86>0)+('Needs calc'!$C$91>0))=0,"everyone who depends on you would have the income you want for them"&IF('Needs calc'!$C$4=1,", with the trust sharing by need as one family pot","")&".",IF('Needs calc'!$C$51>0,'Inputs'!$B$89&" would have about R "&FIXED(ROUND('Needs calc'!$C$52,-2),0)&" a month of the R "&FIXED(ROUND('Inputs'!$E$89,-2),0)&" you want. ","")&IF('Needs calc'!$C$58>0,'Inputs'!$B$90&" would have about R "&FIXED(ROUND('Needs calc'!$C$59,-2),0)&" a month of the R "&FIXED(ROUND('Inputs'!$E$90,-2),0)&" you want. ","")&IF('Needs calc'!$C$65>0,'Inputs'!$B$91&" would have about R "&FIXED(ROUND('Needs calc'!$C$66,-2),0)&" a month of the R "&FIXED(ROUND('Inputs'!$E$91,-2),0)&" you want. ","")&IF('Needs calc'!$C$72>0,'Inputs'!$B$92&" would have about R "&FIXED(ROUND('Needs calc'!$C$73,-2),0)&" a month of the R "&FIXED(ROUND('Inputs'!$E$92,-2),0)&" you want. ","")&IF('Needs calc'!$C$79>0,'Inputs'!$B$93&" would have about R "&FIXED(ROUND('Needs calc'!$C$80,-2),0)&" a month of the R "&FIXED(ROUND('Inputs'!$E$93,-2),0)&" you want. ","")&IF('Needs calc'!$C$86>0,'Inputs'!$B$94&" would have about R "&FIXED(ROUND('Needs calc'!$C$87,-2),0)&" a month of the R "&FIXED(ROUND('Inputs'!$E$94,-2),0)&" you want. ","")&IF('Needs calc'!$C$91>0,"The family pot would be short by R "&FIXED(ROUND('Needs calc'!$C$91,-3),0)&". ","")&IF((('Needs calc'!$C$51>0)+('Needs calc'!$C$58>0)+('Needs calc'!$C$65>0)+('Needs calc'!$C$72>0)+('Needs calc'!$C$79>0)+('Needs calc'!$C$86>0)+('Needs calc'!$C$91>0))<COUNTIF('Inputs'!$B$89:$B$94,"?*"),"Everyone else is provided for.","")))
B8: =IF('Workings'!$C$64>0,"Your estate itself would be short of cash by about R "&FIXED(ROUND('Workings'!$C$64,-3),0)&" to pay its debts and costs.","Your estate itself has enough cash to pay its debts and costs, with about R "&FIXED(ROUND('Workings'!$C$65,-3),0)&" left over for your heirs.")
B10: =IF(('Needs calc'!$T$7+'Needs calc'!$T$8+'Needs calc'!$T$9+'Needs calc'!$T$10+'Needs calc'!$T$11+'Needs calc'!$T$12+'Needs calc'!$T$13)>0,"LIFE COVER TO CLOSE THE GAPS","EVERYONE WHO DEPENDS ON YOU IS PROVIDED FOR")
B11: =IF(('Needs calc'!$T$7+'Needs calc'!$T$8+'Needs calc'!$T$9+'Needs calc'!$T$10+'Needs calc'!$T$11+'Needs calc'!$T$12+'Needs calc'!$T$13)>0,"R "&FIXED(ROUND(('Needs calc'!$T$7+'Needs calc'!$T$8+'Needs calc'!$T$9+'Needs calc'!$T$10+'Needs calc'!$T$11+'Needs calc'!$T$12+'Needs calc'!$T$13),-3),0),"No new cover needed")
B12: =IF(('Needs calc'!$T$7+'Needs calc'!$T$8+'Needs calc'!$T$9+'Needs calc'!$T$10+'Needs calc'!$T$11+'Needs calc'!$T$12+'Needs calc'!$T$13)>0,"new cover nominated for the people who are short, after the estate duty it brings","on the needs you gave us, as your policies and will instructions stand today")
B14: Your estate (the cost of dying)
B15: Cash the executor needs | C15: ='Workings'!$C$60
B16: Cash the executor has | C16: ='Workings'!$C$63
B17: Result | C17: =IF('Workings'!$C$64>0,"Short R "&FIXED(ROUND('Workings'!$C$64,-3),0)&". To close it: R "&FIXED(ROUND('Needs years'!$C$377,-3),0)&" of cover paid to your estate"&IF(OR(LEFT('Inputs'!$C$13,7)="Married",'Inputs'!$C$13="Life partner",'Inputs'!$C$13="Civil Union")," or R "&FIXED(ROUND('Workings'!$C$64,-3),0)&" nominated to your spouse, who pays it in","")&".","Covered: R "&FIXED(ROUND('Workings'!$C$65,-3),0)&" left for your heirs")
B19: The people who depend on you | C19: =IF('Inputs'!$B$89="","",'Inputs'!$B$89) | D19: =IF('Inputs'!$B$90="","",'Inputs'!$B$90) | E19: =IF('Inputs'!$B$91="","",'Inputs'!$B$91) | F19: =IF('Inputs'!$B$92="","",'Inputs'!$B$92)
B20: You want for them, a month | C20: =IF('Inputs'!$B$89="","",N('Inputs'!$E$89)) | D20: =IF('Inputs'!$B$90="","",N('Inputs'!$E$90)) | E20: =IF('Inputs'!$B$91="","",N('Inputs'!$E$91)) | F20: =IF('Inputs'!$B$92="","",N('Inputs'!$E$92))
B21: For | C21: =IF('Inputs'!$B$89="","",'Needs years'!$C$8&" years") | D21: =IF('Inputs'!$B$90="","",'Needs years'!$C$64&" years") | E21: =IF('Inputs'!$B$91="","",'Needs years'!$C$120&" years") | F21: =IF('Inputs'!$B$92="","",'Needs years'!$C$176&" years")
B22: Rising each year by | C22: =IF('Inputs'!$B$89="","",'Needs years'!$C$10) | D22: =IF('Inputs'!$B$90="","",'Needs years'!$C$66) | E22: =IF('Inputs'!$B$91="","",'Needs years'!$C$122) | F22: =IF('Inputs'!$B$92="","",'Needs years'!$C$178)
B23: Capital needed today | C23: =IF('Inputs'!$B$89="","",IF(AND('Needs calc'!$C$4=1,'Inputs'!$Q$89=1),'Needs calc'!$C$50,'Needs years'!$C$7+'Needs calc'!$C$50)) | D23: =IF('Inputs'!$B$90="","",IF(AND('Needs calc'!$C$4=1,'Inputs'!$Q$90=1),'Needs calc'!$C$57,'Needs years'!$C$63+'Needs calc'!$C$57)) | E23: =IF('Inputs'!$B$91="","",IF(AND('Needs calc'!$C$4=1,'Inputs'!$Q$91=1),'Needs calc'!$C$64,'Needs years'!$C$119+'Needs calc'!$C$64)) | F23: =IF('Inputs'!$B$92="","",IF(AND('Needs calc'!$C$4=1,'Inputs'!$Q$92=1),'Needs calc'!$C$71,'Needs years'!$C$175+'Needs calc'!$C$71))
B24: Retirement money (a living annuity for them) | C24: =IF('Inputs'!$B$89="","",'Needs years'!$C$7) | D24: =IF('Inputs'!$B$90="","",'Needs years'!$C$63) | E24: =IF('Inputs'!$B$91="","",'Needs years'!$C$119) | F24: =IF('Inputs'!$B$92="","",'Needs years'!$C$175)
B25: From your estate, policies and the trust | C25: =IF('Inputs'!$B$89="","",'Needs calc'!$C$46) | D25: =IF('Inputs'!$B$90="","",'Needs calc'!$C$53) | E25: =IF('Inputs'!$B$91="","",'Needs calc'!$C$60) | F25: =IF('Inputs'!$B$92="","",'Needs calc'!$C$67)
B26: Capital in place | C26: =IF('Inputs'!$B$89="","",IF(AND('Needs calc'!$C$4=1,'Inputs'!$Q$89=1),'Needs calc'!$C$50,'Needs years'!$C$7+'Needs calc'!$C$46)) | D26: =IF('Inputs'!$B$90="","",IF(AND('Needs calc'!$C$4=1,'Inputs'!$Q$90=1),'Needs calc'!$C$57,'Needs years'!$C$63+'Needs calc'!$C$53)) | E26: =IF('Inputs'!$B$91="","",IF(AND('Needs calc'!$C$4=1,'Inputs'!$Q$91=1),'Needs calc'!$C$64,'Needs years'!$C$119+'Needs calc'!$C$60)) | F26: =IF('Inputs'!$B$92="","",IF(AND('Needs calc'!$C$4=1,'Inputs'!$Q$92=1),'Needs calc'!$C$71,'Needs years'!$C$175+'Needs calc'!$C$67))
B27: Monthly income it pays | C27: =IF('Inputs'!$B$89="","",'Needs calc'!$C$52) | D27: =IF('Inputs'!$B$90="","",'Needs calc'!$C$59) | E27: =IF('Inputs'!$B$91="","",'Needs calc'!$C$66) | F27: =IF('Inputs'!$B$92="","",'Needs calc'!$C$73)
B28: Shortfall, or over | C28: =IF('Inputs'!$B$89="","",IF(AND('Needs calc'!$C$4=1,'Inputs'!$Q$89=1),IF('Needs calc'!$C$90>=0,"Covered by the pot","Pot short"),IF('Needs calc'!$C$51>0,"Short R "&FIXED(ROUND('Needs calc'!$C$51,-3),0),IF('Needs calc'!$C$51<0,"R "&FIXED(ROUND(-'Needs calc'!$C$51,-3),0)&" over","Covered")))) | D28: =IF('Inputs'!$B$90="","",IF(AND('Needs calc'!$C$4=1,'Inputs'!$Q$90=1),IF('Needs calc'!$C$90>=0,"Covered by the pot","Pot short"),IF('Needs calc'!$C$58>0,"Short R "&FIXED(ROUND('Needs calc'!$C$58,-3),0),IF('Needs calc'!$C$58<0,"R "&FIXED(ROUND(-'Needs calc'!$C$58,-3),0)&" over","Covered")))) | E28: =IF('Inputs'!$B$91="","",IF(AND('Needs calc'!$C$4=1,'Inputs'!$Q$91=1),IF('Needs calc'!$C$90>=0,"Covered by the pot","Pot short"),IF('Needs calc'!$C$65>0,"Short R "&FIXED(ROUND('Needs calc'!$C$65,-3),0),IF('Needs calc'!$C$65<0,"R "&FIXED(ROUND(-'Needs calc'!$C$65,-3),0)&" over","Covered")))) | F28: =IF('Inputs'!$B$92="","",IF(AND('Needs calc'!$C$4=1,'Inputs'!$Q$92=1),IF('Needs calc'!$C$90>=0,"Covered by the pot","Pot short"),IF('Needs calc'!$C$72>0,"Short R "&FIXED(ROUND('Needs calc'!$C$72,-3),0),IF('Needs calc'!$C$72<0,"R "&FIXED(ROUND(-'Needs calc'!$C$72,-3),0)&" over","Covered"))))
B29: New life cover to close the gap | C29: =IF('Inputs'!$B$89="","",IF('Needs calc'!$T$7>0,'Needs calc'!$T$7,"None needed")) | D29: =IF('Inputs'!$B$90="","",IF('Needs calc'!$T$8>0,'Needs calc'!$T$8,"None needed")) | E29: =IF('Inputs'!$B$91="","",IF('Needs calc'!$T$9>0,'Needs calc'!$T$9,"None needed")) | F29: =IF('Inputs'!$B$92="","",IF('Needs calc'!$T$10>0,'Needs calc'!$T$10,"None needed"))
B30: =IF('Needs calc'!$C$4=1,"The trust shares by need as one family pot: R "&FIXED(ROUND('Needs calc'!$C$88,-3),0)&" in the pot, R "&FIXED(ROUND('Needs calc'!$C$89,-3),0)&" needed for the children, "&IF('Needs calc'!$C$90>=0,"R "&FIXED(ROUND('Needs calc'!$C$90,-3),0)&" left to share equally at the end.","short by R "&FIXED(ROUND(-'Needs calc'!$C$90,-3),0)&"."),"")&IF(COUNTIF('Inputs'!$B$89:$B$94,"?*")>4," The others who depend on you are on the workings page.","")
B31: =IF('Needs calc'!$C$44>0,"Life cover of R "&FIXED(ROUND('Needs calc'!$C$44,-3),0)&" is paid directly to "&IF(SUMPRODUCT('Inputs'!$R$59:$R$70*('Inputs'!$F$59:$F$70="")*('Inputs'!$D$59:$D$70>0))=1,"someone who is","people who are")&" not recorded as depending on you; they pay R "&FIXED(ROUND('Needs calc'!$C$45,-3),0)&" of the estate duty on it, and it is not counted for anyone above.","")
B33: =IF(SUMPRODUCT(('Inputs'!$H$89:$H$94="Yes")*('Inputs'!$B$89:$B$94<>""))>0,"What the trust will cost (trustee fees of "&IF(ROUND('Inputs'!$H$108,0)='Inputs'!$H$108,FIXED('Inputs'!$H$108,0),IF(ROUND('Inputs'!$H$108,1)='Inputs'!$H$108,FIXED('Inputs'!$H$108,1),FIXED('Inputs'!$H$108,2)))&"%"&" a year)","") | C33: =IF('Inputs'!$H$89="Yes",'Inputs'!$B$89,"") | D33: =IF('Inputs'!$H$90="Yes",'Inputs'!$B$90,"") | E33: =IF('Inputs'!$H$91="Yes",'Inputs'!$B$91,"") | F33: =IF('Inputs'!$H$92="Yes",'Inputs'!$B$92,"")
B34: =IF(SUMPRODUCT(('Inputs'!$H$89:$H$94="Yes")*('Inputs'!$B$89:$B$94<>""))>0,"First year","") | C34: =IF('Inputs'!$H$89="Yes",'Needs years'!$C$17,"") | D34: =IF('Inputs'!$H$90="Yes",'Needs years'!$C$73,"") | E34: =IF('Inputs'!$H$91="Yes",'Needs years'!$C$129,"") | F34: =IF('Inputs'!$H$92="Yes",'Needs years'!$C$185,"")
B35: =IF(SUMPRODUCT(('Inputs'!$H$89:$H$94="Yes")*('Inputs'!$B$89:$B$94<>""))>0,"Over the whole period","") | C35: =IF('Inputs'!$H$89="Yes",'Needs years'!$C$18,"") | D35: =IF('Inputs'!$H$90="Yes",'Needs years'!$C$74,"") | E35: =IF('Inputs'!$H$91="Yes",'Needs years'!$C$130,"") | F35: =IF('Inputs'!$H$92="Yes",'Needs years'!$C$186,"")
B36: =IF(SUMPRODUCT(('Inputs'!$H$89:$H$94="Yes")*('Inputs'!$B$89:$B$94<>""))>0,"Extra capital it needs today (already in the need)","") | C36: =IF('Inputs'!$H$89="Yes",'Needs years'!$C$19,"") | D36: =IF('Inputs'!$H$90="Yes",'Needs years'!$C$75,"") | E36: =IF('Inputs'!$H$91="Yes",'Needs years'!$C$131,"") | F36: =IF('Inputs'!$H$92="Yes",'Needs years'!$C$187,"")
B38: Next steps to discuss
B39: ="1. "&IF(('Needs calc'!$T$7+'Needs calc'!$T$8+'Needs calc'!$T$9+'Needs calc'!$T$10+'Needs calc'!$T$11+'Needs calc'!$T$12+'Needs calc'!$T$13)>0,"Close the gap: the Options page shows the ways to do it, starting with what you already have.","Keep your nominations and will instructions as they are: they provide for everyone today.")
B40: 2. Check who each of your policies and retirement funds pays to: the nominations decide who receives the money, not your will.
B41: ="3. "&IF(SUMPRODUCT(('Inputs'!$H$89:$H$94="Yes")*('Inputs'!$B$89:$B$94<>""))>0,"Decide how the trust in your will shares between the children: equal shares, or one family pot shared by need.","Sign a will that says who inherits, so the law does not decide it for you.")
B43: ="Basis: indicative, on the needs you gave us and your policies and will instructions as they stand. Capital for a dependant is invested at "&FIXED('Inputs'!$C$122,0)&"% a year before tax as a unit trust, less tax"&IF(SUMPRODUCT(('Inputs'!$H$89:$H$94="Yes")*('Inputs'!$B$89:$B$94<>""))>0," and trustee fees of "&IF(ROUND('Inputs'!$H$108,0)='Inputs'!$H$108,FIXED('Inputs'!$H$108,0),IF(ROUND('Inputs'!$H$108,1)='Inputs'!$H$108,FIXED('Inputs'!$H$108,1),FIXED('Inputs'!$H$108,2)))&"%"&" a year while it is in the trust","")&"; retirement money paid to a dependant pays them first from a living annuity, taxed as their income. Each need rises as you asked. Not legal or tax advice."

Sheet Options
B1: Duwalcoe Financial Consultants CC
B2: FSP 9978 | clinton@duwalcoe.co.za | 083 608 5617
B3: =IF(OR(COUNTIF('Inputs'!$B$143:$B$156,"✗ Full FNA*")>0,LEFT('Inputs'!$B$138,1)="✗"),"NOT FOR THE CLIENT: this case needs the full FNA (see Checks on Inputs)","")
B4: Options to discuss
B5: Change a yellow cell and the whole column works itself out again, estate duty included.
B6: =IF((('Needs calc'!$C$51>0)+('Needs calc'!$C$58>0)+('Needs calc'!$C$65>0)+('Needs calc'!$C$72>0)+('Needs calc'!$C$79>0)+('Needs calc'!$C$86>0)+('Needs calc'!$C$91>0))=0,"Everyone who depends on you is provided for today. These options show what changes would do.","Your estate"&IF('Workings'!$C$64>0," is short of cash, and some of the people who depend on you are short."," can pay its bills. The question is how to make sure the people who depend on you have the income you want for them."))
C8: Today | D8: Option 1 | E8: Option 2 | F8: Option 3
B9: How the trust shares | C9: =IF('Needs calc'!$C$4=1,"One family pot",IF('Needs calc'!$C$29>0,"Equal shares","")) | D9: One family pot | E9: Equal shares | F9: Equal shares
B10: Close the gaps with | C10: Nothing | D10: Nothing | E10: Part of a nomination | F10: New life cover
B11: Nomination to use
B12: Moved to (for "All of a nomination") | D12: The children's trust
B13: What changes | C13: Nothing | D13: =IF('Needs calc'!$AK$18=1,"Choose a policy paid to a person or the spouse, not to the estate",IF('Needs calc'!$AK$100=1,"Not enough in that nomination to close the gaps",CHOOSE('Needs calc'!$AK$3+1,"No change to the policies","New cover of R "&FIXED(ROUND('Needs calc'!$AK$15,-3),0)&" nominated for those who are short","R "&FIXED(ROUND('Needs calc'!$AK$14,-3),0)&" of "&'Options'!$D$11&" moved to those who are short","All of "&'Options'!$D$11&" (R "&FIXED(ROUND('Needs calc'!$AK$14,-3),0)&") moved to "&'Options'!$D$12)&IF('Needs calc'!$AK$4=1,"; the trust shares by need as one family pot",""))) | E13: =IF('Needs calc'!$BB$18=1,"Choose a policy paid to a person or the spouse, not to the estate",IF('Needs calc'!$BB$100=1,"Not enough in that nomination to close the gaps",CHOOSE('Needs calc'!$BB$3+1,"No change to the policies","New cover of R "&FIXED(ROUND('Needs calc'!$BB$15,-3),0)&" nominated for those who are short","R "&FIXED(ROUND('Needs calc'!$BB$14,-3),0)&" of "&'Options'!$E$11&" moved to those who are short","All of "&'Options'!$E$11&" (R "&FIXED(ROUND('Needs calc'!$BB$14,-3),0)&") moved to "&'Options'!$E$12)&IF('Needs calc'!$BB$4=1,"; the trust shares by need as one family pot",""))) | F13: =IF('Needs calc'!$BS$18=1,"Choose a policy paid to a person or the spouse, not to the estate",IF('Needs calc'!$BS$100=1,"Not enough in that nomination to close the gaps",CHOOSE('Needs calc'!$BS$3+1,"No change to the policies","New cover of R "&FIXED(ROUND('Needs calc'!$BS$15,-3),0)&" nominated for those who are short","R "&FIXED(ROUND('Needs calc'!$BS$14,-3),0)&" of "&'Options'!$F$11&" moved to those who are short","All of "&'Options'!$F$11&" (R "&FIXED(ROUND('Needs calc'!$BS$14,-3),0)&") moved to "&'Options'!$F$12)&IF('Needs calc'!$BS$4=1,"; the trust shares by need as one family pot","")))
B15: What it does
B16: =IF('Inputs'!$B$89="","",'Inputs'!$B$89&": capital set aside") | C16: =IF('Inputs'!$B$89="","",'Needs years'!$C$7+IF(AND('Needs calc'!$C$4=1,'Inputs'!$Q$89=1),'Needs calc'!$C$50,'Needs calc'!$C$46)) | D16: =IF('Inputs'!$B$89="","",'Needs years'!$C$7+IF(AND('Needs calc'!$AK$4=1,'Inputs'!$Q$89=1),'Needs calc'!$AK$50,'Needs calc'!$AK$46)) | E16: =IF('Inputs'!$B$89="","",'Needs years'!$C$7+IF(AND('Needs calc'!$BB$4=1,'Inputs'!$Q$89=1),'Needs calc'!$BB$50,'Needs calc'!$BB$46)) | F16: =IF('Inputs'!$B$89="","",'Needs years'!$C$7+IF(AND('Needs calc'!$BS$4=1,'Inputs'!$Q$89=1),'Needs calc'!$BS$50,'Needs calc'!$BS$46))
B17: =IF('Inputs'!$B$89="","",'Inputs'!$B$89&": a month") | C17: =IF('Inputs'!$B$89="","",'Needs calc'!$C$52) | D17: =IF('Inputs'!$B$89="","",'Needs calc'!$AK$52) | E17: =IF('Inputs'!$B$89="","",'Needs calc'!$BB$52) | F17: =IF('Inputs'!$B$89="","",'Needs calc'!$BS$52)
B18: =IF('Inputs'!$B$89="","",'Inputs'!$B$89) | C18: =IF('Inputs'!$B$89="","",IF(AND('Needs calc'!$C$4=1,'Inputs'!$Q$89=1),IF('Needs calc'!$C$90>=0,"Covered","Pot short R "&FIXED(ROUND(-'Needs calc'!$C$90,-3),0)),IF('Needs calc'!$C$51>0,"Short R "&FIXED(ROUND('Needs calc'!$C$51,-3),0),IF('Needs calc'!$C$51<0,"R "&FIXED(ROUND(-'Needs calc'!$C$51,-3),0)&" over","Covered")))) | D18: =IF('Inputs'!$B$89="","",IF(AND('Needs calc'!$AK$4=1,'Inputs'!$Q$89=1),IF('Needs calc'!$AK$90>=0,"Covered","Pot short R "&FIXED(ROUND(-'Needs calc'!$AK$90,-3),0)),IF('Needs calc'!$AK$51>0,"Short R "&FIXED(ROUND('Needs calc'!$AK$51,-3),0),IF('Needs calc'!$AK$51<0,"R "&FIXED(ROUND(-'Needs calc'!$AK$51,-3),0)&" over","Covered")))) | E18: =IF('Inputs'!$B$89="","",IF(AND('Needs calc'!$BB$4=1,'Inputs'!$Q$89=1),IF('Needs calc'!$BB$90>=0,"Covered","Pot short R "&FIXED(ROUND(-'Needs calc'!$BB$90,-3),0)),IF('Needs calc'!$BB$51>0,"Short R "&FIXED(ROUND('Needs calc'!$BB$51,-3),0),IF('Needs calc'!$BB$51<0,"R "&FIXED(ROUND(-'Needs calc'!$BB$51,-3),0)&" over","Covered")))) | F18: =IF('Inputs'!$B$89="","",IF(AND('Needs calc'!$BS$4=1,'Inputs'!$Q$89=1),IF('Needs calc'!$BS$90>=0,"Covered","Pot short R "&FIXED(ROUND(-'Needs calc'!$BS$90,-3),0)),IF('Needs calc'!$BS$51>0,"Short R "&FIXED(ROUND('Needs calc'!$BS$51,-3),0),IF('Needs calc'!$BS$51<0,"R "&FIXED(ROUND(-'Needs calc'!$BS$51,-3),0)&" over","Covered"))))
B19: =IF('Inputs'!$B$90="","",'Inputs'!$B$90&": capital set aside") | C19: =IF('Inputs'!$B$90="","",'Needs years'!$C$63+IF(AND('Needs calc'!$C$4=1,'Inputs'!$Q$90=1),'Needs calc'!$C$57,'Needs calc'!$C$53)) | D19: =IF('Inputs'!$B$90="","",'Needs years'!$C$63+IF(AND('Needs calc'!$AK$4=1,'Inputs'!$Q$90=1),'Needs calc'!$AK$57,'Needs calc'!$AK$53)) | E19: =IF('Inputs'!$B$90="","",'Needs years'!$C$63+IF(AND('Needs calc'!$BB$4=1,'Inputs'!$Q$90=1),'Needs calc'!$BB$57,'Needs calc'!$BB$53)) | F19: =IF('Inputs'!$B$90="","",'Needs years'!$C$63+IF(AND('Needs calc'!$BS$4=1,'Inputs'!$Q$90=1),'Needs calc'!$BS$57,'Needs calc'!$BS$53))
B20: =IF('Inputs'!$B$90="","",'Inputs'!$B$90&": a month") | C20: =IF('Inputs'!$B$90="","",'Needs calc'!$C$59) | D20: =IF('Inputs'!$B$90="","",'Needs calc'!$AK$59) | E20: =IF('Inputs'!$B$90="","",'Needs calc'!$BB$59) | F20: =IF('Inputs'!$B$90="","",'Needs calc'!$BS$59)
B21: =IF('Inputs'!$B$90="","",'Inputs'!$B$90) | C21: =IF('Inputs'!$B$90="","",IF(AND('Needs calc'!$C$4=1,'Inputs'!$Q$90=1),IF('Needs calc'!$C$90>=0,"Covered","Pot short R "&FIXED(ROUND(-'Needs calc'!$C$90,-3),0)),IF('Needs calc'!$C$58>0,"Short R "&FIXED(ROUND('Needs calc'!$C$58,-3),0),IF('Needs calc'!$C$58<0,"R "&FIXED(ROUND(-'Needs calc'!$C$58,-3),0)&" over","Covered")))) | D21: =IF('Inputs'!$B$90="","",IF(AND('Needs calc'!$AK$4=1,'Inputs'!$Q$90=1),IF('Needs calc'!$AK$90>=0,"Covered","Pot short R "&FIXED(ROUND(-'Needs calc'!$AK$90,-3),0)),IF('Needs calc'!$AK$58>0,"Short R "&FIXED(ROUND('Needs calc'!$AK$58,-3),0),IF('Needs calc'!$AK$58<0,"R "&FIXED(ROUND(-'Needs calc'!$AK$58,-3),0)&" over","Covered")))) | E21: =IF('Inputs'!$B$90="","",IF(AND('Needs calc'!$BB$4=1,'Inputs'!$Q$90=1),IF('Needs calc'!$BB$90>=0,"Covered","Pot short R "&FIXED(ROUND(-'Needs calc'!$BB$90,-3),0)),IF('Needs calc'!$BB$58>0,"Short R "&FIXED(ROUND('Needs calc'!$BB$58,-3),0),IF('Needs calc'!$BB$58<0,"R "&FIXED(ROUND(-'Needs calc'!$BB$58,-3),0)&" over","Covered")))) | F21: =IF('Inputs'!$B$90="","",IF(AND('Needs calc'!$BS$4=1,'Inputs'!$Q$90=1),IF('Needs calc'!$BS$90>=0,"Covered","Pot short R "&FIXED(ROUND(-'Needs calc'!$BS$90,-3),0)),IF('Needs calc'!$BS$58>0,"Short R "&FIXED(ROUND('Needs calc'!$BS$58,-3),0),IF('Needs calc'!$BS$58<0,"R "&FIXED(ROUND(-'Needs calc'!$BS$58,-3),0)&" over","Covered"))))
B22: =IF('Inputs'!$B$91="","",'Inputs'!$B$91&": capital set aside") | C22: =IF('Inputs'!$B$91="","",'Needs years'!$C$119+IF(AND('Needs calc'!$C$4=1,'Inputs'!$Q$91=1),'Needs calc'!$C$64,'Needs calc'!$C$60)) | D22: =IF('Inputs'!$B$91="","",'Needs years'!$C$119+IF(AND('Needs calc'!$AK$4=1,'Inputs'!$Q$91=1),'Needs calc'!$AK$64,'Needs calc'!$AK$60)) | E22: =IF('Inputs'!$B$91="","",'Needs years'!$C$119+IF(AND('Needs calc'!$BB$4=1,'Inputs'!$Q$91=1),'Needs calc'!$BB$64,'Needs calc'!$BB$60)) | F22: =IF('Inputs'!$B$91="","",'Needs years'!$C$119+IF(AND('Needs calc'!$BS$4=1,'Inputs'!$Q$91=1),'Needs calc'!$BS$64,'Needs calc'!$BS$60))
B23: =IF('Inputs'!$B$91="","",'Inputs'!$B$91&": a month") | C23: =IF('Inputs'!$B$91="","",'Needs calc'!$C$66) | D23: =IF('Inputs'!$B$91="","",'Needs calc'!$AK$66) | E23: =IF('Inputs'!$B$91="","",'Needs calc'!$BB$66) | F23: =IF('Inputs'!$B$91="","",'Needs calc'!$BS$66)
B24: =IF('Inputs'!$B$91="","",'Inputs'!$B$91) | C24: =IF('Inputs'!$B$91="","",IF(AND('Needs calc'!$C$4=1,'Inputs'!$Q$91=1),IF('Needs calc'!$C$90>=0,"Covered","Pot short R "&FIXED(ROUND(-'Needs calc'!$C$90,-3),0)),IF('Needs calc'!$C$65>0,"Short R "&FIXED(ROUND('Needs calc'!$C$65,-3),0),IF('Needs calc'!$C$65<0,"R "&FIXED(ROUND(-'Needs calc'!$C$65,-3),0)&" over","Covered")))) | D24: =IF('Inputs'!$B$91="","",IF(AND('Needs calc'!$AK$4=1,'Inputs'!$Q$91=1),IF('Needs calc'!$AK$90>=0,"Covered","Pot short R "&FIXED(ROUND(-'Needs calc'!$AK$90,-3),0)),IF('Needs calc'!$AK$65>0,"Short R "&FIXED(ROUND('Needs calc'!$AK$65,-3),0),IF('Needs calc'!$AK$65<0,"R "&FIXED(ROUND(-'Needs calc'!$AK$65,-3),0)&" over","Covered")))) | E24: =IF('Inputs'!$B$91="","",IF(AND('Needs calc'!$BB$4=1,'Inputs'!$Q$91=1),IF('Needs calc'!$BB$90>=0,"Covered","Pot short R "&FIXED(ROUND(-'Needs calc'!$BB$90,-3),0)),IF('Needs calc'!$BB$65>0,"Short R "&FIXED(ROUND('Needs calc'!$BB$65,-3),0),IF('Needs calc'!$BB$65<0,"R "&FIXED(ROUND(-'Needs calc'!$BB$65,-3),0)&" over","Covered")))) | F24: =IF('Inputs'!$B$91="","",IF(AND('Needs calc'!$BS$4=1,'Inputs'!$Q$91=1),IF('Needs calc'!$BS$90>=0,"Covered","Pot short R "&FIXED(ROUND(-'Needs calc'!$BS$90,-3),0)),IF('Needs calc'!$BS$65>0,"Short R "&FIXED(ROUND('Needs calc'!$BS$65,-3),0),IF('Needs calc'!$BS$65<0,"R "&FIXED(ROUND(-'Needs calc'!$BS$65,-3),0)&" over","Covered"))))
B25: =IF('Inputs'!$B$92="","",'Inputs'!$B$92&": capital set aside") | C25: =IF('Inputs'!$B$92="","",'Needs years'!$C$175+IF(AND('Needs calc'!$C$4=1,'Inputs'!$Q$92=1),'Needs calc'!$C$71,'Needs calc'!$C$67)) | D25: =IF('Inputs'!$B$92="","",'Needs years'!$C$175+IF(AND('Needs calc'!$AK$4=1,'Inputs'!$Q$92=1),'Needs calc'!$AK$71,'Needs calc'!$AK$67)) | E25: =IF('Inputs'!$B$92="","",'Needs years'!$C$175+IF(AND('Needs calc'!$BB$4=1,'Inputs'!$Q$92=1),'Needs calc'!$BB$71,'Needs calc'!$BB$67)) | F25: =IF('Inputs'!$B$92="","",'Needs years'!$C$175+IF(AND('Needs calc'!$BS$4=1,'Inputs'!$Q$92=1),'Needs calc'!$BS$71,'Needs calc'!$BS$67))
B26: =IF('Inputs'!$B$92="","",'Inputs'!$B$92&": a month") | C26: =IF('Inputs'!$B$92="","",'Needs calc'!$C$73) | D26: =IF('Inputs'!$B$92="","",'Needs calc'!$AK$73) | E26: =IF('Inputs'!$B$92="","",'Needs calc'!$BB$73) | F26: =IF('Inputs'!$B$92="","",'Needs calc'!$BS$73)
B27: =IF('Inputs'!$B$92="","",'Inputs'!$B$92) | C27: =IF('Inputs'!$B$92="","",IF(AND('Needs calc'!$C$4=1,'Inputs'!$Q$92=1),IF('Needs calc'!$C$90>=0,"Covered","Pot short R "&FIXED(ROUND(-'Needs calc'!$C$90,-3),0)),IF('Needs calc'!$C$72>0,"Short R "&FIXED(ROUND('Needs calc'!$C$72,-3),0),IF('Needs calc'!$C$72<0,"R "&FIXED(ROUND(-'Needs calc'!$C$72,-3),0)&" over","Covered")))) | D27: =IF('Inputs'!$B$92="","",IF(AND('Needs calc'!$AK$4=1,'Inputs'!$Q$92=1),IF('Needs calc'!$AK$90>=0,"Covered","Pot short R "&FIXED(ROUND(-'Needs calc'!$AK$90,-3),0)),IF('Needs calc'!$AK$72>0,"Short R "&FIXED(ROUND('Needs calc'!$AK$72,-3),0),IF('Needs calc'!$AK$72<0,"R "&FIXED(ROUND(-'Needs calc'!$AK$72,-3),0)&" over","Covered")))) | E27: =IF('Inputs'!$B$92="","",IF(AND('Needs calc'!$BB$4=1,'Inputs'!$Q$92=1),IF('Needs calc'!$BB$90>=0,"Covered","Pot short R "&FIXED(ROUND(-'Needs calc'!$BB$90,-3),0)),IF('Needs calc'!$BB$72>0,"Short R "&FIXED(ROUND('Needs calc'!$BB$72,-3),0),IF('Needs calc'!$BB$72<0,"R "&FIXED(ROUND(-'Needs calc'!$BB$72,-3),0)&" over","Covered")))) | F27: =IF('Inputs'!$B$92="","",IF(AND('Needs calc'!$BS$4=1,'Inputs'!$Q$92=1),IF('Needs calc'!$BS$90>=0,"Covered","Pot short R "&FIXED(ROUND(-'Needs calc'!$BS$90,-3),0)),IF('Needs calc'!$BS$72>0,"Short R "&FIXED(ROUND('Needs calc'!$BS$72,-3),0),IF('Needs calc'!$BS$72<0,"R "&FIXED(ROUND(-'Needs calc'!$BS$72,-3),0)&" over","Covered"))))
B28: Left in the family pot after every need | C28: =IF('Needs calc'!$C$4=1,'Needs calc'!$C$90,"") | D28: =IF('Needs calc'!$AK$4=1,'Needs calc'!$AK$90,"") | E28: =IF('Needs calc'!$BB$4=1,'Needs calc'!$BB$90,"") | F28: =IF('Needs calc'!$BS$4=1,'Needs calc'!$BS$90,"")
B29: Others receive, after their estate duty | C29: ='Needs calc'!$C$44-'Needs calc'!$C$45 | D29: ='Needs calc'!$AK$44-'Needs calc'!$AK$45 | E29: ='Needs calc'!$BB$44-'Needs calc'!$BB$45 | F29: ='Needs calc'!$BS$44-'Needs calc'!$BS$45
B30: Estate duty in total | C30: ='Needs calc'!$C$20 | D30: ='Needs calc'!$AK$20 | E30: ='Needs calc'!$BB$20 | F30: ='Needs calc'!$BS$20
B31: New life cover | C31: ='Needs calc'!$C$15 | D31: ='Needs calc'!$AK$15 | E31: ='Needs calc'!$BB$15 | F31: ='Needs calc'!$BS$15
B32: New premium | C32: =IF('Needs calc'!$C$15>0,"Yes","No") | D32: =IF('Needs calc'!$AK$15>0,"Yes","No") | E32: =IF('Needs calc'!$BB$15>0,"Yes","No") | F32: =IF('Needs calc'!$BS$15>0,"Yes","No")
B34: Things to know
B35: Moving a nomination uses what you already have: no new premium, but the person it is moved from receives less. One family pot lets the trustees pay each child what they need first and share what is left at the end.
B36: Policy money nominated to the trust or to a child carries its share of estate duty at the estate's average rate. New cover adds to the estate for duty, which is why it is more than the shortfall.
B37: Before a nomination is changed to the trust in your will, we confirm with the insurer that it accepts the trustees as the nominee.

Sheet Figures for quoting
B1: Duwalcoe Financial Consultants CC
B2: FSP 9978 | clinton@duwalcoe.co.za | 083 608 5617
B4: Winding up the estate: the figures
B5: Split the way quotes ask for them. Debts are shown separately.
C7: ="If "&'Inputs'!$C$9&" dies" | D7: =IF(AND(ISNUMBER('Inputs'!$C$100),'Inputs'!$C$100>0),"With the Legacy plan","")
B8: IN THE ESTATE: EXECUTOR'S FEES ARE CHARGED ON THESE
B9: Immovable property | C9: =SUMIFS('Inputs'!$D$22:$D$39,'Inputs'!$C$22:$C$39,"Property") | D9: =IF(AND(ISNUMBER('Inputs'!$C$100),'Inputs'!$C$100>0),SUMIFS('Inputs'!$D$22:$D$39,'Inputs'!$C$22:$C$39,"Property"),"")
B10: Movable property (vehicles, contents) | C10: =SUMIFS('Inputs'!$D$22:$D$39,'Inputs'!$C$22:$C$39,"Vehicle or contents") | D10: =IF(AND(ISNUMBER('Inputs'!$C$100),'Inputs'!$C$100>0),SUMIFS('Inputs'!$D$22:$D$39,'Inputs'!$C$22:$C$39,"Vehicle or contents"),"")
B11: Cash: bank accounts and deposits | C11: =SUMIFS('Inputs'!$D$22:$D$39,'Inputs'!$C$22:$C$39,"Cash and deposits") | D11: =IF(AND(ISNUMBER('Inputs'!$C$100),'Inputs'!$C$100>0),SUMIFS('Inputs'!$D$22:$D$39,'Inputs'!$C$22:$C$39,"Cash and deposits"),"")
B12: Listed shares and unit trusts | C12: =SUMIFS('Inputs'!$D$22:$D$39,'Inputs'!$C$22:$C$39,"Shares and unit trusts") | D12: =IF(AND(ISNUMBER('Inputs'!$C$100),'Inputs'!$C$100>0),SUMIFS('Inputs'!$D$22:$D$39,'Inputs'!$C$22:$C$39,"Shares and unit trusts"),"")
B13: Other investments (tax-free, loan accounts, business interests) | C13: =SUMIFS('Inputs'!$D$22:$D$39,'Inputs'!$C$22:$C$39,"Other investment")+SUMIFS('Inputs'!$D$22:$D$39,'Inputs'!$C$22:$C$39,"Tax-free investment")+SUMIFS('Inputs'!$D$22:$D$39,'Inputs'!$C$22:$C$39,"Loan account")+SUMIFS('Inputs'!$D$22:$D$39,'Inputs'!$C$22:$C$39,"Business interest") | D13: =IF(AND(ISNUMBER('Inputs'!$C$100),'Inputs'!$C$100>0),SUMIFS('Inputs'!$D$22:$D$39,'Inputs'!$C$22:$C$39,"Other investment")+SUMIFS('Inputs'!$D$22:$D$39,'Inputs'!$C$22:$C$39,"Tax-free investment")+SUMIFS('Inputs'!$D$22:$D$39,'Inputs'!$C$22:$C$39,"Loan account")+SUMIFS('Inputs'!$D$22:$D$39,'Inputs'!$C$22:$C$39,"Business interest"),"")
B14: Life assurance paid into the estate | C14: ='Workings'!$C$20 | D14: =IF(AND(ISNUMBER('Inputs'!$C$100),'Inputs'!$C$100>0),'Workings'!$C$20,"")
B15: Total in the estate | C15: =SUM(C9:C14) | D15: =IF(AND(ISNUMBER('Inputs'!$C$100),'Inputs'!$C$100>0),SUM(C9:C14),"")
B16: OUTSIDE THE ESTATE: NO EXECUTOR'S FEES
B17: Policies paid to a named person or spouse (counted for estate duty) | C17: ='Workings'!$C$22 | D17: =IF(AND(ISNUMBER('Inputs'!$C$100),'Inputs'!$C$100>0),'Workings'!$C$22,"")
B18: Approved group life (not counted) | C18: =SUMIFS('Inputs'!$D$59:$D$70,'Inputs'!$E$59:$E$70,"No") | D18: =IF(AND(ISNUMBER('Inputs'!$C$100),'Inputs'!$C$100>0),SUMIFS('Inputs'!$D$59:$D$70,'Inputs'!$E$59:$E$70,"No"),"")
B19: Retirement funds (not counted) | C19: =SUM('Inputs'!$D$76:$D$83) | D19: =IF(AND(ISNUMBER('Inputs'!$C$100),'Inputs'!$C$100>0),SUM('Inputs'!$D$76:$D$83),"")
B20: TOTALS
B21: Everything owned | C21: =C15+SUM(C17:C19) | D21: =IF(AND(ISNUMBER('Inputs'!$C$100),'Inputs'!$C$100>0),C15+SUM(C17:C19),"")
B22: Counted for estate duty | C22: ='Workings'!$C$23 | D22: =IF(AND(ISNUMBER('Inputs'!$C$100),'Inputs'!$C$100>0),'Workings'!$C$23,"")
B23: Liabilities | C23: ='Workings'!$C$59 | D23: =IF(AND(ISNUMBER('Inputs'!$C$100),'Inputs'!$C$100>0),'Workings'!$C$59,"")
B24: COST OF WINDING UP
B25: Executor's fees | C25: ='Workings'!$C$51 | D25: =IF(AND(ISNUMBER('Inputs'!$C$100),'Inputs'!$C$100>0),'Workings'!$D$51,"")
B26: Master's fees, funeral, notices and sundries | C26: ='Workings'!$C$50 | D26: =IF(AND(ISNUMBER('Inputs'!$C$100),'Inputs'!$C$100>0),'Workings'!$D$50,"")
B27: Property transfer and conveyancing | C27: ='Workings'!$C$52 | D27: =IF(AND(ISNUMBER('Inputs'!$C$100),'Inputs'!$C$100>0),'Workings'!$D$52,"")
B28: Agent's commission on property sold | C28: ='Workings'!$C$53 | D28: =IF(AND(ISNUMBER('Inputs'!$C$100),'Inputs'!$C$100>0),'Workings'!$D$53,"")
B29: Capital gains tax | C29: ='Workings'!$C$54 | D29: =IF(AND(ISNUMBER('Inputs'!$C$100),'Inputs'!$C$100>0),'Workings'!$D$54,"")
B30: Estate duty borne by the estate | C30: ='Workings'!$C$55 | D30: =IF(AND(ISNUMBER('Inputs'!$C$100),'Inputs'!$C$100>0),'Workings'!$D$55,"")
B31: Cost of winding up, before debts | C31: ='Workings'!$C$56 | D31: =IF(AND(ISNUMBER('Inputs'!$C$100),'Inputs'!$C$100>0),'Workings'!$D$56,"")
B32: Paid by the Legacy plan | C32: =-'Workings'!$C$57 | D32: =IF(AND(ISNUMBER('Inputs'!$C$100),'Inputs'!$C$100>0),-'Workings'!$D$57,"")
B33: Debts (not included above) | C33: ='Workings'!$C$59 | D33: =IF(AND(ISNUMBER('Inputs'!$C$100),'Inputs'!$C$100>0),'Workings'!$D$59,"")
B35: Cover paid into an estate is itself charged executor's fees; cover paid to a named person or trust is not.

Sheet Workings
B1: Duwalcoe Financial Consultants CC
B2: FSP 9978 | clinton@duwalcoe.co.za | 083 608 5617
B4: Workings
B5: Adviser reference and compliance record. Precise figures.
B7: 1. Capital gains tax on death | C7: Today | D7: With the plan
B8: ="Taxable income for the year"&IF('Inputs'!$C$17<>"",": "&'Inputs'!$C$17,"") | C8: =N('Inputs'!$C$16) | D8: =N('Inputs'!$C$16)
B9: Gains: value less base cost, on property, shares, unit trusts and other investments | C9: =SUM('Inputs'!$M$22:$M$39) | D9: =SUM('Inputs'!$M$22:$M$39)
B10: Less the primary residence exclusion | C10: =-SUM('Inputs'!$N$22:$N$39) | D10: =-SUM('Inputs'!$N$22:$N$39)
B11: Less the exclusion in the year of death | C11: =-MIN('Inputs'!$C$119,MAX(0,C9+C10)) | D11: =-MIN('Inputs'!$C$119,MAX(0,D9+D10))
B12: Net gain | C12: =MAX(0,C9+C10+C11) | D12: =MAX(0,D9+D10+D11)
B13: ="Added to taxable income: "&FIXED('Inputs'!$C$120,0)&"% of the net gain (the inclusion rate, not a tax rate)" | C13: =C12*'Inputs'!$C$120/100 | D13: =D12*'Inputs'!$C$120/100
B14: Tax on taxable income plus the gain added | C14: =(INDEX('Inputs'!$D$125:$D$131,MATCH(C8+C13,'Inputs'!$C$125:$C$131,1))+INDEX('Inputs'!$E$125:$E$131,MATCH(C8+C13,'Inputs'!$C$125:$C$131,1))/100*((C8+C13)-INDEX('Inputs'!$C$125:$C$131,MATCH(C8+C13,'Inputs'!$C$125:$C$131,1)))) | D14: =(INDEX('Inputs'!$D$125:$D$131,MATCH(D8+D13,'Inputs'!$C$125:$C$131,1))+INDEX('Inputs'!$E$125:$E$131,MATCH(D8+D13,'Inputs'!$C$125:$C$131,1))/100*((D8+D13)-INDEX('Inputs'!$C$125:$C$131,MATCH(D8+D13,'Inputs'!$C$125:$C$131,1))))
B15: Less tax on taxable income alone | C15: =-(INDEX('Inputs'!$D$125:$D$131,MATCH(C8,'Inputs'!$C$125:$C$131,1))+INDEX('Inputs'!$E$125:$E$131,MATCH(C8,'Inputs'!$C$125:$C$131,1))/100*((C8)-INDEX('Inputs'!$C$125:$C$131,MATCH(C8,'Inputs'!$C$125:$C$131,1)))) | D15: =-(INDEX('Inputs'!$D$125:$D$131,MATCH(D8,'Inputs'!$C$125:$C$131,1))+INDEX('Inputs'!$E$125:$E$131,MATCH(D8,'Inputs'!$C$125:$C$131,1))/100*((D8)-INDEX('Inputs'!$C$125:$C$131,MATCH(D8,'Inputs'!$C$125:$C$131,1))))
B16: Capital gains tax on death | C16: =IF(C12>0,ROUND(C14+C15,2),0) | D16: =IF(D12>0,ROUND(D14+D15,2),0)
B18: 2. Estate duty | C18: Today | D18: With the plan
B19: Assets in the estate | C19: =ROUND(SUM('Inputs'!$D$22:$D$39),2) | D19: =ROUND(SUM('Inputs'!$D$22:$D$39),2)
B20: Life cover paid into the estate | C20: =SUMIFS('Inputs'!$D$59:$D$70,'Inputs'!$C$59:$C$70,"Estate") | D20: =SUMIFS('Inputs'!$D$59:$D$70,'Inputs'!$C$59:$C$70,"Estate")
B21: Gross estate (handled by the executor) | C21: =C19+C20 | D21: =D19+D20
B22: Policies paid to a named person or spouse, counted for estate duty | C22: =SUMIFS('Inputs'!$D$59:$D$70,'Inputs'!$C$59:$C$70,"<>Estate",'Inputs'!$E$59:$E$70,"<>No") | D22: =SUMIFS('Inputs'!$D$59:$D$70,'Inputs'!$C$59:$C$70,"<>Estate",'Inputs'!$E$59:$E$70,"<>No")
B23: Gross dutiable estate | C23: =C21+C22 | D23: =D21+D22
B24: Less debts | C24: =-SUM('Inputs'!$D$45:$D$54) | D24: =-SUM('Inputs'!$D$45:$D$54)
B25: Less funeral | C25: =-'Inputs'!$C$111 | D25: =-'Inputs'!$C$111
B26: Less Master's fees | C26: =-'Inputs'!$C$110 | D26: =-'Inputs'!$C$110
B27: Less estate sundries | C27: =-'Inputs'!$C$112 | D27: =-'Inputs'!$C$112
B28: ="Less executor's fees: "&IF(ROUND('Inputs'!$C$108,0)='Inputs'!$C$108,FIXED('Inputs'!$C$108,0),IF(ROUND('Inputs'!$C$108,1)='Inputs'!$C$108,FIXED('Inputs'!$C$108,1),FIXED('Inputs'!$C$108,2)))&"%"&" plus VAT"&IF(AND(ISNUMBER('Inputs'!$C$100),'Inputs'!$C$100>0)," / Capital Legacy "&IF(ROUND('Inputs'!$C$100,0)='Inputs'!$C$100,FIXED('Inputs'!$C$100,0),IF(ROUND('Inputs'!$C$100,1)='Inputs'!$C$100,FIXED('Inputs'!$C$100,1),FIXED('Inputs'!$C$100,2)))&"%"&" plus VAT","") | C28: =-ROUND('Inputs'!$C$108/100*(1+'Inputs'!$C$109/100)*C21,2) | D28: =-ROUND(IF(AND(ISNUMBER('Inputs'!$C$100),'Inputs'!$C$100>0),'Inputs'!$C$100,'Inputs'!$C$108)/100*(1+'Inputs'!$C$109/100)*D21,2)
B29: Less property transfer costs / Capital Legacy conveyancing | C29: =-SUM('Inputs'!$P$22:$P$39) | D29: =-IF(AND(AND(ISNUMBER('Inputs'!$C$100),'Inputs'!$C$100>0),ISNUMBER('Inputs'!$C$101)),'Inputs'!$C$101,SUM('Inputs'!$P$22:$P$39))
B30: Less agent's commission on property sold | C30: =-SUM('Inputs'!$Q$22:$Q$39) | D30: =-SUM('Inputs'!$Q$22:$Q$39)
B31: Less capital gains tax on death (s.4(l)) | C31: =-C16 | D31: =-D16
B32: Less everything passing to the spouse (s.4(q)) | C32: =-(SUM('Inputs'!$R$22:$R$39)+SUMIFS('Inputs'!$D$59:$D$70,'Inputs'!$C$59:$C$70,"Spouse",'Inputs'!$E$59:$E$70,"<>No")+IF('Inputs'!$C$14="Spouse",MAX(0,C21+C24-(-C25-C26-C27-C28-C29-C30-C31)-SUM('Inputs'!$R$22:$R$39)-SUM('Inputs'!$S$22:$S$39)),0)) | D32: =-(SUM('Inputs'!$R$22:$R$39)+SUMIFS('Inputs'!$D$59:$D$70,'Inputs'!$C$59:$C$70,"Spouse",'Inputs'!$E$59:$E$70,"<>No")+IF('Inputs'!$C$14="Spouse",MAX(0,D21+D24-(-D25-D26-D27-D28-D29-D30-D31)-SUM('Inputs'!$R$22:$R$39)-SUM('Inputs'!$S$22:$S$39)),0))
B33: Net value of the estate | C33: =ROUND(C23+C24+C25+C26+C27+C28+C29+C30+C31+C32,2) | D33: =ROUND(D23+D24+D25+D26+D27+D28+D29+D30+D31+D32,2)
B34: Less abatement (s.4A) | C34: =-'Inputs'!$C$115 | D34: =-'Inputs'!$C$115
B35: Dutiable amount | C35: =MAX(0,C33+C34) | D35: =MAX(0,D33+D34)
B36: Estate duty | C36: =ROUND(IF(C35<='Inputs'!$C$117,C35*'Inputs'!$C$116/100,'Inputs'!$C$117*'Inputs'!$C$116/100+(C35-'Inputs'!$C$117)*'Inputs'!$C$118/100),2) | D36: =ROUND(IF(D35<='Inputs'!$C$117,D35*'Inputs'!$C$116/100,'Inputs'!$C$117*'Inputs'!$C$116/100+(D35-'Inputs'!$C$117)*'Inputs'!$C$118/100),2)
B37: Average rate (duty / net value) | C37: =IF(C33>0,C36/C33,0) | D37: =IF(D33>0,D36/D33,0)
B38: Estate duty the named people pay themselves (the executor recovers it from them):
B39: =IFERROR(" Bequest: "&INDEX('Inputs'!$B$22:$B$39,MATCH(1,'Inputs'!$X$22:$X$39,0))&IF(INDEX('Inputs'!$I$22:$I$39,MATCH(1,'Inputs'!$X$22:$X$39,0))<>""," ("&INDEX('Inputs'!$I$22:$I$39,MATCH(1,'Inputs'!$X$22:$X$39,0))&")",""),IFERROR(" Policy: "&INDEX('Inputs'!$B$59:$B$70,MATCH(1,'Inputs'!$O$59:$O$70,0))&IF(INDEX('Inputs'!$I$59:$I$70,MATCH(1,'Inputs'!$O$59:$O$70,0))<>""," ("&INDEX('Inputs'!$I$59:$I$70,MATCH(1,'Inputs'!$O$59:$O$70,0))&")",""),"")) | C39: =IFERROR(INDEX('Inputs'!$U$22:$U$39,MATCH(1,'Inputs'!$X$22:$X$39,0)),IFERROR(INDEX('Inputs'!$M$59:$M$70,MATCH(1,'Inputs'!$O$59:$O$70,0)),"")) | D39: =IFERROR(INDEX('Inputs'!$V$22:$V$39,MATCH(1,'Inputs'!$X$22:$X$39,0)),IFERROR(INDEX('Inputs'!$N$59:$N$70,MATCH(1,'Inputs'!$O$59:$O$70,0)),""))
B40: =IFERROR(" Bequest: "&INDEX('Inputs'!$B$22:$B$39,MATCH(2,'Inputs'!$X$22:$X$39,0))&IF(INDEX('Inputs'!$I$22:$I$39,MATCH(2,'Inputs'!$X$22:$X$39,0))<>""," ("&INDEX('Inputs'!$I$22:$I$39,MATCH(2,'Inputs'!$X$22:$X$39,0))&")",""),IFERROR(" Policy: "&INDEX('Inputs'!$B$59:$B$70,MATCH(2,'Inputs'!$O$59:$O$70,0))&IF(INDEX('Inputs'!$I$59:$I$70,MATCH(2,'Inputs'!$O$59:$O$70,0))<>""," ("&INDEX('Inputs'!$I$59:$I$70,MATCH(2,'Inputs'!$O$59:$O$70,0))&")",""),"")) | C40: =IFERROR(INDEX('Inputs'!$U$22:$U$39,MATCH(2,'Inputs'!$X$22:$X$39,0)),IFERROR(INDEX('Inputs'!$M$59:$M$70,MATCH(2,'Inputs'!$O$59:$O$70,0)),"")) | D40: =IFERROR(INDEX('Inputs'!$V$22:$V$39,MATCH(2,'Inputs'!$X$22:$X$39,0)),IFERROR(INDEX('Inputs'!$N$59:$N$70,MATCH(2,'Inputs'!$O$59:$O$70,0)),""))
B41: =IFERROR(" Bequest: "&INDEX('Inputs'!$B$22:$B$39,MATCH(3,'Inputs'!$X$22:$X$39,0))&IF(INDEX('Inputs'!$I$22:$I$39,MATCH(3,'Inputs'!$X$22:$X$39,0))<>""," ("&INDEX('Inputs'!$I$22:$I$39,MATCH(3,'Inputs'!$X$22:$X$39,0))&")",""),IFERROR(" Policy: "&INDEX('Inputs'!$B$59:$B$70,MATCH(3,'Inputs'!$O$59:$O$70,0))&IF(INDEX('Inputs'!$I$59:$I$70,MATCH(3,'Inputs'!$O$59:$O$70,0))<>""," ("&INDEX('Inputs'!$I$59:$I$70,MATCH(3,'Inputs'!$O$59:$O$70,0))&")",""),"")) | C41: =IFERROR(INDEX('Inputs'!$U$22:$U$39,MATCH(3,'Inputs'!$X$22:$X$39,0)),IFERROR(INDEX('Inputs'!$M$59:$M$70,MATCH(3,'Inputs'!$O$59:$O$70,0)),"")) | D41: =IFERROR(INDEX('Inputs'!$V$22:$V$39,MATCH(3,'Inputs'!$X$22:$X$39,0)),IFERROR(INDEX('Inputs'!$N$59:$N$70,MATCH(3,'Inputs'!$O$59:$O$70,0)),""))
B42: =IFERROR(" Bequest: "&INDEX('Inputs'!$B$22:$B$39,MATCH(4,'Inputs'!$X$22:$X$39,0))&IF(INDEX('Inputs'!$I$22:$I$39,MATCH(4,'Inputs'!$X$22:$X$39,0))<>""," ("&INDEX('Inputs'!$I$22:$I$39,MATCH(4,'Inputs'!$X$22:$X$39,0))&")",""),IFERROR(" Policy: "&INDEX('Inputs'!$B$59:$B$70,MATCH(4,'Inputs'!$O$59:$O$70,0))&IF(INDEX('Inputs'!$I$59:$I$70,MATCH(4,'Inputs'!$O$59:$O$70,0))<>""," ("&INDEX('Inputs'!$I$59:$I$70,MATCH(4,'Inputs'!$O$59:$O$70,0))&")",""),"")) | C42: =IFERROR(INDEX('Inputs'!$U$22:$U$39,MATCH(4,'Inputs'!$X$22:$X$39,0)),IFERROR(INDEX('Inputs'!$M$59:$M$70,MATCH(4,'Inputs'!$O$59:$O$70,0)),"")) | D42: =IFERROR(INDEX('Inputs'!$V$22:$V$39,MATCH(4,'Inputs'!$X$22:$X$39,0)),IFERROR(INDEX('Inputs'!$N$59:$N$70,MATCH(4,'Inputs'!$O$59:$O$70,0)),""))
B43: =IFERROR(" Bequest: "&INDEX('Inputs'!$B$22:$B$39,MATCH(5,'Inputs'!$X$22:$X$39,0))&IF(INDEX('Inputs'!$I$22:$I$39,MATCH(5,'Inputs'!$X$22:$X$39,0))<>""," ("&INDEX('Inputs'!$I$22:$I$39,MATCH(5,'Inputs'!$X$22:$X$39,0))&")",""),IFERROR(" Policy: "&INDEX('Inputs'!$B$59:$B$70,MATCH(5,'Inputs'!$O$59:$O$70,0))&IF(INDEX('Inputs'!$I$59:$I$70,MATCH(5,'Inputs'!$O$59:$O$70,0))<>""," ("&INDEX('Inputs'!$I$59:$I$70,MATCH(5,'Inputs'!$O$59:$O$70,0))&")",""),"")) | C43: =IFERROR(INDEX('Inputs'!$U$22:$U$39,MATCH(5,'Inputs'!$X$22:$X$39,0)),IFERROR(INDEX('Inputs'!$M$59:$M$70,MATCH(5,'Inputs'!$O$59:$O$70,0)),"")) | D43: =IFERROR(INDEX('Inputs'!$V$22:$V$39,MATCH(5,'Inputs'!$X$22:$X$39,0)),IFERROR(INDEX('Inputs'!$N$59:$N$70,MATCH(5,'Inputs'!$O$59:$O$70,0)),""))
B44: =IFERROR(" Bequest: "&INDEX('Inputs'!$B$22:$B$39,MATCH(6,'Inputs'!$X$22:$X$39,0))&IF(INDEX('Inputs'!$I$22:$I$39,MATCH(6,'Inputs'!$X$22:$X$39,0))<>""," ("&INDEX('Inputs'!$I$22:$I$39,MATCH(6,'Inputs'!$X$22:$X$39,0))&")",""),IFERROR(" Policy: "&INDEX('Inputs'!$B$59:$B$70,MATCH(6,'Inputs'!$O$59:$O$70,0))&IF(INDEX('Inputs'!$I$59:$I$70,MATCH(6,'Inputs'!$O$59:$O$70,0))<>""," ("&INDEX('Inputs'!$I$59:$I$70,MATCH(6,'Inputs'!$O$59:$O$70,0))&")",""),"")) | C44: =IFERROR(INDEX('Inputs'!$U$22:$U$39,MATCH(6,'Inputs'!$X$22:$X$39,0)),IFERROR(INDEX('Inputs'!$M$59:$M$70,MATCH(6,'Inputs'!$O$59:$O$70,0)),"")) | D44: =IFERROR(INDEX('Inputs'!$V$22:$V$39,MATCH(6,'Inputs'!$X$22:$X$39,0)),IFERROR(INDEX('Inputs'!$N$59:$N$70,MATCH(6,'Inputs'!$O$59:$O$70,0)),""))
B45: Less duty the executor recovers from named people (policies and bequests) | C45: =-(SUM('Inputs'!$M$59:$M$70)+SUM('Inputs'!$U$22:$U$39)) | D45: =-(SUM('Inputs'!$N$59:$N$70)+SUM('Inputs'!$V$22:$V$39))
B46: Estate duty borne by the estate | C46: =C36+C45 | D46: =D36+D45
B47: If the executor cannot recover it from them, the estate pays it.
B49: 3. Does the estate have enough cash? | C49: Today | D49: With the plan
B50: Funeral, Master's fees and sundries | C50: =-(C25+C26+C27) | D50: =-(D25+D26+D27)
B51: Executor's fees | C51: =-C28 | D51: =-D28
B52: Property transfer costs / conveyancing | C52: =-C29 | D52: =-D29
B53: Agent's commission | C53: =-C30 | D53: =-D30
B54: Capital gains tax on death | C54: =C16 | D54: =D16
B55: Estate duty borne by the estate | C55: =C46 | D55: =D46
B56: Cost of winding up, before debts | C56: =ROUND(SUM(C50:C55),2) | D56: =ROUND(SUM(D50:D55),2)
B57: ="Less paid by the Legacy plan: "&IF(AND(ISNUMBER('Inputs'!$C$100),'Inputs'!$C$100>0),FIXED(N('Inputs'!$C$102),0)&"% of the executor's fee and conveyancing, up to R "&FIXED(N('Inputs'!$C$103),2),"no quote entered") | C57: =0 | D57: =IF(AND(ISNUMBER('Inputs'!$C$100),'Inputs'!$C$100>0),-ROUND(MIN(N('Inputs'!$C$102)/100*(D51+D52),N('Inputs'!$C$103)),2),0)
B58: Paid by the estate | C58: =ROUND(C56+C57,2) | D58: =ROUND(D56+D57,2)
B59: Debts | C59: =-C24 | D59: =-D24
B60: Cash the executor needs | C60: =ROUND(C58+C59,2) | D60: =ROUND(D58+D59,2)
B61: Cash and deposits, and investments the executor cashes in | C61: =ROUND(SUM('Inputs'!$O$22:$O$39),2) | D61: =ROUND(SUM('Inputs'!$O$22:$O$39),2)
B62: Life cover paid into the estate | C62: =C20 | D62: =D20
B63: Cash the executor has | C63: =C61+C62 | D63: =D61+D62
B64: Shortfall | C64: =ROUND(MAX(0,C60-C63),2) | D64: =ROUND(MAX(0,D60-D63),2)
B65: Cash left over | C65: =ROUND(MAX(0,C63-C60),2) | D65: =ROUND(MAX(0,D63-D60),2)
B66: Left from the estate for everyone who inherits from it, if they pay any shortfall in | C66: =ROUND(C21-C60,2) | D66: =ROUND(D21-D60,2)
B68: ="Our standard assumptions: executor "&IF(ROUND('Inputs'!$C$108,0)='Inputs'!$C$108,FIXED('Inputs'!$C$108,0),IF(ROUND('Inputs'!$C$108,1)='Inputs'!$C$108,FIXED('Inputs'!$C$108,1),FIXED('Inputs'!$C$108,2)))&"%"&" plus VAT unless Capital Legacy acts; Master's fees R "&FIXED('Inputs'!$C$110,0)&"; funeral R "&FIXED('Inputs'!$C$111,0)&"; sundries R "&FIXED('Inputs'!$C$112,0)&"; property transfer costs "&IF(ROUND('Inputs'!$C$113,0)='Inputs'!$C$113,FIXED('Inputs'!$C$113,0),IF(ROUND('Inputs'!$C$113,1)='Inputs'!$C$113,FIXED('Inputs'!$C$113,1),FIXED('Inputs'!$C$113,2)))&"%"&" of value; agent's commission "&IF(ROUND('Inputs'!$C$114,0)='Inputs'!$C$114,FIXED('Inputs'!$C$114,0),IF(ROUND('Inputs'!$C$114,1)='Inputs'!$C$114,FIXED('Inputs'!$C$114,1),FIXED('Inputs'!$C$114,2)))&"%"&" plus VAT on a property sold; estate duty "&IF(ROUND('Inputs'!$C$116,0)='Inputs'!$C$116,FIXED('Inputs'!$C$116,0),IF(ROUND('Inputs'!$C$116,1)='Inputs'!$C$116,FIXED('Inputs'!$C$116,1),FIXED('Inputs'!$C$116,2)))&"%"&" above R "&FIXED('Inputs'!$C$115,0)&"; 2027 tax tables. Capital gains tax on death (s.9HA): everything treated as sold at its value; assets left to a spouse roll over (no tax now). The Capital Legacy fees stay deductible for estate duty, although the plan pays them."

Sheet Needs workings
B1: Duwalcoe Financial Consultants CC
B2: FSP 9978 | clinton@duwalcoe.co.za | 083 608 5617
B4: Workings: the life cover need
B5: Adviser reference and compliance record. Same basis as the full FNA calculator.
B6: 1. Each dependant today
C7: =IF('Inputs'!$B$89="","",'Inputs'!$B$89) | D7: =IF('Inputs'!$B$90="","",'Inputs'!$B$90) | E7: =IF('Inputs'!$B$91="","",'Inputs'!$B$91) | F7: =IF('Inputs'!$B$92="","",'Inputs'!$B$92) | G7: =IF('Inputs'!$B$93="","",'Inputs'!$B$93) | H7: =IF('Inputs'!$B$94="","",'Inputs'!$B$94)
B8: Needs a month from this money (after tax) | C8: =IF('Inputs'!$B$89="","",N('Inputs'!$E$89)) | D8: =IF('Inputs'!$B$90="","",N('Inputs'!$E$90)) | E8: =IF('Inputs'!$B$91="","",N('Inputs'!$E$91)) | F8: =IF('Inputs'!$B$92="","",N('Inputs'!$E$92)) | G8: =IF('Inputs'!$B$93="","",N('Inputs'!$E$93)) | H8: =IF('Inputs'!$B$94="","",N('Inputs'!$E$94))
B9: For how many years | C9: =IF('Inputs'!$B$89="","",'Needs years'!$C$8) | D9: =IF('Inputs'!$B$90="","",'Needs years'!$C$64) | E9: =IF('Inputs'!$B$91="","",'Needs years'!$C$120) | F9: =IF('Inputs'!$B$92="","",'Needs years'!$C$176) | G9: =IF('Inputs'!$B$93="","",'Needs years'!$C$232) | H9: =IF('Inputs'!$B$94="","",'Needs years'!$C$288)
B10: Rising each year by | C10: =IF('Inputs'!$B$89="","",'Needs years'!$C$10) | D10: =IF('Inputs'!$B$90="","",'Needs years'!$C$66) | E10: =IF('Inputs'!$B$91="","",'Needs years'!$C$122) | F10: =IF('Inputs'!$B$92="","",'Needs years'!$C$178) | G10: =IF('Inputs'!$B$93="","",'Needs years'!$C$234) | H10: =IF('Inputs'!$B$94="","",'Needs years'!$C$290)
B11: Retirement money into a living annuity in their name | C11: =IF('Inputs'!$B$89="","",'Needs years'!$C$7) | D11: =IF('Inputs'!$B$90="","",'Needs years'!$C$63) | E11: =IF('Inputs'!$B$91="","",'Needs years'!$C$119) | F11: =IF('Inputs'!$B$92="","",'Needs years'!$C$175) | G11: =IF('Inputs'!$B$93="","",'Needs years'!$C$231) | H11: =IF('Inputs'!$B$94="","",'Needs years'!$C$287)
B12: It pays in the first year, after tax (a month) | C12: =IF('Inputs'!$B$89="","",'Needs years'!$C$15/12) | D12: =IF('Inputs'!$B$90="","",'Needs years'!$C$71/12) | E12: =IF('Inputs'!$B$91="","",'Needs years'!$C$127/12) | F12: =IF('Inputs'!$B$92="","",'Needs years'!$C$183/12) | G12: =IF('Inputs'!$B$93="","",'Needs years'!$C$239/12) | H12: =IF('Inputs'!$B$94="","",'Needs years'!$C$295/12)
B13: Capital invested for them (residue, policies, the trust) | C13: =IF('Inputs'!$B$89="","",'Needs calc'!$C$46) | D13: =IF('Inputs'!$B$90="","",'Needs calc'!$C$53) | E13: =IF('Inputs'!$B$91="","",'Needs calc'!$C$60) | F13: =IF('Inputs'!$B$92="","",'Needs calc'!$C$67) | G13: =IF('Inputs'!$B$93="","",'Needs calc'!$C$74) | H13: =IF('Inputs'!$B$94="","",'Needs calc'!$C$81)
B14: Their marginal tax rate (unit trust basis) | C14: =IF('Inputs'!$B$89="","",'Needs calc'!$C$48) | D14: =IF('Inputs'!$B$90="","",'Needs calc'!$C$55) | E14: =IF('Inputs'!$B$91="","",'Needs calc'!$C$62) | F14: =IF('Inputs'!$B$92="","",'Needs calc'!$C$69) | G14: =IF('Inputs'!$B$93="","",'Needs calc'!$C$76) | H14: =IF('Inputs'!$B$94="","",'Needs calc'!$C$83)
B15: Net rate: 7% less tax and trustee fees | C15: =IF('Inputs'!$B$89="","",'Needs calc'!$C$49) | D15: =IF('Inputs'!$B$90="","",'Needs calc'!$C$56) | E15: =IF('Inputs'!$B$91="","",'Needs calc'!$C$63) | F15: =IF('Inputs'!$B$92="","",'Needs calc'!$C$70) | G15: =IF('Inputs'!$B$93="","",'Needs calc'!$C$77) | H15: =IF('Inputs'!$B$94="","",'Needs calc'!$C$84)
B16: Capital needed today (invested part) | C16: =IF('Inputs'!$B$89="","",'Needs calc'!$C$50) | D16: =IF('Inputs'!$B$90="","",'Needs calc'!$C$57) | E16: =IF('Inputs'!$B$91="","",'Needs calc'!$C$64) | F16: =IF('Inputs'!$B$92="","",'Needs calc'!$C$71) | G16: =IF('Inputs'!$B$93="","",'Needs calc'!$C$78) | H16: =IF('Inputs'!$B$94="","",'Needs calc'!$C$85)
B17: Shortfall (negative: over) | C17: =IF('Inputs'!$B$89="","",'Needs calc'!$C$51) | D17: =IF('Inputs'!$B$90="","",'Needs calc'!$C$58) | E17: =IF('Inputs'!$B$91="","",'Needs calc'!$C$65) | F17: =IF('Inputs'!$B$92="","",'Needs calc'!$C$72) | G17: =IF('Inputs'!$B$93="","",'Needs calc'!$C$79) | H17: =IF('Inputs'!$B$94="","",'Needs calc'!$C$86)
B18: Monthly income in place (first year) | C18: =IF('Inputs'!$B$89="","",'Needs calc'!$C$52) | D18: =IF('Inputs'!$B$90="","",'Needs calc'!$C$59) | E18: =IF('Inputs'!$B$91="","",'Needs calc'!$C$66) | F18: =IF('Inputs'!$B$92="","",'Needs calc'!$C$73) | G18: =IF('Inputs'!$B$93="","",'Needs calc'!$C$80) | H18: =IF('Inputs'!$B$94="","",'Needs calc'!$C$87)
B20: 2. Life cover to close each gap (nominated for them, sized by rerunning the estate)
C21: =IF('Inputs'!$B$89="","",'Inputs'!$B$89) | D21: =IF('Inputs'!$B$90="","",'Inputs'!$B$90) | E21: =IF('Inputs'!$B$91="","",'Inputs'!$B$91) | F21: =IF('Inputs'!$B$92="","",'Inputs'!$B$92) | G21: =IF('Inputs'!$B$93="","",'Inputs'!$B$93) | H21: =IF('Inputs'!$B$94="","",'Inputs'!$B$94)
B22: New cover for them | C22: =IF('Inputs'!$B$89="","",'Needs calc'!$T$7) | D22: =IF('Inputs'!$B$90="","",'Needs calc'!$T$8) | E22: =IF('Inputs'!$B$91="","",'Needs calc'!$T$9) | F22: =IF('Inputs'!$B$92="","",'Needs calc'!$T$10) | G22: =IF('Inputs'!$B$93="","",'Needs calc'!$T$11) | H22: =IF('Inputs'!$B$94="","",'Needs calc'!$T$12)
B23: Capital after the cover (after its estate duty) | C23: =IF('Inputs'!$B$89="","",'Needs calc'!$T$46) | D23: =IF('Inputs'!$B$90="","",'Needs calc'!$T$53) | E23: =IF('Inputs'!$B$91="","",'Needs calc'!$T$60) | F23: =IF('Inputs'!$B$92="","",'Needs calc'!$T$67) | G23: =IF('Inputs'!$B$93="","",'Needs calc'!$T$74) | H23: =IF('Inputs'!$B$94="","",'Needs calc'!$T$81)
B24: Marginal tax rate then | C24: =IF('Inputs'!$B$89="","",'Needs calc'!$T$48) | D24: =IF('Inputs'!$B$90="","",'Needs calc'!$T$55) | E24: =IF('Inputs'!$B$91="","",'Needs calc'!$T$62) | F24: =IF('Inputs'!$B$92="","",'Needs calc'!$T$69) | G24: =IF('Inputs'!$B$93="","",'Needs calc'!$T$76) | H24: =IF('Inputs'!$B$94="","",'Needs calc'!$T$83)
B25: Capital needed then | C25: =IF('Inputs'!$B$89="","",'Needs calc'!$T$50) | D25: =IF('Inputs'!$B$90="","",'Needs calc'!$T$57) | E25: =IF('Inputs'!$B$91="","",'Needs calc'!$T$64) | F25: =IF('Inputs'!$B$92="","",'Needs calc'!$T$71) | G25: =IF('Inputs'!$B$93="","",'Needs calc'!$T$78) | H25: =IF('Inputs'!$B$94="","",'Needs calc'!$T$85)
B26: Remaining shortfall | C26: =IF('Inputs'!$B$89="","",'Needs calc'!$T$51) | D26: =IF('Inputs'!$B$90="","",'Needs calc'!$T$58) | E26: =IF('Inputs'!$B$91="","",'Needs calc'!$T$65) | F26: =IF('Inputs'!$B$92="","",'Needs calc'!$T$72) | G26: =IF('Inputs'!$B$93="","",'Needs calc'!$T$79) | H26: =IF('Inputs'!$B$94="","",'Needs calc'!$T$86)
B27: Cover for the family pot | C27: ='Needs calc'!$T$13
B28: Estate duty with the new cover / average rate | C28: ='Needs calc'!$T$20 | D28: ='Needs calc'!$T$21
B29: Left in the estate for the heirs, with the new cover | C29: ='Needs calc'!$T$27
B31: 3. Trustee fees (2% a year of what the trust holds for them)
C32: =IF('Inputs'!$B$89="","",'Inputs'!$B$89) | D32: =IF('Inputs'!$B$90="","",'Inputs'!$B$90) | E32: =IF('Inputs'!$B$91="","",'Inputs'!$B$91) | F32: =IF('Inputs'!$B$92="","",'Inputs'!$B$92) | G32: =IF('Inputs'!$B$93="","",'Inputs'!$B$93) | H32: =IF('Inputs'!$B$94="","",'Inputs'!$B$94)
B33: Fees in the first year | C33: =IF('Inputs'!$B$89="","",'Needs years'!$C$17) | D33: =IF('Inputs'!$B$90="","",'Needs years'!$C$73) | E33: =IF('Inputs'!$B$91="","",'Needs years'!$C$129) | F33: =IF('Inputs'!$B$92="","",'Needs years'!$C$185) | G33: =IF('Inputs'!$B$93="","",'Needs years'!$C$241) | H33: =IF('Inputs'!$B$94="","",'Needs years'!$C$297)
B34: Fees over the whole period | C34: =IF('Inputs'!$B$89="","",'Needs years'!$C$18) | D34: =IF('Inputs'!$B$90="","",'Needs years'!$C$74) | E34: =IF('Inputs'!$B$91="","",'Needs years'!$C$130) | F34: =IF('Inputs'!$B$92="","",'Needs years'!$C$186) | G34: =IF('Inputs'!$B$93="","",'Needs years'!$C$242) | H34: =IF('Inputs'!$B$94="","",'Needs years'!$C$298)
B35: Extra capital needed today for the fees (in the need above) | C35: =IF('Inputs'!$B$89="","",'Needs years'!$C$19) | D35: =IF('Inputs'!$B$90="","",'Needs years'!$C$75) | E35: =IF('Inputs'!$B$91="","",'Needs years'!$C$131) | F35: =IF('Inputs'!$B$92="","",'Needs years'!$C$187) | G35: =IF('Inputs'!$B$93="","",'Needs years'!$C$243) | H35: =IF('Inputs'!$B$94="","",'Needs years'!$C$299)
B37: 4. The estate's own gap
B38: Executor's cash shortfall today | C38: ='Workings'!$C$64
B39: Route 1: cover paid to the estate (charged executor's fees and estate duty, rerun to the cent) | C39: ='Needs years'!$C$377
B40: Route 1 reconciled to the cent (no gap at this cover, a gap at a cent less) | C40: ='Needs years'!$C$378
B41: Route 2: cover nominated to the spouse, who pays the costs (no fees, no duty) | C41: =IF(AND(OR(LEFT('Inputs'!$C$13,7)="Married",'Inputs'!$C$13="Life partner",'Inputs'!$C$13="Civil Union"),'Workings'!$C$64>0),'Workings'!$C$64,0)
B43: ="Basis: income needs are net. Capital invested for a dependant earns "&FIXED('Inputs'!$C$122,1)&"% a year before tax as a unit trust, taxed in their hands: E(m) = "&FIXED('Inputs'!$H$110,2)&"% x m + "&FIXED('Inputs'!$H$111,2)&"% x "&FIXED('Inputs'!$H$113,0)&"% + "&FIXED('Inputs'!$H$112,2)&"% x "&FIXED('Inputs'!$C$120,0)&"% x m, with m from their own income plus the taxable part of the first year's return (and any annuity drawdown), less trustee fees of "&FIXED('Inputs'!$H$108,1)&"% a year while in a trust. Retirement money paid to a dependant goes into a living annuity in their name and pays first, within "&FIXED('Inputs'!$H$115,1)&"% to "&FIXED('Inputs'!$H$116,1)&"% a year, taxed as their income with the rebates for their age; the invested capital pays the rest. Retirement money paid to the children's trust is paid out as a lump sum, taxed on the death benefit table. Payments are monthly in advance from the date of death, rising at each anniversary. Rebates, the interest exemption and the annual CGT exclusion are left out of the unit trust tax, so it is slightly overstated: an estimate."

Sheet Needs calc
C2: T | E2: V | V2: O1 | AM2: O2 | BD2: O3
B3: close | C3: =0 | E3: =1 | F3: =1 | G3: =1 | H3: =1 | I3: =1 | J3: =1 | K3: =1 | L3: =1 | ... T3: =1 | V3: =IFERROR(MATCH('Options'!$D$10,'Lists'!$I$2:$I$5,0)-1,0) | W3: =IFERROR(MATCH('Options'!$D$10,'Lists'!$I$2:$I$5,0)-1,0) | X3: =IFERROR(MATCH('Options'!$D$10,'Lists'!$I$2:$I$5,0)-1,0) | Y3: =IFERROR(MATCH('Options'!$D$10,'Lists'!$I$2:$I$5,0)-1,0) | Z3: =IFERROR(MATCH('Options'!$D$10,'Lists'!$I$2:$I$5,0)-1,0) | AA3: =IFERROR(MATCH('Options'!$D$10,'Lists'!$I$2:$I$5,0)-1,0) | AB3: =IFERROR(MATCH('Options'!$D$10,'Lists'!$I$2:$I$5,0)-1,0) | AC3: =IFERROR(MATCH('Options'!$D$10,'Lists'!$I$2:$I$5,0)-1,0) | ... AK3: =IFERROR(MATCH('Options'!$D$10,'Lists'!$I$2:$I$5,0)-1,0) | AM3: =IFERROR(MATCH('Options'!$E$10,'Lists'!$I$2:$I$5,0)-1,0) | AN3: =IFERROR(MATCH('Options'!$E$10,'Lists'!$I$2:$I$5,0)-1,0) | AO3: =IFERROR(MATCH('Options'!$E$10,'Lists'!$I$2:$I$5,0)-1,0) | AP3: =IFERROR(MATCH('Options'!$E$10,'Lists'!$I$2:$I$5,0)-1,0) | AQ3: =IFERROR(MATCH('Options'!$E$10,'Lists'!$I$2:$I$5,0)-1,0) | AR3: =IFERROR(MATCH('Options'!$E$10,'Lists'!$I$2:$I$5,0)-1,0) | AS3: =IFERROR(MATCH('Options'!$E$10,'Lists'!$I$2:$I$5,0)-1,0) | AT3: =IFERROR(MATCH('Options'!$E$10,'Lists'!$I$2:$I$5,0)-1,0) | ... BB3: =IFERROR(MATCH('Options'!$E$10,'Lists'!$I$2:$I$5,0)-1,0) | BD3: =IFERROR(MATCH('Options'!$F$10,'Lists'!$I$2:$I$5,0)-1,0) | BE3: =IFERROR(MATCH('Options'!$F$10,'Lists'!$I$2:$I$5,0)-1,0) | BF3: =IFERROR(MATCH('Options'!$F$10,'Lists'!$I$2:$I$5,0)-1,0) | BG3: =IFERROR(MATCH('Options'!$F$10,'Lists'!$I$2:$I$5,0)-1,0) | BH3: =IFERROR(MATCH('Options'!$F$10,'Lists'!$I$2:$I$5,0)-1,0) | BI3: =IFERROR(MATCH('Options'!$F$10,'Lists'!$I$2:$I$5,0)-1,0) | BJ3: =IFERROR(MATCH('Options'!$F$10,'Lists'!$I$2:$I$5,0)-1,0) | BK3: =IFERROR(MATCH('Options'!$F$10,'Lists'!$I$2:$I$5,0)-1,0) | ... BS3: =IFERROR(MATCH('Options'!$F$10,'Lists'!$I$2:$I$5,0)-1,0)
B4: pot | C4: =IF(AND('Inputs'!$C$95="As one family pot",SUM('Inputs'!$Q$89:$Q$94)>0),1,0) | E4: =IF(AND('Inputs'!$C$95="As one family pot",SUM('Inputs'!$Q$89:$Q$94)>0),1,0) | F4: =IF(AND('Inputs'!$C$95="As one family pot",SUM('Inputs'!$Q$89:$Q$94)>0),1,0) | G4: =IF(AND('Inputs'!$C$95="As one family pot",SUM('Inputs'!$Q$89:$Q$94)>0),1,0) | H4: =IF(AND('Inputs'!$C$95="As one family pot",SUM('Inputs'!$Q$89:$Q$94)>0),1,0) | I4: =IF(AND('Inputs'!$C$95="As one family pot",SUM('Inputs'!$Q$89:$Q$94)>0),1,0) | J4: =IF(AND('Inputs'!$C$95="As one family pot",SUM('Inputs'!$Q$89:$Q$94)>0),1,0) | K4: =IF(AND('Inputs'!$C$95="As one family pot",SUM('Inputs'!$Q$89:$Q$94)>0),1,0) | L4: =IF(AND('Inputs'!$C$95="As one family pot",SUM('Inputs'!$Q$89:$Q$94)>0),1,0) | ... T4: =IF(AND('Inputs'!$C$95="As one family pot",SUM('Inputs'!$Q$89:$Q$94)>0),1,0) | V4: =IF(AND('Options'!$D$9="One family pot",SUM('Inputs'!$Q$89:$Q$94)>0),1,0) | W4: =IF(AND('Options'!$D$9="One family pot",SUM('Inputs'!$Q$89:$Q$94)>0),1,0) | X4: =IF(AND('Options'!$D$9="One family pot",SUM('Inputs'!$Q$89:$Q$94)>0),1,0) | Y4: =IF(AND('Options'!$D$9="One family pot",SUM('Inputs'!$Q$89:$Q$94)>0),1,0) | Z4: =IF(AND('Options'!$D$9="One family pot",SUM('Inputs'!$Q$89:$Q$94)>0),1,0) | AA4: =IF(AND('Options'!$D$9="One family pot",SUM('Inputs'!$Q$89:$Q$94)>0),1,0) | AB4: =IF(AND('Options'!$D$9="One family pot",SUM('Inputs'!$Q$89:$Q$94)>0),1,0) | AC4: =IF(AND('Options'!$D$9="One family pot",SUM('Inputs'!$Q$89:$Q$94)>0),1,0) | ... AK4: =IF(AND('Options'!$D$9="One family pot",SUM('Inputs'!$Q$89:$Q$94)>0),1,0) | AM4: =IF(AND('Options'!$E$9="One family pot",SUM('Inputs'!$Q$89:$Q$94)>0),1,0) | AN4: =IF(AND('Options'!$E$9="One family pot",SUM('Inputs'!$Q$89:$Q$94)>0),1,0) | AO4: =IF(AND('Options'!$E$9="One family pot",SUM('Inputs'!$Q$89:$Q$94)>0),1,0) | AP4: =IF(AND('Options'!$E$9="One family pot",SUM('Inputs'!$Q$89:$Q$94)>0),1,0) | AQ4: =IF(AND('Options'!$E$9="One family pot",SUM('Inputs'!$Q$89:$Q$94)>0),1,0) | AR4: =IF(AND('Options'!$E$9="One family pot",SUM('Inputs'!$Q$89:$Q$94)>0),1,0) | AS4: =IF(AND('Options'!$E$9="One family pot",SUM('Inputs'!$Q$89:$Q$94)>0),1,0) | AT4: =IF(AND('Options'!$E$9="One family pot",SUM('Inputs'!$Q$89:$Q$94)>0),1,0) | ... BB4: =IF(AND('Options'!$E$9="One family pot",SUM('Inputs'!$Q$89:$Q$94)>0),1,0) | BD4: =IF(AND('Options'!$F$9="One family pot",SUM('Inputs'!$Q$89:$Q$94)>0),1,0) | BE4: =IF(AND('Options'!$F$9="One family pot",SUM('Inputs'!$Q$89:$Q$94)>0),1,0) | BF4: =IF(AND('Options'!$F$9="One family pot",SUM('Inputs'!$Q$89:$Q$94)>0),1,0) | BG4: =IF(AND('Options'!$F$9="One family pot",SUM('Inputs'!$Q$89:$Q$94)>0),1,0) | BH4: =IF(AND('Options'!$F$9="One family pot",SUM('Inputs'!$Q$89:$Q$94)>0),1,0) | BI4: =IF(AND('Options'!$F$9="One family pot",SUM('Inputs'!$Q$89:$Q$94)>0),1,0) | BJ4: =IF(AND('Options'!$F$9="One family pot",SUM('Inputs'!$Q$89:$Q$94)>0),1,0) | BK4: =IF(AND('Options'!$F$9="One family pot",SUM('Inputs'!$Q$89:$Q$94)>0),1,0) | ... BS4: =IF(AND('Options'!$F$9="One family pot",SUM('Inputs'!$Q$89:$Q$94)>0),1,0)
B5: src | C5: =IF(0=0,0,IF(OR(INDEX('Inputs'!$C$59:$C$70,0)="Estate",INDEX('Inputs'!$E$59:$E$70,0)="No"),0,0)) | E5: =IF(0=0,0,IF(OR(INDEX('Inputs'!$C$59:$C$70,0)="Estate",INDEX('Inputs'!$E$59:$E$70,0)="No"),0,0)) | F5: =IF(0=0,0,IF(OR(INDEX('Inputs'!$C$59:$C$70,0)="Estate",INDEX('Inputs'!$E$59:$E$70,0)="No"),0,0)) | G5: =IF(0=0,0,IF(OR(INDEX('Inputs'!$C$59:$C$70,0)="Estate",INDEX('Inputs'!$E$59:$E$70,0)="No"),0,0)) | H5: =IF(0=0,0,IF(OR(INDEX('Inputs'!$C$59:$C$70,0)="Estate",INDEX('Inputs'!$E$59:$E$70,0)="No"),0,0)) | I5: =IF(0=0,0,IF(OR(INDEX('Inputs'!$C$59:$C$70,0)="Estate",INDEX('Inputs'!$E$59:$E$70,0)="No"),0,0)) | J5: =IF(0=0,0,IF(OR(INDEX('Inputs'!$C$59:$C$70,0)="Estate",INDEX('Inputs'!$E$59:$E$70,0)="No"),0,0)) | K5: =IF(0=0,0,IF(OR(INDEX('Inputs'!$C$59:$C$70,0)="Estate",INDEX('Inputs'!$E$59:$E$70,0)="No"),0,0)) | L5: =IF(0=0,0,IF(OR(INDEX('Inputs'!$C$59:$C$70,0)="Estate",INDEX('Inputs'!$E$59:$E$70,0)="No"),0,0)) | ... T5: =IF(0=0,0,IF(OR(INDEX('Inputs'!$C$59:$C$70,0)="Estate",INDEX('Inputs'!$E$59:$E$70,0)="No"),0,0)) | V5: =IF(IF(IFERROR(MATCH('Options'!$D$10,'Lists'!$I$2:$I$5,0)-1,0)>=2,IFERROR(MATCH('Options'!$D$11,'Inputs'!$B$59:$B$70,0),0),0)=0,0,IF(OR(INDEX('Inputs'!$C$59:$C$70,IF(IFERROR(MATCH('Options'!$D$10,'Lists'!$I$2:$I$5,0)-1,0)>=2,IFERROR(MATCH('Options'!$D$11,'Inputs'!$B$59:$B$70,0),0),0))="Estate",INDEX('Inputs'!$E$59:$E$70,IF(IFERROR(MATCH('Options'!$D$10,'Lists'!$I$2:$I$5,0)-1,0)>=2,IFERROR(MATCH('Options'!$D$11,'Inputs'!$B$59:$B$70,0),0),0))="No"),0,IF(IFERROR(MATCH('Options'!$D$10,'Lists'!$I$2:$I$5,0)-1,0)>=2,IFERROR(MATCH('Options'!$D$11,'Inputs'!$B$59:$B$70,0),0),0))) | W5: =IF(IF(IFERROR(MATCH('Options'!$D$10,'Lists'!$I$2:$I$5,0)-1,0)>=2,IFERROR(MATCH('Options'!$D$11,'Inputs'!$B$59:$B$70,0),0),0)=0,0,IF(OR(INDEX('Inputs'!$C$59:$C$70,IF(IFERROR(MATCH('Options'!$D$10,'Lists'!$I$2:$I$5,0)-1,0)>=2,IFERROR(MATCH('Options'!$D$11,'Inputs'!$B$59:$B$70,0),0),0))="Estate",INDEX('Inputs'!$E$59:$E$70,IF(IFERROR(MATCH('Options'!$D$10,'Lists'!$I$2:$I$5,0)-1,0)>=2,IFERROR(MATCH('Options'!$D$11,'Inputs'!$B$59:$B$70,0),0),0))="No"),0,IF(IFERROR(MATCH('Options'!$D$10,'Lists'!$I$2:$I$5,0)-1,0)>=2,IFERROR(MATCH('Options'!$D$11,'Inputs'!$B$59:$B$70,0),0),0))) | X5: =IF(IF(IFERROR(MATCH('Options'!$D$10,'Lists'!$I$2:$I$5,0)-1,0)>=2,IFERROR(MATCH('Options'!$D$11,'Inputs'!$B$59:$B$70,0),0),0)=0,0,IF(OR(INDEX('Inputs'!$C$59:$C$70,IF(IFERROR(MATCH('Options'!$D$10,'Lists'!$I$2:$I$5,0)-1,0)>=2,IFERROR(MATCH('Options'!$D$11,'Inputs'!$B$59:$B$70,0),0),0))="Estate",INDEX('Inputs'!$E$59:$E$70,IF(IFERROR(MATCH('Options'!$D$10,'Lists'!$I$2:$I$5,0)-1,0)>=2,IFERROR(MATCH('Options'!$D$11,'Inputs'!$B$59:$B$70,0),0),0))="No"),0,IF(IFERROR(MATCH('Options'!$D$10,'Lists'!$I$2:$I$5,0)-1,0)>=2,IFERROR(MATCH('Options'!$D$11,'Inputs'!$B$59:$B$70,0),0),0))) | Y5: =IF(IF(IFERROR(MATCH('Options'!$D$10,'Lists'!$I$2:$I$5,0)-1,0)>=2,IFERROR(MATCH('Options'!$D$11,'Inputs'!$B$59:$B$70,0),0),0)=0,0,IF(OR(INDEX('Inputs'!$C$59:$C$70,IF(IFERROR(MATCH('Options'!$D$10,'Lists'!$I$2:$I$5,0)-1,0)>=2,IFERROR(MATCH('Options'!$D$11,'Inputs'!$B$59:$B$70,0),0),0))="Estate",INDEX('Inputs'!$E$59:$E$70,IF(IFERROR(MATCH('Options'!$D$10,'Lists'!$I$2:$I$5,0)-1,0)>=2,IFERROR(MATCH('Options'!$D$11,'Inputs'!$B$59:$B$70,0),0),0))="No"),0,IF(IFERROR(MATCH('Options'!$D$10,'Lists'!$I$2:$I$5,0)-1,0)>=2,IFERROR(MATCH('Options'!$D$11,'Inputs'!$B$59:$B$70,0),0),0))) | Z5: =IF(IF(IFERROR(MATCH('Options'!$D$10,'Lists'!$I$2:$I$5,0)-1,0)>=2,IFERROR(MATCH('Options'!$D$11,'Inputs'!$B$59:$B$70,0),0),0)=0,0,IF(OR(INDEX('Inputs'!$C$59:$C$70,IF(IFERROR(MATCH('Options'!$D$10,'Lists'!$I$2:$I$5,0)-1,0)>=2,IFERROR(MATCH('Options'!$D$11,'Inputs'!$B$59:$B$70,0),0),0))="Estate",INDEX('Inputs'!$E$59:$E$70,IF(IFERROR(MATCH('Options'!$D$10,'Lists'!$I$2:$I$5,0)-1,0)>=2,IFERROR(MATCH('Options'!$D$11,'Inputs'!$B$59:$B$70,0),0),0))="No"),0,IF(IFERROR(MATCH('Options'!$D$10,'Lists'!$I$2:$I$5,0)-1,0)>=2,IFERROR(MATCH('Options'!$D$11,'Inputs'!$B$59:$B$70,0),0),0))) | AA5: =IF(IF(IFERROR(MATCH('Options'!$D$10,'Lists'!$I$2:$I$5,0)-1,0)>=2,IFERROR(MATCH('Options'!$D$11,'Inputs'!$B$59:$B$70,0),0),0)=0,0,IF(OR(INDEX('Inputs'!$C$59:$C$70,IF(IFERROR(MATCH('Options'!$D$10,'Lists'!$I$2:$I$5,0)-1,0)>=2,IFERROR(MATCH('Options'!$D$11,'Inputs'!$B$59:$B$70,0),0),0))="Estate",INDEX('Inputs'!$E$59:$E$70,IF(IFERROR(MATCH('Options'!$D$10,'Lists'!$I$2:$I$5,0)-1,0)>=2,IFERROR(MATCH('Options'!$D$11,'Inputs'!$B$59:$B$70,0),0),0))="No"),0,IF(IFERROR(MATCH('Options'!$D$10,'Lists'!$I$2:$I$5,0)-1,0)>=2,IFERROR(MATCH('Options'!$D$11,'Inputs'!$B$59:$B$70,0),0),0))) | AB5: =IF(IF(IFERROR(MATCH('Options'!$D$10,'Lists'!$I$2:$I$5,0)-1,0)>=2,IFERROR(MATCH('Options'!$D$11,'Inputs'!$B$59:$B$70,0),0),0)=0,0,IF(OR(INDEX('Inputs'!$C$59:$C$70,IF(IFERROR(MATCH('Options'!$D$10,'Lists'!$I$2:$I$5,0)-1,0)>=2,IFERROR(MATCH('Options'!$D$11,'Inputs'!$B$59:$B$70,0),0),0))="Estate",INDEX('Inputs'!$E$59:$E$70,IF(IFERROR(MATCH('Options'!$D$10,'Lists'!$I$2:$I$5,0)-1,0)>=2,IFERROR(MATCH('Options'!$D$11,'Inputs'!$B$59:$B$70,0),0),0))="No"),0,IF(IFERROR(MATCH('Options'!$D$10,'Lists'!$I$2:$I$5,0)-1,0)>=2,IFERROR(MATCH('Options'!$D$11,'Inputs'!$B$59:$B$70,0),0),0))) | AC5: =IF(IF(IFERROR(MATCH('Options'!$D$10,'Lists'!$I$2:$I$5,0)-1,0)>=2,IFERROR(MATCH('Options'!$D$11,'Inputs'!$B$59:$B$70,0),0),0)=0,0,IF(OR(INDEX('Inputs'!$C$59:$C$70,IF(IFERROR(MATCH('Options'!$D$10,'Lists'!$I$2:$I$5,0)-1,0)>=2,IFERROR(MATCH('Options'!$D$11,'Inputs'!$B$59:$B$70,0),0),0))="Estate",INDEX('Inputs'!$E$59:$E$70,IF(IFERROR(MATCH('Options'!$D$10,'Lists'!$I$2:$I$5,0)-1,0)>=2,IFERROR(MATCH('Options'!$D$11,'Inputs'!$B$59:$B$70,0),0),0))="No"),0,IF(IFERROR(MATCH('Options'!$D$10,'Lists'!$I$2:$I$5,0)-1,0)>=2,IFERROR(MATCH('Options'!$D$11,'Inputs'!$B$59:$B$70,0),0),0))) | ... AK5: =IF(IF(IFERROR(MATCH('Options'!$D$10,'Lists'!$I$2:$I$5,0)-1,0)>=2,IFERROR(MATCH('Options'!$D$11,'Inputs'!$B$59:$B$70,0),0),0)=0,0,IF(OR(INDEX('Inputs'!$C$59:$C$70,IF(IFERROR(MATCH('Options'!$D$10,'Lists'!$I$2:$I$5,0)-1,0)>=2,IFERROR(MATCH('Options'!$D$11,'Inputs'!$B$59:$B$70,0),0),0))="Estate",INDEX('Inputs'!$E$59:$E$70,IF(IFERROR(MATCH('Options'!$D$10,'Lists'!$I$2:$I$5,0)-1,0)>=2,IFERROR(MATCH('Options'!$D$11,'Inputs'!$B$59:$B$70,0),0),0))="No"),0,IF(IFERROR(MATCH('Options'!$D$10,'Lists'!$I$2:$I$5,0)-1,0)>=2,IFERROR(MATCH('Options'!$D$11,'Inputs'!$B$59:$B$70,0),0),0))) | AM5: =IF(IF(IFERROR(MATCH('Options'!$E$10,'Lists'!$I$2:$I$5,0)-1,0)>=2,IFERROR(MATCH('Options'!$E$11,'Inputs'!$B$59:$B$70,0),0),0)=0,0,IF(OR(INDEX('Inputs'!$C$59:$C$70,IF(IFERROR(MATCH('Options'!$E$10,'Lists'!$I$2:$I$5,0)-1,0)>=2,IFERROR(MATCH('Options'!$E$11,'Inputs'!$B$59:$B$70,0),0),0))="Estate",INDEX('Inputs'!$E$59:$E$70,IF(IFERROR(MATCH('Options'!$E$10,'Lists'!$I$2:$I$5,0)-1,0)>=2,IFERROR(MATCH('Options'!$E$11,'Inputs'!$B$59:$B$70,0),0),0))="No"),0,IF(IFERROR(MATCH('Options'!$E$10,'Lists'!$I$2:$I$5,0)-1,0)>=2,IFERROR(MATCH('Options'!$E$11,'Inputs'!$B$59:$B$70,0),0),0))) | AN5: =IF(IF(IFERROR(MATCH('Options'!$E$10,'Lists'!$I$2:$I$5,0)-1,0)>=2,IFERROR(MATCH('Options'!$E$11,'Inputs'!$B$59:$B$70,0),0),0)=0,0,IF(OR(INDEX('Inputs'!$C$59:$C$70,IF(IFERROR(MATCH('Options'!$E$10,'Lists'!$I$2:$I$5,0)-1,0)>=2,IFERROR(MATCH('Options'!$E$11,'Inputs'!$B$59:$B$70,0),0),0))="Estate",INDEX('Inputs'!$E$59:$E$70,IF(IFERROR(MATCH('Options'!$E$10,'Lists'!$I$2:$I$5,0)-1,0)>=2,IFERROR(MATCH('Options'!$E$11,'Inputs'!$B$59:$B$70,0),0),0))="No"),0,IF(IFERROR(MATCH('Options'!$E$10,'Lists'!$I$2:$I$5,0)-1,0)>=2,IFERROR(MATCH('Options'!$E$11,'Inputs'!$B$59:$B$70,0),0),0))) | AO5: =IF(IF(IFERROR(MATCH('Options'!$E$10,'Lists'!$I$2:$I$5,0)-1,0)>=2,IFERROR(MATCH('Options'!$E$11,'Inputs'!$B$59:$B$70,0),0),0)=0,0,IF(OR(INDEX('Inputs'!$C$59:$C$70,IF(IFERROR(MATCH('Options'!$E$10,'Lists'!$I$2:$I$5,0)-1,0)>=2,IFERROR(MATCH('Options'!$E$11,'Inputs'!$B$59:$B$70,0),0),0))="Estate",INDEX('Inputs'!$E$59:$E$70,IF(IFERROR(MATCH('Options'!$E$10,'Lists'!$I$2:$I$5,0)-1,0)>=2,IFERROR(MATCH('Options'!$E$11,'Inputs'!$B$59:$B$70,0),0),0))="No"),0,IF(IFERROR(MATCH('Options'!$E$10,'Lists'!$I$2:$I$5,0)-1,0)>=2,IFERROR(MATCH('Options'!$E$11,'Inputs'!$B$59:$B$70,0),0),0))) | AP5: =IF(IF(IFERROR(MATCH('Options'!$E$10,'Lists'!$I$2:$I$5,0)-1,0)>=2,IFERROR(MATCH('Options'!$E$11,'Inputs'!$B$59:$B$70,0),0),0)=0,0,IF(OR(INDEX('Inputs'!$C$59:$C$70,IF(IFERROR(MATCH('Options'!$E$10,'Lists'!$I$2:$I$5,0)-1,0)>=2,IFERROR(MATCH('Options'!$E$11,'Inputs'!$B$59:$B$70,0),0),0))="Estate",INDEX('Inputs'!$E$59:$E$70,IF(IFERROR(MATCH('Options'!$E$10,'Lists'!$I$2:$I$5,0)-1,0)>=2,IFERROR(MATCH('Options'!$E$11,'Inputs'!$B$59:$B$70,0),0),0))="No"),0,IF(IFERROR(MATCH('Options'!$E$10,'Lists'!$I$2:$I$5,0)-1,0)>=2,IFERROR(MATCH('Options'!$E$11,'Inputs'!$B$59:$B$70,0),0),0))) | AQ5: =IF(IF(IFERROR(MATCH('Options'!$E$10,'Lists'!$I$2:$I$5,0)-1,0)>=2,IFERROR(MATCH('Options'!$E$11,'Inputs'!$B$59:$B$70,0),0),0)=0,0,IF(OR(INDEX('Inputs'!$C$59:$C$70,IF(IFERROR(MATCH('Options'!$E$10,'Lists'!$I$2:$I$5,0)-1,0)>=2,IFERROR(MATCH('Options'!$E$11,'Inputs'!$B$59:$B$70,0),0),0))="Estate",INDEX('Inputs'!$E$59:$E$70,IF(IFERROR(MATCH('Options'!$E$10,'Lists'!$I$2:$I$5,0)-1,0)>=2,IFERROR(MATCH('Options'!$E$11,'Inputs'!$B$59:$B$70,0),0),0))="No"),0,IF(IFERROR(MATCH('Options'!$E$10,'Lists'!$I$2:$I$5,0)-1,0)>=2,IFERROR(MATCH('Options'!$E$11,'Inputs'!$B$59:$B$70,0),0),0))) | AR5: =IF(IF(IFERROR(MATCH('Options'!$E$10,'Lists'!$I$2:$I$5,0)-1,0)>=2,IFERROR(MATCH('Options'!$E$11,'Inputs'!$B$59:$B$70,0),0),0)=0,0,IF(OR(INDEX('Inputs'!$C$59:$C$70,IF(IFERROR(MATCH('Options'!$E$10,'Lists'!$I$2:$I$5,0)-1,0)>=2,IFERROR(MATCH('Options'!$E$11,'Inputs'!$B$59:$B$70,0),0),0))="Estate",INDEX('Inputs'!$E$59:$E$70,IF(IFERROR(MATCH('Options'!$E$10,'Lists'!$I$2:$I$5,0)-1,0)>=2,IFERROR(MATCH('Options'!$E$11,'Inputs'!$B$59:$B$70,0),0),0))="No"),0,IF(IFERROR(MATCH('Options'!$E$10,'Lists'!$I$2:$I$5,0)-1,0)>=2,IFERROR(MATCH('Options'!$E$11,'Inputs'!$B$59:$B$70,0),0),0))) | AS5: =IF(IF(IFERROR(MATCH('Options'!$E$10,'Lists'!$I$2:$I$5,0)-1,0)>=2,IFERROR(MATCH('Options'!$E$11,'Inputs'!$B$59:$B$70,0),0),0)=0,0,IF(OR(INDEX('Inputs'!$C$59:$C$70,IF(IFERROR(MATCH('Options'!$E$10,'Lists'!$I$2:$I$5,0)-1,0)>=2,IFERROR(MATCH('Options'!$E$11,'Inputs'!$B$59:$B$70,0),0),0))="Estate",INDEX('Inputs'!$E$59:$E$70,IF(IFERROR(MATCH('Options'!$E$10,'Lists'!$I$2:$I$5,0)-1,0)>=2,IFERROR(MATCH('Options'!$E$11,'Inputs'!$B$59:$B$70,0),0),0))="No"),0,IF(IFERROR(MATCH('Options'!$E$10,'Lists'!$I$2:$I$5,0)-1,0)>=2,IFERROR(MATCH('Options'!$E$11,'Inputs'!$B$59:$B$70,0),0),0))) | AT5: =IF(IF(IFERROR(MATCH('Options'!$E$10,'Lists'!$I$2:$I$5,0)-1,0)>=2,IFERROR(MATCH('Options'!$E$11,'Inputs'!$B$59:$B$70,0),0),0)=0,0,IF(OR(INDEX('Inputs'!$C$59:$C$70,IF(IFERROR(MATCH('Options'!$E$10,'Lists'!$I$2:$I$5,0)-1,0)>=2,IFERROR(MATCH('Options'!$E$11,'Inputs'!$B$59:$B$70,0),0),0))="Estate",INDEX('Inputs'!$E$59:$E$70,IF(IFERROR(MATCH('Options'!$E$10,'Lists'!$I$2:$I$5,0)-1,0)>=2,IFERROR(MATCH('Options'!$E$11,'Inputs'!$B$59:$B$70,0),0),0))="No"),0,IF(IFERROR(MATCH('Options'!$E$10,'Lists'!$I$2:$I$5,0)-1,0)>=2,IFERROR(MATCH('Options'!$E$11,'Inputs'!$B$59:$B$70,0),0),0))) | ... BB5: =IF(IF(IFERROR(MATCH('Options'!$E$10,'Lists'!$I$2:$I$5,0)-1,0)>=2,IFERROR(MATCH('Options'!$E$11,'Inputs'!$B$59:$B$70,0),0),0)=0,0,IF(OR(INDEX('Inputs'!$C$59:$C$70,IF(IFERROR(MATCH('Options'!$E$10,'Lists'!$I$2:$I$5,0)-1,0)>=2,IFERROR(MATCH('Options'!$E$11,'Inputs'!$B$59:$B$70,0),0),0))="Estate",INDEX('Inputs'!$E$59:$E$70,IF(IFERROR(MATCH('Options'!$E$10,'Lists'!$I$2:$I$5,0)-1,0)>=2,IFERROR(MATCH('Options'!$E$11,'Inputs'!$B$59:$B$70,0),0),0))="No"),0,IF(IFERROR(MATCH('Options'!$E$10,'Lists'!$I$2:$I$5,0)-1,0)>=2,IFERROR(MATCH('Options'!$E$11,'Inputs'!$B$59:$B$70,0),0),0))) | BD5: =IF(IF(IFERROR(MATCH('Options'!$F$10,'Lists'!$I$2:$I$5,0)-1,0)>=2,IFERROR(MATCH('Options'!$F$11,'Inputs'!$B$59:$B$70,0),0),0)=0,0,IF(OR(INDEX('Inputs'!$C$59:$C$70,IF(IFERROR(MATCH('Options'!$F$10,'Lists'!$I$2:$I$5,0)-1,0)>=2,IFERROR(MATCH('Options'!$F$11,'Inputs'!$B$59:$B$70,0),0),0))="Estate",INDEX('Inputs'!$E$59:$E$70,IF(IFERROR(MATCH('Options'!$F$10,'Lists'!$I$2:$I$5,0)-1,0)>=2,IFERROR(MATCH('Options'!$F$11,'Inputs'!$B$59:$B$70,0),0),0))="No"),0,IF(IFERROR(MATCH('Options'!$F$10,'Lists'!$I$2:$I$5,0)-1,0)>=2,IFERROR(MATCH('Options'!$F$11,'Inputs'!$B$59:$B$70,0),0),0))) | BE5: =IF(IF(IFERROR(MATCH('Options'!$F$10,'Lists'!$I$2:$I$5,0)-1,0)>=2,IFERROR(MATCH('Options'!$F$11,'Inputs'!$B$59:$B$70,0),0),0)=0,0,IF(OR(INDEX('Inputs'!$C$59:$C$70,IF(IFERROR(MATCH('Options'!$F$10,'Lists'!$I$2:$I$5,0)-1,0)>=2,IFERROR(MATCH('Options'!$F$11,'Inputs'!$B$59:$B$70,0),0),0))="Estate",INDEX('Inputs'!$E$59:$E$70,IF(IFERROR(MATCH('Options'!$F$10,'Lists'!$I$2:$I$5,0)-1,0)>=2,IFERROR(MATCH('Options'!$F$11,'Inputs'!$B$59:$B$70,0),0),0))="No"),0,IF(IFERROR(MATCH('Options'!$F$10,'Lists'!$I$2:$I$5,0)-1,0)>=2,IFERROR(MATCH('Options'!$F$11,'Inputs'!$B$59:$B$70,0),0),0))) | BF5: =IF(IF(IFERROR(MATCH('Options'!$F$10,'Lists'!$I$2:$I$5,0)-1,0)>=2,IFERROR(MATCH('Options'!$F$11,'Inputs'!$B$59:$B$70,0),0),0)=0,0,IF(OR(INDEX('Inputs'!$C$59:$C$70,IF(IFERROR(MATCH('Options'!$F$10,'Lists'!$I$2:$I$5,0)-1,0)>=2,IFERROR(MATCH('Options'!$F$11,'Inputs'!$B$59:$B$70,0),0),0))="Estate",INDEX('Inputs'!$E$59:$E$70,IF(IFERROR(MATCH('Options'!$F$10,'Lists'!$I$2:$I$5,0)-1,0)>=2,IFERROR(MATCH('Options'!$F$11,'Inputs'!$B$59:$B$70,0),0),0))="No"),0,IF(IFERROR(MATCH('Options'!$F$10,'Lists'!$I$2:$I$5,0)-1,0)>=2,IFERROR(MATCH('Options'!$F$11,'Inputs'!$B$59:$B$70,0),0),0))) | BG5: =IF(IF(IFERROR(MATCH('Options'!$F$10,'Lists'!$I$2:$I$5,0)-1,0)>=2,IFERROR(MATCH('Options'!$F$11,'Inputs'!$B$59:$B$70,0),0),0)=0,0,IF(OR(INDEX('Inputs'!$C$59:$C$70,IF(IFERROR(MATCH('Options'!$F$10,'Lists'!$I$2:$I$5,0)-1,0)>=2,IFERROR(MATCH('Options'!$F$11,'Inputs'!$B$59:$B$70,0),0),0))="Estate",INDEX('Inputs'!$E$59:$E$70,IF(IFERROR(MATCH('Options'!$F$10,'Lists'!$I$2:$I$5,0)-1,0)>=2,IFERROR(MATCH('Options'!$F$11,'Inputs'!$B$59:$B$70,0),0),0))="No"),0,IF(IFERROR(MATCH('Options'!$F$10,'Lists'!$I$2:$I$5,0)-1,0)>=2,IFERROR(MATCH('Options'!$F$11,'Inputs'!$B$59:$B$70,0),0),0))) | BH5: =IF(IF(IFERROR(MATCH('Options'!$F$10,'Lists'!$I$2:$I$5,0)-1,0)>=2,IFERROR(MATCH('Options'!$F$11,'Inputs'!$B$59:$B$70,0),0),0)=0,0,IF(OR(INDEX('Inputs'!$C$59:$C$70,IF(IFERROR(MATCH('Options'!$F$10,'Lists'!$I$2:$I$5,0)-1,0)>=2,IFERROR(MATCH('Options'!$F$11,'Inputs'!$B$59:$B$70,0),0),0))="Estate",INDEX('Inputs'!$E$59:$E$70,IF(IFERROR(MATCH('Options'!$F$10,'Lists'!$I$2:$I$5,0)-1,0)>=2,IFERROR(MATCH('Options'!$F$11,'Inputs'!$B$59:$B$70,0),0),0))="No"),0,IF(IFERROR(MATCH('Options'!$F$10,'Lists'!$I$2:$I$5,0)-1,0)>=2,IFERROR(MATCH('Options'!$F$11,'Inputs'!$B$59:$B$70,0),0),0))) | BI5: =IF(IF(IFERROR(MATCH('Options'!$F$10,'Lists'!$I$2:$I$5,0)-1,0)>=2,IFERROR(MATCH('Options'!$F$11,'Inputs'!$B$59:$B$70,0),0),0)=0,0,IF(OR(INDEX('Inputs'!$C$59:$C$70,IF(IFERROR(MATCH('Options'!$F$10,'Lists'!$I$2:$I$5,0)-1,0)>=2,IFERROR(MATCH('Options'!$F$11,'Inputs'!$B$59:$B$70,0),0),0))="Estate",INDEX('Inputs'!$E$59:$E$70,IF(IFERROR(MATCH('Options'!$F$10,'Lists'!$I$2:$I$5,0)-1,0)>=2,IFERROR(MATCH('Options'!$F$11,'Inputs'!$B$59:$B$70,0),0),0))="No"),0,IF(IFERROR(MATCH('Options'!$F$10,'Lists'!$I$2:$I$5,0)-1,0)>=2,IFERROR(MATCH('Options'!$F$11,'Inputs'!$B$59:$B$70,0),0),0))) | BJ5: =IF(IF(IFERROR(MATCH('Options'!$F$10,'Lists'!$I$2:$I$5,0)-1,0)>=2,IFERROR(MATCH('Options'!$F$11,'Inputs'!$B$59:$B$70,0),0),0)=0,0,IF(OR(INDEX('Inputs'!$C$59:$C$70,IF(IFERROR(MATCH('Options'!$F$10,'Lists'!$I$2:$I$5,0)-1,0)>=2,IFERROR(MATCH('Options'!$F$11,'Inputs'!$B$59:$B$70,0),0),0))="Estate",INDEX('Inputs'!$E$59:$E$70,IF(IFERROR(MATCH('Options'!$F$10,'Lists'!$I$2:$I$5,0)-1,0)>=2,IFERROR(MATCH('Options'!$F$11,'Inputs'!$B$59:$B$70,0),0),0))="No"),0,IF(IFERROR(MATCH('Options'!$F$10,'Lists'!$I$2:$I$5,0)-1,0)>=2,IFERROR(MATCH('Options'!$F$11,'Inputs'!$B$59:$B$70,0),0),0))) | BK5: =IF(IF(IFERROR(MATCH('Options'!$F$10,'Lists'!$I$2:$I$5,0)-1,0)>=2,IFERROR(MATCH('Options'!$F$11,'Inputs'!$B$59:$B$70,0),0),0)=0,0,IF(OR(INDEX('Inputs'!$C$59:$C$70,IF(IFERROR(MATCH('Options'!$F$10,'Lists'!$I$2:$I$5,0)-1,0)>=2,IFERROR(MATCH('Options'!$F$11,'Inputs'!$B$59:$B$70,0),0),0))="Estate",INDEX('Inputs'!$E$59:$E$70,IF(IFERROR(MATCH('Options'!$F$10,'Lists'!$I$2:$I$5,0)-1,0)>=2,IFERROR(MATCH('Options'!$F$11,'Inputs'!$B$59:$B$70,0),0),0))="No"),0,IF(IFERROR(MATCH('Options'!$F$10,'Lists'!$I$2:$I$5,0)-1,0)>=2,IFERROR(MATCH('Options'!$F$11,'Inputs'!$B$59:$B$70,0),0),0))) | ... BS5: =IF(IF(IFERROR(MATCH('Options'!$F$10,'Lists'!$I$2:$I$5,0)-1,0)>=2,IFERROR(MATCH('Options'!$F$11,'Inputs'!$B$59:$B$70,0),0),0)=0,0,IF(OR(INDEX('Inputs'!$C$59:$C$70,IF(IFERROR(MATCH('Options'!$F$10,'Lists'!$I$2:$I$5,0)-1,0)>=2,IFERROR(MATCH('Options'!$F$11,'Inputs'!$B$59:$B$70,0),0),0))="Estate",INDEX('Inputs'!$E$59:$E$70,IF(IFERROR(MATCH('Options'!$F$10,'Lists'!$I$2:$I$5,0)-1,0)>=2,IFERROR(MATCH('Options'!$F$11,'Inputs'!$B$59:$B$70,0),0),0))="No"),0,IF(IFERROR(MATCH('Options'!$F$10,'Lists'!$I$2:$I$5,0)-1,0)>=2,IFERROR(MATCH('Options'!$F$11,'Inputs'!$B$59:$B$70,0),0),0)))
B6: dest | C6: ="" | E6: ="" | F6: ="" | G6: ="" | H6: ="" | I6: ="" | J6: ="" | K6: ="" | L6: ="" | ... T6: ="" | V6: =IF('Options'!$D$12="","",'Options'!$D$12) | W6: =IF('Options'!$D$12="","",'Options'!$D$12) | X6: =IF('Options'!$D$12="","",'Options'!$D$12) | Y6: =IF('Options'!$D$12="","",'Options'!$D$12) | Z6: =IF('Options'!$D$12="","",'Options'!$D$12) | AA6: =IF('Options'!$D$12="","",'Options'!$D$12) | AB6: =IF('Options'!$D$12="","",'Options'!$D$12) | AC6: =IF('Options'!$D$12="","",'Options'!$D$12) | ... AK6: =IF('Options'!$D$12="","",'Options'!$D$12) | AM6: =IF('Options'!$E$12="","",'Options'!$E$12) | AN6: =IF('Options'!$E$12="","",'Options'!$E$12) | AO6: =IF('Options'!$E$12="","",'Options'!$E$12) | AP6: =IF('Options'!$E$12="","",'Options'!$E$12) | AQ6: =IF('Options'!$E$12="","",'Options'!$E$12) | AR6: =IF('Options'!$E$12="","",'Options'!$E$12) | AS6: =IF('Options'!$E$12="","",'Options'!$E$12) | AT6: =IF('Options'!$E$12="","",'Options'!$E$12) | ... BB6: =IF('Options'!$E$12="","",'Options'!$E$12) | BD6: =IF('Options'!$F$12="","",'Options'!$F$12) | BE6: =IF('Options'!$F$12="","",'Options'!$F$12) | BF6: =IF('Options'!$F$12="","",'Options'!$F$12) | BG6: =IF('Options'!$F$12="","",'Options'!$F$12) | BH6: =IF('Options'!$F$12="","",'Options'!$F$12) | BI6: =IF('Options'!$F$12="","",'Options'!$F$12) | BJ6: =IF('Options'!$F$12="","",'Options'!$F$12) | BK6: =IF('Options'!$F$12="","",'Options'!$F$12) | ... BS6: =IF('Options'!$F$12="","",'Options'!$F$12)
B7: extra for dependant 1 | C7: =0 | E7: =0 | F7: =E92 | G7: =F92 | H7: =G92 | I7: =H92 | J7: =I92 | K7: =J92 | L7: =K92 | M7: =L92 | ... P7: =O92 | Q7: =IF(ROUND(P92,2)>0,MAX(0,ROUND(P92,2)-0.01),0) | R7: =ROUND(P92,2) | S7: =IF(ROUND(P92,2)>0,ROUND(P92,2)+0.01,0) | T7: =IF(AND(T3=2,R99>T16+0.005),0,IF(ROUND(P92,2)=0,0,IF(T3=1,IF(R51<=0,ROUND(P92,2),IF(S51<=0,ROUND(P92,2)+0.01,ROUND(P92,2)+0.02)),IF(Q51<=0,ROUND(P92,2)-0.01,IF(R51<=0,ROUND(P92,2),ROUND(P92,2)+0.01))))) | V7: =0 | W7: =V92 | X7: =W92 | Y7: =X92 | Z7: =Y92 | AA7: =Z92 | AB7: =AA92 | AC7: =AB92 | AD7: =AC92 | ... AG7: =AF92 | AH7: =IF(ROUND(AG92,2)>0,MAX(0,ROUND(AG92,2)-0.01),0) | AI7: =ROUND(AG92,2) | AJ7: =IF(ROUND(AG92,2)>0,ROUND(AG92,2)+0.01,0) | AK7: =IF(AND(AK3=2,AI99>AK16+0.005),0,IF(ROUND(AG92,2)=0,0,IF(AK3=1,IF(AI51<=0,ROUND(AG92,2),IF(AJ51<=0,ROUND(AG92,2)+0.01,ROUND(AG92,2)+0.02)),IF(AH51<=0,ROUND(AG92,2)-0.01,IF(AI51<=0,ROUND(AG92,2),ROUND(AG92,2)+0.01))))) | AM7: =0 | AN7: =AM92 | AO7: =AN92 | AP7: =AO92 | AQ7: =AP92 | AR7: =AQ92 | AS7: =AR92 | AT7: =AS92 | AU7: =AT92 | ... AX7: =AW92 | AY7: =IF(ROUND(AX92,2)>0,MAX(0,ROUND(AX92,2)-0.01),0) | AZ7: =ROUND(AX92,2) | BA7: =IF(ROUND(AX92,2)>0,ROUND(AX92,2)+0.01,0) | BB7: =IF(AND(BB3=2,AZ99>BB16+0.005),0,IF(ROUND(AX92,2)=0,0,IF(BB3=1,IF(AZ51<=0,ROUND(AX92,2),IF(BA51<=0,ROUND(AX92,2)+0.01,ROUND(AX92,2)+0.02)),IF(AY51<=0,ROUND(AX92,2)-0.01,IF(AZ51<=0,ROUND(AX92,2),ROUND(AX92,2)+0.01))))) | BD7: =0 | BE7: =BD92 | BF7: =BE92 | BG7: =BF92 | BH7: =BG92 | BI7: =BH92 | BJ7: =BI92 | BK7: =BJ92 | BL7: =BK92 | ... BO7: =BN92 | BP7: =IF(ROUND(BO92,2)>0,MAX(0,ROUND(BO92,2)-0.01),0) | BQ7: =ROUND(BO92,2) | BR7: =IF(ROUND(BO92,2)>0,ROUND(BO92,2)+0.01,0) | BS7: =IF(AND(BS3=2,BQ99>BS16+0.005),0,IF(ROUND(BO92,2)=0,0,IF(BS3=1,IF(BQ51<=0,ROUND(BO92,2),IF(BR51<=0,ROUND(BO92,2)+0.01,ROUND(BO92,2)+0.02)),IF(BP51<=0,ROUND(BO92,2)-0.01,IF(BQ51<=0,ROUND(BO92,2),ROUND(BO92,2)+0.01)))))
B8: extra for dependant 2 | C8: =0 | E8: =0 | F8: =E93 | G8: =F93 | H8: =G93 | I8: =H93 | J8: =I93 | K8: =J93 | L8: =K93 | M8: =L93 | ... P8: =O93 | Q8: =IF(ROUND(P93,2)>0,MAX(0,ROUND(P93,2)-0.01),0) | R8: =ROUND(P93,2) | S8: =IF(ROUND(P93,2)>0,ROUND(P93,2)+0.01,0) | T8: =IF(AND(T3=2,R99>T16+0.005),0,IF(ROUND(P93,2)=0,0,IF(T3=1,IF(R58<=0,ROUND(P93,2),IF(S58<=0,ROUND(P93,2)+0.01,ROUND(P93,2)+0.02)),IF(Q58<=0,ROUND(P93,2)-0.01,IF(R58<=0,ROUND(P93,2),ROUND(P93,2)+0.01))))) | V8: =0 | W8: =V93 | X8: =W93 | Y8: =X93 | Z8: =Y93 | AA8: =Z93 | AB8: =AA93 | AC8: =AB93 | AD8: =AC93 | ... AG8: =AF93 | AH8: =IF(ROUND(AG93,2)>0,MAX(0,ROUND(AG93,2)-0.01),0) | AI8: =ROUND(AG93,2) | AJ8: =IF(ROUND(AG93,2)>0,ROUND(AG93,2)+0.01,0) | AK8: =IF(AND(AK3=2,AI99>AK16+0.005),0,IF(ROUND(AG93,2)=0,0,IF(AK3=1,IF(AI58<=0,ROUND(AG93,2),IF(AJ58<=0,ROUND(AG93,2)+0.01,ROUND(AG93,2)+0.02)),IF(AH58<=0,ROUND(AG93,2)-0.01,IF(AI58<=0,ROUND(AG93,2),ROUND(AG93,2)+0.01))))) | AM8: =0 | AN8: =AM93 | AO8: =AN93 | AP8: =AO93 | AQ8: =AP93 | AR8: =AQ93 | AS8: =AR93 | AT8: =AS93 | AU8: =AT93 | ... AX8: =AW93 | AY8: =IF(ROUND(AX93,2)>0,MAX(0,ROUND(AX93,2)-0.01),0) | AZ8: =ROUND(AX93,2) | BA8: =IF(ROUND(AX93,2)>0,ROUND(AX93,2)+0.01,0) | BB8: =IF(AND(BB3=2,AZ99>BB16+0.005),0,IF(ROUND(AX93,2)=0,0,IF(BB3=1,IF(AZ58<=0,ROUND(AX93,2),IF(BA58<=0,ROUND(AX93,2)+0.01,ROUND(AX93,2)+0.02)),IF(AY58<=0,ROUND(AX93,2)-0.01,IF(AZ58<=0,ROUND(AX93,2),ROUND(AX93,2)+0.01))))) | BD8: =0 | BE8: =BD93 | BF8: =BE93 | BG8: =BF93 | BH8: =BG93 | BI8: =BH93 | BJ8: =BI93 | BK8: =BJ93 | BL8: =BK93 | ... BO8: =BN93 | BP8: =IF(ROUND(BO93,2)>0,MAX(0,ROUND(BO93,2)-0.01),0) | BQ8: =ROUND(BO93,2) | BR8: =IF(ROUND(BO93,2)>0,ROUND(BO93,2)+0.01,0) | BS8: =IF(AND(BS3=2,BQ99>BS16+0.005),0,IF(ROUND(BO93,2)=0,0,IF(BS3=1,IF(BQ58<=0,ROUND(BO93,2),IF(BR58<=0,ROUND(BO93,2)+0.01,ROUND(BO93,2)+0.02)),IF(BP58<=0,ROUND(BO93,2)-0.01,IF(BQ58<=0,ROUND(BO93,2),ROUND(BO93,2)+0.01)))))
B9: extra for dependant 3 | C9: =0 | E9: =0 | F9: =E94 | G9: =F94 | H9: =G94 | I9: =H94 | J9: =I94 | K9: =J94 | L9: =K94 | M9: =L94 | ... P9: =O94 | Q9: =IF(ROUND(P94,2)>0,MAX(0,ROUND(P94,2)-0.01),0) | R9: =ROUND(P94,2) | S9: =IF(ROUND(P94,2)>0,ROUND(P94,2)+0.01,0) | T9: =IF(AND(T3=2,R99>T16+0.005),0,IF(ROUND(P94,2)=0,0,IF(T3=1,IF(R65<=0,ROUND(P94,2),IF(S65<=0,ROUND(P94,2)+0.01,ROUND(P94,2)+0.02)),IF(Q65<=0,ROUND(P94,2)-0.01,IF(R65<=0,ROUND(P94,2),ROUND(P94,2)+0.01))))) | V9: =0 | W9: =V94 | X9: =W94 | Y9: =X94 | Z9: =Y94 | AA9: =Z94 | AB9: =AA94 | AC9: =AB94 | AD9: =AC94 | ... AG9: =AF94 | AH9: =IF(ROUND(AG94,2)>0,MAX(0,ROUND(AG94,2)-0.01),0) | AI9: =ROUND(AG94,2) | AJ9: =IF(ROUND(AG94,2)>0,ROUND(AG94,2)+0.01,0) | AK9: =IF(AND(AK3=2,AI99>AK16+0.005),0,IF(ROUND(AG94,2)=0,0,IF(AK3=1,IF(AI65<=0,ROUND(AG94,2),IF(AJ65<=0,ROUND(AG94,2)+0.01,ROUND(AG94,2)+0.02)),IF(AH65<=0,ROUND(AG94,2)-0.01,IF(AI65<=0,ROUND(AG94,2),ROUND(AG94,2)+0.01))))) | AM9: =0 | AN9: =AM94 | AO9: =AN94 | AP9: =AO94 | AQ9: =AP94 | AR9: =AQ94 | AS9: =AR94 | AT9: =AS94 | AU9: =AT94 | ... AX9: =AW94 | AY9: =IF(ROUND(AX94,2)>0,MAX(0,ROUND(AX94,2)-0.01),0) | AZ9: =ROUND(AX94,2) | BA9: =IF(ROUND(AX94,2)>0,ROUND(AX94,2)+0.01,0) | BB9: =IF(AND(BB3=2,AZ99>BB16+0.005),0,IF(ROUND(AX94,2)=0,0,IF(BB3=1,IF(AZ65<=0,ROUND(AX94,2),IF(BA65<=0,ROUND(AX94,2)+0.01,ROUND(AX94,2)+0.02)),IF(AY65<=0,ROUND(AX94,2)-0.01,IF(AZ65<=0,ROUND(AX94,2),ROUND(AX94,2)+0.01))))) | BD9: =0 | BE9: =BD94 | BF9: =BE94 | BG9: =BF94 | BH9: =BG94 | BI9: =BH94 | BJ9: =BI94 | BK9: =BJ94 | BL9: =BK94 | ... BO9: =BN94 | BP9: =IF(ROUND(BO94,2)>0,MAX(0,ROUND(BO94,2)-0.01),0) | BQ9: =ROUND(BO94,2) | BR9: =IF(ROUND(BO94,2)>0,ROUND(BO94,2)+0.01,0) | BS9: =IF(AND(BS3=2,BQ99>BS16+0.005),0,IF(ROUND(BO94,2)=0,0,IF(BS3=1,IF(BQ65<=0,ROUND(BO94,2),IF(BR65<=0,ROUND(BO94,2)+0.01,ROUND(BO94,2)+0.02)),IF(BP65<=0,ROUND(BO94,2)-0.01,IF(BQ65<=0,ROUND(BO94,2),ROUND(BO94,2)+0.01)))))
B10: extra for dependant 4 | C10: =0 | E10: =0 | F10: =E95 | G10: =F95 | H10: =G95 | I10: =H95 | J10: =I95 | K10: =J95 | L10: =K95 | M10: =L95 | ... P10: =O95 | Q10: =IF(ROUND(P95,2)>0,MAX(0,ROUND(P95,2)-0.01),0) | R10: =ROUND(P95,2) | S10: =IF(ROUND(P95,2)>0,ROUND(P95,2)+0.01,0) | T10: =IF(AND(T3=2,R99>T16+0.005),0,IF(ROUND(P95,2)=0,0,IF(T3=1,IF(R72<=0,ROUND(P95,2),IF(S72<=0,ROUND(P95,2)+0.01,ROUND(P95,2)+0.02)),IF(Q72<=0,ROUND(P95,2)-0.01,IF(R72<=0,ROUND(P95,2),ROUND(P95,2)+0.01))))) | V10: =0 | W10: =V95 | X10: =W95 | Y10: =X95 | Z10: =Y95 | AA10: =Z95 | AB10: =AA95 | AC10: =AB95 | AD10: =AC95 | ... AG10: =AF95 | AH10: =IF(ROUND(AG95,2)>0,MAX(0,ROUND(AG95,2)-0.01),0) | AI10: =ROUND(AG95,2) | AJ10: =IF(ROUND(AG95,2)>0,ROUND(AG95,2)+0.01,0) | AK10: =IF(AND(AK3=2,AI99>AK16+0.005),0,IF(ROUND(AG95,2)=0,0,IF(AK3=1,IF(AI72<=0,ROUND(AG95,2),IF(AJ72<=0,ROUND(AG95,2)+0.01,ROUND(AG95,2)+0.02)),IF(AH72<=0,ROUND(AG95,2)-0.01,IF(AI72<=0,ROUND(AG95,2),ROUND(AG95,2)+0.01))))) | AM10: =0 | AN10: =AM95 | AO10: =AN95 | AP10: =AO95 | AQ10: =AP95 | AR10: =AQ95 | AS10: =AR95 | AT10: =AS95 | AU10: =AT95 | ... AX10: =AW95 | AY10: =IF(ROUND(AX95,2)>0,MAX(0,ROUND(AX95,2)-0.01),0) | AZ10: =ROUND(AX95,2) | BA10: =IF(ROUND(AX95,2)>0,ROUND(AX95,2)+0.01,0) | BB10: =IF(AND(BB3=2,AZ99>BB16+0.005),0,IF(ROUND(AX95,2)=0,0,IF(BB3=1,IF(AZ72<=0,ROUND(AX95,2),IF(BA72<=0,ROUND(AX95,2)+0.01,ROUND(AX95,2)+0.02)),IF(AY72<=0,ROUND(AX95,2)-0.01,IF(AZ72<=0,ROUND(AX95,2),ROUND(AX95,2)+0.01))))) | BD10: =0 | BE10: =BD95 | BF10: =BE95 | BG10: =BF95 | BH10: =BG95 | BI10: =BH95 | BJ10: =BI95 | BK10: =BJ95 | BL10: =BK95 | ... BO10: =BN95 | BP10: =IF(ROUND(BO95,2)>0,MAX(0,ROUND(BO95,2)-0.01),0) | BQ10: =ROUND(BO95,2) | BR10: =IF(ROUND(BO95,2)>0,ROUND(BO95,2)+0.01,0) | BS10: =IF(AND(BS3=2,BQ99>BS16+0.005),0,IF(ROUND(BO95,2)=0,0,IF(BS3=1,IF(BQ72<=0,ROUND(BO95,2),IF(BR72<=0,ROUND(BO95,2)+0.01,ROUND(BO95,2)+0.02)),IF(BP72<=0,ROUND(BO95,2)-0.01,IF(BQ72<=0,ROUND(BO95,2),ROUND(BO95,2)+0.01)))))
B11: extra for dependant 5 | C11: =0 | E11: =0 | F11: =E96 | G11: =F96 | H11: =G96 | I11: =H96 | J11: =I96 | K11: =J96 | L11: =K96 | M11: =L96 | ... P11: =O96 | Q11: =IF(ROUND(P96,2)>0,MAX(0,ROUND(P96,2)-0.01),0) | R11: =ROUND(P96,2) | S11: =IF(ROUND(P96,2)>0,ROUND(P96,2)+0.01,0) | T11: =IF(AND(T3=2,R99>T16+0.005),0,IF(ROUND(P96,2)=0,0,IF(T3=1,IF(R79<=0,ROUND(P96,2),IF(S79<=0,ROUND(P96,2)+0.01,ROUND(P96,2)+0.02)),IF(Q79<=0,ROUND(P96,2)-0.01,IF(R79<=0,ROUND(P96,2),ROUND(P96,2)+0.01))))) | V11: =0 | W11: =V96 | X11: =W96 | Y11: =X96 | Z11: =Y96 | AA11: =Z96 | AB11: =AA96 | AC11: =AB96 | AD11: =AC96 | ... AG11: =AF96 | AH11: =IF(ROUND(AG96,2)>0,MAX(0,ROUND(AG96,2)-0.01),0) | AI11: =ROUND(AG96,2) | AJ11: =IF(ROUND(AG96,2)>0,ROUND(AG96,2)+0.01,0) | AK11: =IF(AND(AK3=2,AI99>AK16+0.005),0,IF(ROUND(AG96,2)=0,0,IF(AK3=1,IF(AI79<=0,ROUND(AG96,2),IF(AJ79<=0,ROUND(AG96,2)+0.01,ROUND(AG96,2)+0.02)),IF(AH79<=0,ROUND(AG96,2)-0.01,IF(AI79<=0,ROUND(AG96,2),ROUND(AG96,2)+0.01))))) | AM11: =0 | AN11: =AM96 | AO11: =AN96 | AP11: =AO96 | AQ11: =AP96 | AR11: =AQ96 | AS11: =AR96 | AT11: =AS96 | AU11: =AT96 | ... AX11: =AW96 | AY11: =IF(ROUND(AX96,2)>0,MAX(0,ROUND(AX96,2)-0.01),0) | AZ11: =ROUND(AX96,2) | BA11: =IF(ROUND(AX96,2)>0,ROUND(AX96,2)+0.01,0) | BB11: =IF(AND(BB3=2,AZ99>BB16+0.005),0,IF(ROUND(AX96,2)=0,0,IF(BB3=1,IF(AZ79<=0,ROUND(AX96,2),IF(BA79<=0,ROUND(AX96,2)+0.01,ROUND(AX96,2)+0.02)),IF(AY79<=0,ROUND(AX96,2)-0.01,IF(AZ79<=0,ROUND(AX96,2),ROUND(AX96,2)+0.01))))) | BD11: =0 | BE11: =BD96 | BF11: =BE96 | BG11: =BF96 | BH11: =BG96 | BI11: =BH96 | BJ11: =BI96 | BK11: =BJ96 | BL11: =BK96 | ... BO11: =BN96 | BP11: =IF(ROUND(BO96,2)>0,MAX(0,ROUND(BO96,2)-0.01),0) | BQ11: =ROUND(BO96,2) | BR11: =IF(ROUND(BO96,2)>0,ROUND(BO96,2)+0.01,0) | BS11: =IF(AND(BS3=2,BQ99>BS16+0.005),0,IF(ROUND(BO96,2)=0,0,IF(BS3=1,IF(BQ79<=0,ROUND(BO96,2),IF(BR79<=0,ROUND(BO96,2)+0.01,ROUND(BO96,2)+0.02)),IF(BP79<=0,ROUND(BO96,2)-0.01,IF(BQ79<=0,ROUND(BO96,2),ROUND(BO96,2)+0.01)))))
B12: extra for dependant 6 | C12: =0 | E12: =0 | F12: =E97 | G12: =F97 | H12: =G97 | I12: =H97 | J12: =I97 | K12: =J97 | L12: =K97 | M12: =L97 | ... P12: =O97 | Q12: =IF(ROUND(P97,2)>0,MAX(0,ROUND(P97,2)-0.01),0) | R12: =ROUND(P97,2) | S12: =IF(ROUND(P97,2)>0,ROUND(P97,2)+0.01,0) | T12: =IF(AND(T3=2,R99>T16+0.005),0,IF(ROUND(P97,2)=0,0,IF(T3=1,IF(R86<=0,ROUND(P97,2),IF(S86<=0,ROUND(P97,2)+0.01,ROUND(P97,2)+0.02)),IF(Q86<=0,ROUND(P97,2)-0.01,IF(R86<=0,ROUND(P97,2),ROUND(P97,2)+0.01))))) | V12: =0 | W12: =V97 | X12: =W97 | Y12: =X97 | Z12: =Y97 | AA12: =Z97 | AB12: =AA97 | AC12: =AB97 | AD12: =AC97 | ... AG12: =AF97 | AH12: =IF(ROUND(AG97,2)>0,MAX(0,ROUND(AG97,2)-0.01),0) | AI12: =ROUND(AG97,2) | AJ12: =IF(ROUND(AG97,2)>0,ROUND(AG97,2)+0.01,0) | AK12: =IF(AND(AK3=2,AI99>AK16+0.005),0,IF(ROUND(AG97,2)=0,0,IF(AK3=1,IF(AI86<=0,ROUND(AG97,2),IF(AJ86<=0,ROUND(AG97,2)+0.01,ROUND(AG97,2)+0.02)),IF(AH86<=0,ROUND(AG97,2)-0.01,IF(AI86<=0,ROUND(AG97,2),ROUND(AG97,2)+0.01))))) | AM12: =0 | AN12: =AM97 | AO12: =AN97 | AP12: =AO97 | AQ12: =AP97 | AR12: =AQ97 | AS12: =AR97 | AT12: =AS97 | AU12: =AT97 | ... AX12: =AW97 | AY12: =IF(ROUND(AX97,2)>0,MAX(0,ROUND(AX97,2)-0.01),0) | AZ12: =ROUND(AX97,2) | BA12: =IF(ROUND(AX97,2)>0,ROUND(AX97,2)+0.01,0) | BB12: =IF(AND(BB3=2,AZ99>BB16+0.005),0,IF(ROUND(AX97,2)=0,0,IF(BB3=1,IF(AZ86<=0,ROUND(AX97,2),IF(BA86<=0,ROUND(AX97,2)+0.01,ROUND(AX97,2)+0.02)),IF(AY86<=0,ROUND(AX97,2)-0.01,IF(AZ86<=0,ROUND(AX97,2),ROUND(AX97,2)+0.01))))) | BD12: =0 | BE12: =BD97 | BF12: =BE97 | BG12: =BF97 | BH12: =BG97 | BI12: =BH97 | BJ12: =BI97 | BK12: =BJ97 | BL12: =BK97 | ... BO12: =BN97 | BP12: =IF(ROUND(BO97,2)>0,MAX(0,ROUND(BO97,2)-0.01),0) | BQ12: =ROUND(BO97,2) | BR12: =IF(ROUND(BO97,2)>0,ROUND(BO97,2)+0.01,0) | BS12: =IF(AND(BS3=2,BQ99>BS16+0.005),0,IF(ROUND(BO97,2)=0,0,IF(BS3=1,IF(BQ86<=0,ROUND(BO97,2),IF(BR86<=0,ROUND(BO97,2)+0.01,ROUND(BO97,2)+0.02)),IF(BP86<=0,ROUND(BO97,2)-0.01,IF(BQ86<=0,ROUND(BO97,2),ROUND(BO97,2)+0.01)))))
B13: extra for the family pot | C13: =0 | E13: =0 | F13: =E98 | G13: =F98 | H13: =G98 | I13: =H98 | J13: =I98 | K13: =J98 | L13: =K98 | M13: =L98 | ... P13: =O98 | Q13: =IF(ROUND(P98,2)>0,MAX(0,ROUND(P98,2)-0.01),0) | R13: =ROUND(P98,2) | S13: =IF(ROUND(P98,2)>0,ROUND(P98,2)+0.01,0) | T13: =IF(AND(T3=2,R99>T16+0.005),0,IF(ROUND(P98,2)=0,0,IF(T3=1,IF(R91<=0,ROUND(P98,2),IF(S91<=0,ROUND(P98,2)+0.01,ROUND(P98,2)+0.02)),IF(Q91<=0,ROUND(P98,2)-0.01,IF(R91<=0,ROUND(P98,2),ROUND(P98,2)+0.01))))) | V13: =0 | W13: =V98 | X13: =W98 | Y13: =X98 | Z13: =Y98 | AA13: =Z98 | AB13: =AA98 | AC13: =AB98 | AD13: =AC98 | ... AG13: =AF98 | AH13: =IF(ROUND(AG98,2)>0,MAX(0,ROUND(AG98,2)-0.01),0) | AI13: =ROUND(AG98,2) | AJ13: =IF(ROUND(AG98,2)>0,ROUND(AG98,2)+0.01,0) | AK13: =IF(AND(AK3=2,AI99>AK16+0.005),0,IF(ROUND(AG98,2)=0,0,IF(AK3=1,IF(AI91<=0,ROUND(AG98,2),IF(AJ91<=0,ROUND(AG98,2)+0.01,ROUND(AG98,2)+0.02)),IF(AH91<=0,ROUND(AG98,2)-0.01,IF(AI91<=0,ROUND(AG98,2),ROUND(AG98,2)+0.01))))) | AM13: =0 | AN13: =AM98 | AO13: =AN98 | AP13: =AO98 | AQ13: =AP98 | AR13: =AQ98 | AS13: =AR98 | AT13: =AS98 | AU13: =AT98 | ... AX13: =AW98 | AY13: =IF(ROUND(AX98,2)>0,MAX(0,ROUND(AX98,2)-0.01),0) | AZ13: =ROUND(AX98,2) | BA13: =IF(ROUND(AX98,2)>0,ROUND(AX98,2)+0.01,0) | BB13: =IF(AND(BB3=2,AZ99>BB16+0.005),0,IF(ROUND(AX98,2)=0,0,IF(BB3=1,IF(AZ91<=0,ROUND(AX98,2),IF(BA91<=0,ROUND(AX98,2)+0.01,ROUND(AX98,2)+0.02)),IF(AY91<=0,ROUND(AX98,2)-0.01,IF(AZ91<=0,ROUND(AX98,2),ROUND(AX98,2)+0.01))))) | BD13: =0 | BE13: =BD98 | BF13: =BE98 | BG13: =BF98 | BH13: =BG98 | BI13: =BH98 | BJ13: =BI98 | BK13: =BJ98 | BL13: =BK98 | ... BO13: =BN98 | BP13: =IF(ROUND(BO98,2)>0,MAX(0,ROUND(BO98,2)-0.01),0) | BQ13: =ROUND(BO98,2) | BR13: =IF(ROUND(BO98,2)>0,ROUND(BO98,2)+0.01,0) | BS13: =IF(AND(BS3=2,BQ99>BS16+0.005),0,IF(ROUND(BO98,2)=0,0,IF(BS3=1,IF(BQ91<=0,ROUND(BO98,2),IF(BR91<=0,ROUND(BO98,2)+0.01,ROUND(BO98,2)+0.02)),IF(BP91<=0,ROUND(BO98,2)-0.01,IF(BQ91<=0,ROUND(BO98,2),ROUND(BO98,2)+0.01)))))
B14: M | C14: =IF(C3=2,C7+C8+C9+C10+C11+C12+C13,IF(AND(C3=3,C5>0),C16,0)) | E14: =IF(E3=2,E7+E8+E9+E10+E11+E12+E13,IF(AND(E3=3,E5>0),E16,0)) | F14: =IF(F3=2,F7+F8+F9+F10+F11+F12+F13,IF(AND(F3=3,F5>0),F16,0)) | G14: =IF(G3=2,G7+G8+G9+G10+G11+G12+G13,IF(AND(G3=3,G5>0),G16,0)) | H14: =IF(H3=2,H7+H8+H9+H10+H11+H12+H13,IF(AND(H3=3,H5>0),H16,0)) | I14: =IF(I3=2,I7+I8+I9+I10+I11+I12+I13,IF(AND(I3=3,I5>0),I16,0)) | J14: =IF(J3=2,J7+J8+J9+J10+J11+J12+J13,IF(AND(J3=3,J5>0),J16,0)) | K14: =IF(K3=2,K7+K8+K9+K10+K11+K12+K13,IF(AND(K3=3,K5>0),K16,0)) | L14: =IF(L3=2,L7+L8+L9+L10+L11+L12+L13,IF(AND(L3=3,L5>0),L16,0)) | ... T14: =IF(T3=2,T7+T8+T9+T10+T11+T12+T13,IF(AND(T3=3,T5>0),T16,0)) | V14: =IF(V3=2,V7+V8+V9+V10+V11+V12+V13,IF(AND(V3=3,V5>0),V16,0)) | W14: =IF(W3=2,W7+W8+W9+W10+W11+W12+W13,IF(AND(W3=3,W5>0),W16,0)) | X14: =IF(X3=2,X7+X8+X9+X10+X11+X12+X13,IF(AND(X3=3,X5>0),X16,0)) | Y14: =IF(Y3=2,Y7+Y8+Y9+Y10+Y11+Y12+Y13,IF(AND(Y3=3,Y5>0),Y16,0)) | Z14: =IF(Z3=2,Z7+Z8+Z9+Z10+Z11+Z12+Z13,IF(AND(Z3=3,Z5>0),Z16,0)) | AA14: =IF(AA3=2,AA7+AA8+AA9+AA10+AA11+AA12+AA13,IF(AND(AA3=3,AA5>0),AA16,0)) | AB14: =IF(AB3=2,AB7+AB8+AB9+AB10+AB11+AB12+AB13,IF(AND(AB3=3,AB5>0),AB16,0)) | AC14: =IF(AC3=2,AC7+AC8+AC9+AC10+AC11+AC12+AC13,IF(AND(AC3=3,AC5>0),AC16,0)) | ... AK14: =IF(AK3=2,AK7+AK8+AK9+AK10+AK11+AK12+AK13,IF(AND(AK3=3,AK5>0),AK16,0)) | AM14: =IF(AM3=2,AM7+AM8+AM9+AM10+AM11+AM12+AM13,IF(AND(AM3=3,AM5>0),AM16,0)) | AN14: =IF(AN3=2,AN7+AN8+AN9+AN10+AN11+AN12+AN13,IF(AND(AN3=3,AN5>0),AN16,0)) | AO14: =IF(AO3=2,AO7+AO8+AO9+AO10+AO11+AO12+AO13,IF(AND(AO3=3,AO5>0),AO16,0)) | AP14: =IF(AP3=2,AP7+AP8+AP9+AP10+AP11+AP12+AP13,IF(AND(AP3=3,AP5>0),AP16,0)) | AQ14: =IF(AQ3=2,AQ7+AQ8+AQ9+AQ10+AQ11+AQ12+AQ13,IF(AND(AQ3=3,AQ5>0),AQ16,0)) | AR14: =IF(AR3=2,AR7+AR8+AR9+AR10+AR11+AR12+AR13,IF(AND(AR3=3,AR5>0),AR16,0)) | AS14: =IF(AS3=2,AS7+AS8+AS9+AS10+AS11+AS12+AS13,IF(AND(AS3=3,AS5>0),AS16,0)) | AT14: =IF(AT3=2,AT7+AT8+AT9+AT10+AT11+AT12+AT13,IF(AND(AT3=3,AT5>0),AT16,0)) | ... BB14: =IF(BB3=2,BB7+BB8+BB9+BB10+BB11+BB12+BB13,IF(AND(BB3=3,BB5>0),BB16,0)) | BD14: =IF(BD3=2,BD7+BD8+BD9+BD10+BD11+BD12+BD13,IF(AND(BD3=3,BD5>0),BD16,0)) | BE14: =IF(BE3=2,BE7+BE8+BE9+BE10+BE11+BE12+BE13,IF(AND(BE3=3,BE5>0),BE16,0)) | BF14: =IF(BF3=2,BF7+BF8+BF9+BF10+BF11+BF12+BF13,IF(AND(BF3=3,BF5>0),BF16,0)) | BG14: =IF(BG3=2,BG7+BG8+BG9+BG10+BG11+BG12+BG13,IF(AND(BG3=3,BG5>0),BG16,0)) | BH14: =IF(BH3=2,BH7+BH8+BH9+BH10+BH11+BH12+BH13,IF(AND(BH3=3,BH5>0),BH16,0)) | BI14: =IF(BI3=2,BI7+BI8+BI9+BI10+BI11+BI12+BI13,IF(AND(BI3=3,BI5>0),BI16,0)) | BJ14: =IF(BJ3=2,BJ7+BJ8+BJ9+BJ10+BJ11+BJ12+BJ13,IF(AND(BJ3=3,BJ5>0),BJ16,0)) | BK14: =IF(BK3=2,BK7+BK8+BK9+BK10+BK11+BK12+BK13,IF(AND(BK3=3,BK5>0),BK16,0)) | ... BS14: =IF(BS3=2,BS7+BS8+BS9+BS10+BS11+BS12+BS13,IF(AND(BS3=3,BS5>0),BS16,0))
B15: NC | C15: =IF(C3=1,C7+C8+C9+C10+C11+C12+C13,0) | E15: =IF(E3=1,E7+E8+E9+E10+E11+E12+E13,0) | F15: =IF(F3=1,F7+F8+F9+F10+F11+F12+F13,0) | G15: =IF(G3=1,G7+G8+G9+G10+G11+G12+G13,0) | H15: =IF(H3=1,H7+H8+H9+H10+H11+H12+H13,0) | I15: =IF(I3=1,I7+I8+I9+I10+I11+I12+I13,0) | J15: =IF(J3=1,J7+J8+J9+J10+J11+J12+J13,0) | K15: =IF(K3=1,K7+K8+K9+K10+K11+K12+K13,0) | L15: =IF(L3=1,L7+L8+L9+L10+L11+L12+L13,0) | ... T15: =IF(T3=1,T7+T8+T9+T10+T11+T12+T13,0) | V15: =IF(V3=1,V7+V8+V9+V10+V11+V12+V13,0) | W15: =IF(W3=1,W7+W8+W9+W10+W11+W12+W13,0) | X15: =IF(X3=1,X7+X8+X9+X10+X11+X12+X13,0) | Y15: =IF(Y3=1,Y7+Y8+Y9+Y10+Y11+Y12+Y13,0) | Z15: =IF(Z3=1,Z7+Z8+Z9+Z10+Z11+Z12+Z13,0) | AA15: =IF(AA3=1,AA7+AA8+AA9+AA10+AA11+AA12+AA13,0) | AB15: =IF(AB3=1,AB7+AB8+AB9+AB10+AB11+AB12+AB13,0) | AC15: =IF(AC3=1,AC7+AC8+AC9+AC10+AC11+AC12+AC13,0) | ... AK15: =IF(AK3=1,AK7+AK8+AK9+AK10+AK11+AK12+AK13,0) | AM15: =IF(AM3=1,AM7+AM8+AM9+AM10+AM11+AM12+AM13,0) | AN15: =IF(AN3=1,AN7+AN8+AN9+AN10+AN11+AN12+AN13,0) | AO15: =IF(AO3=1,AO7+AO8+AO9+AO10+AO11+AO12+AO13,0) | AP15: =IF(AP3=1,AP7+AP8+AP9+AP10+AP11+AP12+AP13,0) | AQ15: =IF(AQ3=1,AQ7+AQ8+AQ9+AQ10+AQ11+AQ12+AQ13,0) | AR15: =IF(AR3=1,AR7+AR8+AR9+AR10+AR11+AR12+AR13,0) | AS15: =IF(AS3=1,AS7+AS8+AS9+AS10+AS11+AS12+AS13,0) | AT15: =IF(AT3=1,AT7+AT8+AT9+AT10+AT11+AT12+AT13,0) | ... BB15: =IF(BB3=1,BB7+BB8+BB9+BB10+BB11+BB12+BB13,0) | BD15: =IF(BD3=1,BD7+BD8+BD9+BD10+BD11+BD12+BD13,0) | BE15: =IF(BE3=1,BE7+BE8+BE9+BE10+BE11+BE12+BE13,0) | BF15: =IF(BF3=1,BF7+BF8+BF9+BF10+BF11+BF12+BF13,0) | BG15: =IF(BG3=1,BG7+BG8+BG9+BG10+BG11+BG12+BG13,0) | BH15: =IF(BH3=1,BH7+BH8+BH9+BH10+BH11+BH12+BH13,0) | BI15: =IF(BI3=1,BI7+BI8+BI9+BI10+BI11+BI12+BI13,0) | BJ15: =IF(BJ3=1,BJ7+BJ8+BJ9+BJ10+BJ11+BJ12+BJ13,0) | BK15: =IF(BK3=1,BK7+BK8+BK9+BK10+BK11+BK12+BK13,0) | ... BS15: =IF(BS3=1,BS7+BS8+BS9+BS10+BS11+BS12+BS13,0)
B16: srcAmt | C16: =IF(C5>0,N(INDEX('Inputs'!$D$59:$D$70,C5)),0) | E16: =IF(E5>0,N(INDEX('Inputs'!$D$59:$D$70,E5)),0) | F16: =IF(F5>0,N(INDEX('Inputs'!$D$59:$D$70,F5)),0) | G16: =IF(G5>0,N(INDEX('Inputs'!$D$59:$D$70,G5)),0) | H16: =IF(H5>0,N(INDEX('Inputs'!$D$59:$D$70,H5)),0) | I16: =IF(I5>0,N(INDEX('Inputs'!$D$59:$D$70,I5)),0) | J16: =IF(J5>0,N(INDEX('Inputs'!$D$59:$D$70,J5)),0) | K16: =IF(K5>0,N(INDEX('Inputs'!$D$59:$D$70,K5)),0) | L16: =IF(L5>0,N(INDEX('Inputs'!$D$59:$D$70,L5)),0) | ... T16: =IF(T5>0,N(INDEX('Inputs'!$D$59:$D$70,T5)),0) | V16: =IF(V5>0,N(INDEX('Inputs'!$D$59:$D$70,V5)),0) | W16: =IF(W5>0,N(INDEX('Inputs'!$D$59:$D$70,W5)),0) | X16: =IF(X5>0,N(INDEX('Inputs'!$D$59:$D$70,X5)),0) | Y16: =IF(Y5>0,N(INDEX('Inputs'!$D$59:$D$70,Y5)),0) | Z16: =IF(Z5>0,N(INDEX('Inputs'!$D$59:$D$70,Z5)),0) | AA16: =IF(AA5>0,N(INDEX('Inputs'!$D$59:$D$70,AA5)),0) | AB16: =IF(AB5>0,N(INDEX('Inputs'!$D$59:$D$70,AB5)),0) | AC16: =IF(AC5>0,N(INDEX('Inputs'!$D$59:$D$70,AC5)),0) | ... AK16: =IF(AK5>0,N(INDEX('Inputs'!$D$59:$D$70,AK5)),0) | AM16: =IF(AM5>0,N(INDEX('Inputs'!$D$59:$D$70,AM5)),0) | AN16: =IF(AN5>0,N(INDEX('Inputs'!$D$59:$D$70,AN5)),0) | AO16: =IF(AO5>0,N(INDEX('Inputs'!$D$59:$D$70,AO5)),0) | AP16: =IF(AP5>0,N(INDEX('Inputs'!$D$59:$D$70,AP5)),0) | AQ16: =IF(AQ5>0,N(INDEX('Inputs'!$D$59:$D$70,AQ5)),0) | AR16: =IF(AR5>0,N(INDEX('Inputs'!$D$59:$D$70,AR5)),0) | AS16: =IF(AS5>0,N(INDEX('Inputs'!$D$59:$D$70,AS5)),0) | AT16: =IF(AT5>0,N(INDEX('Inputs'!$D$59:$D$70,AT5)),0) | ... BB16: =IF(BB5>0,N(INDEX('Inputs'!$D$59:$D$70,BB5)),0) | BD16: =IF(BD5>0,N(INDEX('Inputs'!$D$59:$D$70,BD5)),0) | BE16: =IF(BE5>0,N(INDEX('Inputs'!$D$59:$D$70,BE5)),0) | BF16: =IF(BF5>0,N(INDEX('Inputs'!$D$59:$D$70,BF5)),0) | BG16: =IF(BG5>0,N(INDEX('Inputs'!$D$59:$D$70,BG5)),0) | BH16: =IF(BH5>0,N(INDEX('Inputs'!$D$59:$D$70,BH5)),0) | BI16: =IF(BI5>0,N(INDEX('Inputs'!$D$59:$D$70,BI5)),0) | BJ16: =IF(BJ5>0,N(INDEX('Inputs'!$D$59:$D$70,BJ5)),0) | BK16: =IF(BK5>0,N(INDEX('Inputs'!$D$59:$D$70,BK5)),0) | ... BS16: =IF(BS5>0,N(INDEX('Inputs'!$D$59:$D$70,BS5)),0)
B17: srcSp | C17: =IF(C5>0,IF(INDEX('Inputs'!$C$59:$C$70,C5)="Spouse",1,0),0) | E17: =IF(E5>0,IF(INDEX('Inputs'!$C$59:$C$70,E5)="Spouse",1,0),0) | F17: =IF(F5>0,IF(INDEX('Inputs'!$C$59:$C$70,F5)="Spouse",1,0),0) | G17: =IF(G5>0,IF(INDEX('Inputs'!$C$59:$C$70,G5)="Spouse",1,0),0) | H17: =IF(H5>0,IF(INDEX('Inputs'!$C$59:$C$70,H5)="Spouse",1,0),0) | I17: =IF(I5>0,IF(INDEX('Inputs'!$C$59:$C$70,I5)="Spouse",1,0),0) | J17: =IF(J5>0,IF(INDEX('Inputs'!$C$59:$C$70,J5)="Spouse",1,0),0) | K17: =IF(K5>0,IF(INDEX('Inputs'!$C$59:$C$70,K5)="Spouse",1,0),0) | L17: =IF(L5>0,IF(INDEX('Inputs'!$C$59:$C$70,L5)="Spouse",1,0),0) | ... T17: =IF(T5>0,IF(INDEX('Inputs'!$C$59:$C$70,T5)="Spouse",1,0),0) | V17: =IF(V5>0,IF(INDEX('Inputs'!$C$59:$C$70,V5)="Spouse",1,0),0) | W17: =IF(W5>0,IF(INDEX('Inputs'!$C$59:$C$70,W5)="Spouse",1,0),0) | X17: =IF(X5>0,IF(INDEX('Inputs'!$C$59:$C$70,X5)="Spouse",1,0),0) | Y17: =IF(Y5>0,IF(INDEX('Inputs'!$C$59:$C$70,Y5)="Spouse",1,0),0) | Z17: =IF(Z5>0,IF(INDEX('Inputs'!$C$59:$C$70,Z5)="Spouse",1,0),0) | AA17: =IF(AA5>0,IF(INDEX('Inputs'!$C$59:$C$70,AA5)="Spouse",1,0),0) | AB17: =IF(AB5>0,IF(INDEX('Inputs'!$C$59:$C$70,AB5)="Spouse",1,0),0) | AC17: =IF(AC5>0,IF(INDEX('Inputs'!$C$59:$C$70,AC5)="Spouse",1,0),0) | ... AK17: =IF(AK5>0,IF(INDEX('Inputs'!$C$59:$C$70,AK5)="Spouse",1,0),0) | AM17: =IF(AM5>0,IF(INDEX('Inputs'!$C$59:$C$70,AM5)="Spouse",1,0),0) | AN17: =IF(AN5>0,IF(INDEX('Inputs'!$C$59:$C$70,AN5)="Spouse",1,0),0) | AO17: =IF(AO5>0,IF(INDEX('Inputs'!$C$59:$C$70,AO5)="Spouse",1,0),0) | AP17: =IF(AP5>0,IF(INDEX('Inputs'!$C$59:$C$70,AP5)="Spouse",1,0),0) | AQ17: =IF(AQ5>0,IF(INDEX('Inputs'!$C$59:$C$70,AQ5)="Spouse",1,0),0) | AR17: =IF(AR5>0,IF(INDEX('Inputs'!$C$59:$C$70,AR5)="Spouse",1,0),0) | AS17: =IF(AS5>0,IF(INDEX('Inputs'!$C$59:$C$70,AS5)="Spouse",1,0),0) | AT17: =IF(AT5>0,IF(INDEX('Inputs'!$C$59:$C$70,AT5)="Spouse",1,0),0) | ... BB17: =IF(BB5>0,IF(INDEX('Inputs'!$C$59:$C$70,BB5)="Spouse",1,0),0) | BD17: =IF(BD5>0,IF(INDEX('Inputs'!$C$59:$C$70,BD5)="Spouse",1,0),0) | BE17: =IF(BE5>0,IF(INDEX('Inputs'!$C$59:$C$70,BE5)="Spouse",1,0),0) | BF17: =IF(BF5>0,IF(INDEX('Inputs'!$C$59:$C$70,BF5)="Spouse",1,0),0) | BG17: =IF(BG5>0,IF(INDEX('Inputs'!$C$59:$C$70,BG5)="Spouse",1,0),0) | BH17: =IF(BH5>0,IF(INDEX('Inputs'!$C$59:$C$70,BH5)="Spouse",1,0),0) | BI17: =IF(BI5>0,IF(INDEX('Inputs'!$C$59:$C$70,BI5)="Spouse",1,0),0) | BJ17: =IF(BJ5>0,IF(INDEX('Inputs'!$C$59:$C$70,BJ5)="Spouse",1,0),0) | BK17: =IF(BK5>0,IF(INDEX('Inputs'!$C$59:$C$70,BK5)="Spouse",1,0),0) | ... BS17: =IF(BS5>0,IF(INDEX('Inputs'!$C$59:$C$70,BS5)="Spouse",1,0),0)
B18: srcBad | C18: =IF(AND(C3>=2,C5=0),1,0) | E18: =IF(AND(E3>=2,E5=0),1,0) | F18: =IF(AND(F3>=2,F5=0),1,0) | G18: =IF(AND(G3>=2,G5=0),1,0) | H18: =IF(AND(H3>=2,H5=0),1,0) | I18: =IF(AND(I3>=2,I5=0),1,0) | J18: =IF(AND(J3>=2,J5=0),1,0) | K18: =IF(AND(K3>=2,K5=0),1,0) | L18: =IF(AND(L3>=2,L5=0),1,0) | ... T18: =IF(AND(T3>=2,T5=0),1,0) | V18: =IF(AND(V3>=2,V5=0),1,0) | W18: =IF(AND(W3>=2,W5=0),1,0) | X18: =IF(AND(X3>=2,X5=0),1,0) | Y18: =IF(AND(Y3>=2,Y5=0),1,0) | Z18: =IF(AND(Z3>=2,Z5=0),1,0) | AA18: =IF(AND(AA3>=2,AA5=0),1,0) | AB18: =IF(AND(AB3>=2,AB5=0),1,0) | AC18: =IF(AND(AC3>=2,AC5=0),1,0) | ... AK18: =IF(AND(AK3>=2,AK5=0),1,0) | AM18: =IF(AND(AM3>=2,AM5=0),1,0) | AN18: =IF(AND(AN3>=2,AN5=0),1,0) | AO18: =IF(AND(AO3>=2,AO5=0),1,0) | AP18: =IF(AND(AP3>=2,AP5=0),1,0) | AQ18: =IF(AND(AQ3>=2,AQ5=0),1,0) | AR18: =IF(AND(AR3>=2,AR5=0),1,0) | AS18: =IF(AND(AS3>=2,AS5=0),1,0) | AT18: =IF(AND(AT3>=2,AT5=0),1,0) | ... BB18: =IF(AND(BB3>=2,BB5=0),1,0) | BD18: =IF(AND(BD3>=2,BD5=0),1,0) | BE18: =IF(AND(BE3>=2,BE5=0),1,0) | BF18: =IF(AND(BF3>=2,BF5=0),1,0) | BG18: =IF(AND(BG3>=2,BG5=0),1,0) | BH18: =IF(AND(BH3>=2,BH5=0),1,0) | BI18: =IF(AND(BI3>=2,BI5=0),1,0) | BJ18: =IF(AND(BJ3>=2,BJ5=0),1,0) | BK18: =IF(AND(BK3>=2,BK5=0),1,0) | ... BS18: =IF(AND(BS3>=2,BS5=0),1,0)
B19: net | C19: =ROUND('Workings'!$C$33+C15+C17*C14,2) | E19: =ROUND('Workings'!$C$33+E15+E17*E14,2) | F19: =ROUND('Workings'!$C$33+F15+F17*F14,2) | G19: =ROUND('Workings'!$C$33+G15+G17*G14,2) | H19: =ROUND('Workings'!$C$33+H15+H17*H14,2) | I19: =ROUND('Workings'!$C$33+I15+I17*I14,2) | J19: =ROUND('Workings'!$C$33+J15+J17*J14,2) | K19: =ROUND('Workings'!$C$33+K15+K17*K14,2) | L19: =ROUND('Workings'!$C$33+L15+L17*L14,2) | ... T19: =ROUND('Workings'!$C$33+T15+T17*T14,2) | V19: =ROUND('Workings'!$C$33+V15+V17*V14,2) | W19: =ROUND('Workings'!$C$33+W15+W17*W14,2) | X19: =ROUND('Workings'!$C$33+X15+X17*X14,2) | Y19: =ROUND('Workings'!$C$33+Y15+Y17*Y14,2) | Z19: =ROUND('Workings'!$C$33+Z15+Z17*Z14,2) | AA19: =ROUND('Workings'!$C$33+AA15+AA17*AA14,2) | AB19: =ROUND('Workings'!$C$33+AB15+AB17*AB14,2) | AC19: =ROUND('Workings'!$C$33+AC15+AC17*AC14,2) | ... AK19: =ROUND('Workings'!$C$33+AK15+AK17*AK14,2) | AM19: =ROUND('Workings'!$C$33+AM15+AM17*AM14,2) | AN19: =ROUND('Workings'!$C$33+AN15+AN17*AN14,2) | AO19: =ROUND('Workings'!$C$33+AO15+AO17*AO14,2) | AP19: =ROUND('Workings'!$C$33+AP15+AP17*AP14,2) | AQ19: =ROUND('Workings'!$C$33+AQ15+AQ17*AQ14,2) | AR19: =ROUND('Workings'!$C$33+AR15+AR17*AR14,2) | AS19: =ROUND('Workings'!$C$33+AS15+AS17*AS14,2) | AT19: =ROUND('Workings'!$C$33+AT15+AT17*AT14,2) | ... BB19: =ROUND('Workings'!$C$33+BB15+BB17*BB14,2) | BD19: =ROUND('Workings'!$C$33+BD15+BD17*BD14,2) | BE19: =ROUND('Workings'!$C$33+BE15+BE17*BE14,2) | BF19: =ROUND('Workings'!$C$33+BF15+BF17*BF14,2) | BG19: =ROUND('Workings'!$C$33+BG15+BG17*BG14,2) | BH19: =ROUND('Workings'!$C$33+BH15+BH17*BH14,2) | BI19: =ROUND('Workings'!$C$33+BI15+BI17*BI14,2) | BJ19: =ROUND('Workings'!$C$33+BJ15+BJ17*BJ14,2) | BK19: =ROUND('Workings'!$C$33+BK15+BK17*BK14,2) | ... BS19: =ROUND('Workings'!$C$33+BS15+BS17*BS14,2)
B20: duty | C20: =ROUND(IF(MAX(0,C19-'Inputs'!$C$115)<='Inputs'!$C$117,MAX(0,C19-'Inputs'!$C$115)*'Inputs'!$C$116/100,'Inputs'!$C$117*'Inputs'!$C$116/100+(MAX(0,C19-'Inputs'!$C$115)-'Inputs'!$C$117)*'Inputs'!$C$118/100),2) | E20: =ROUND(IF(MAX(0,E19-'Inputs'!$C$115)<='Inputs'!$C$117,MAX(0,E19-'Inputs'!$C$115)*'Inputs'!$C$116/100,'Inputs'!$C$117*'Inputs'!$C$116/100+(MAX(0,E19-'Inputs'!$C$115)-'Inputs'!$C$117)*'Inputs'!$C$118/100),2) | F20: =ROUND(IF(MAX(0,F19-'Inputs'!$C$115)<='Inputs'!$C$117,MAX(0,F19-'Inputs'!$C$115)*'Inputs'!$C$116/100,'Inputs'!$C$117*'Inputs'!$C$116/100+(MAX(0,F19-'Inputs'!$C$115)-'Inputs'!$C$117)*'Inputs'!$C$118/100),2) | G20: =ROUND(IF(MAX(0,G19-'Inputs'!$C$115)<='Inputs'!$C$117,MAX(0,G19-'Inputs'!$C$115)*'Inputs'!$C$116/100,'Inputs'!$C$117*'Inputs'!$C$116/100+(MAX(0,G19-'Inputs'!$C$115)-'Inputs'!$C$117)*'Inputs'!$C$118/100),2) | H20: =ROUND(IF(MAX(0,H19-'Inputs'!$C$115)<='Inputs'!$C$117,MAX(0,H19-'Inputs'!$C$115)*'Inputs'!$C$116/100,'Inputs'!$C$117*'Inputs'!$C$116/100+(MAX(0,H19-'Inputs'!$C$115)-'Inputs'!$C$117)*'Inputs'!$C$118/100),2) | I20: =ROUND(IF(MAX(0,I19-'Inputs'!$C$115)<='Inputs'!$C$117,MAX(0,I19-'Inputs'!$C$115)*'Inputs'!$C$116/100,'Inputs'!$C$117*'Inputs'!$C$116/100+(MAX(0,I19-'Inputs'!$C$115)-'Inputs'!$C$117)*'Inputs'!$C$118/100),2) | J20: =ROUND(IF(MAX(0,J19-'Inputs'!$C$115)<='Inputs'!$C$117,MAX(0,J19-'Inputs'!$C$115)*'Inputs'!$C$116/100,'Inputs'!$C$117*'Inputs'!$C$116/100+(MAX(0,J19-'Inputs'!$C$115)-'Inputs'!$C$117)*'Inputs'!$C$118/100),2) | K20: =ROUND(IF(MAX(0,K19-'Inputs'!$C$115)<='Inputs'!$C$117,MAX(0,K19-'Inputs'!$C$115)*'Inputs'!$C$116/100,'Inputs'!$C$117*'Inputs'!$C$116/100+(MAX(0,K19-'Inputs'!$C$115)-'Inputs'!$C$117)*'Inputs'!$C$118/100),2) | L20: =ROUND(IF(MAX(0,L19-'Inputs'!$C$115)<='Inputs'!$C$117,MAX(0,L19-'Inputs'!$C$115)*'Inputs'!$C$116/100,'Inputs'!$C$117*'Inputs'!$C$116/100+(MAX(0,L19-'Inputs'!$C$115)-'Inputs'!$C$117)*'Inputs'!$C$118/100),2) | ... T20: =ROUND(IF(MAX(0,T19-'Inputs'!$C$115)<='Inputs'!$C$117,MAX(0,T19-'Inputs'!$C$115)*'Inputs'!$C$116/100,'Inputs'!$C$117*'Inputs'!$C$116/100+(MAX(0,T19-'Inputs'!$C$115)-'Inputs'!$C$117)*'Inputs'!$C$118/100),2) | V20: =ROUND(IF(MAX(0,V19-'Inputs'!$C$115)<='Inputs'!$C$117,MAX(0,V19-'Inputs'!$C$115)*'Inputs'!$C$116/100,'Inputs'!$C$117*'Inputs'!$C$116/100+(MAX(0,V19-'Inputs'!$C$115)-'Inputs'!$C$117)*'Inputs'!$C$118/100),2) | W20: =ROUND(IF(MAX(0,W19-'Inputs'!$C$115)<='Inputs'!$C$117,MAX(0,W19-'Inputs'!$C$115)*'Inputs'!$C$116/100,'Inputs'!$C$117*'Inputs'!$C$116/100+(MAX(0,W19-'Inputs'!$C$115)-'Inputs'!$C$117)*'Inputs'!$C$118/100),2) | X20: =ROUND(IF(MAX(0,X19-'Inputs'!$C$115)<='Inputs'!$C$117,MAX(0,X19-'Inputs'!$C$115)*'Inputs'!$C$116/100,'Inputs'!$C$117*'Inputs'!$C$116/100+(MAX(0,X19-'Inputs'!$C$115)-'Inputs'!$C$117)*'Inputs'!$C$118/100),2) | Y20: =ROUND(IF(MAX(0,Y19-'Inputs'!$C$115)<='Inputs'!$C$117,MAX(0,Y19-'Inputs'!$C$115)*'Inputs'!$C$116/100,'Inputs'!$C$117*'Inputs'!$C$116/100+(MAX(0,Y19-'Inputs'!$C$115)-'Inputs'!$C$117)*'Inputs'!$C$118/100),2) | Z20: =ROUND(IF(MAX(0,Z19-'Inputs'!$C$115)<='Inputs'!$C$117,MAX(0,Z19-'Inputs'!$C$115)*'Inputs'!$C$116/100,'Inputs'!$C$117*'Inputs'!$C$116/100+(MAX(0,Z19-'Inputs'!$C$115)-'Inputs'!$C$117)*'Inputs'!$C$118/100),2) | AA20: =ROUND(IF(MAX(0,AA19-'Inputs'!$C$115)<='Inputs'!$C$117,MAX(0,AA19-'Inputs'!$C$115)*'Inputs'!$C$116/100,'Inputs'!$C$117*'Inputs'!$C$116/100+(MAX(0,AA19-'Inputs'!$C$115)-'Inputs'!$C$117)*'Inputs'!$C$118/100),2) | AB20: =ROUND(IF(MAX(0,AB19-'Inputs'!$C$115)<='Inputs'!$C$117,MAX(0,AB19-'Inputs'!$C$115)*'Inputs'!$C$116/100,'Inputs'!$C$117*'Inputs'!$C$116/100+(MAX(0,AB19-'Inputs'!$C$115)-'Inputs'!$C$117)*'Inputs'!$C$118/100),2) | AC20: =ROUND(IF(MAX(0,AC19-'Inputs'!$C$115)<='Inputs'!$C$117,MAX(0,AC19-'Inputs'!$C$115)*'Inputs'!$C$116/100,'Inputs'!$C$117*'Inputs'!$C$116/100+(MAX(0,AC19-'Inputs'!$C$115)-'Inputs'!$C$117)*'Inputs'!$C$118/100),2) | ... AK20: =ROUND(IF(MAX(0,AK19-'Inputs'!$C$115)<='Inputs'!$C$117,MAX(0,AK19-'Inputs'!$C$115)*'Inputs'!$C$116/100,'Inputs'!$C$117*'Inputs'!$C$116/100+(MAX(0,AK19-'Inputs'!$C$115)-'Inputs'!$C$117)*'Inputs'!$C$118/100),2) | AM20: =ROUND(IF(MAX(0,AM19-'Inputs'!$C$115)<='Inputs'!$C$117,MAX(0,AM19-'Inputs'!$C$115)*'Inputs'!$C$116/100,'Inputs'!$C$117*'Inputs'!$C$116/100+(MAX(0,AM19-'Inputs'!$C$115)-'Inputs'!$C$117)*'Inputs'!$C$118/100),2) | AN20: =ROUND(IF(MAX(0,AN19-'Inputs'!$C$115)<='Inputs'!$C$117,MAX(0,AN19-'Inputs'!$C$115)*'Inputs'!$C$116/100,'Inputs'!$C$117*'Inputs'!$C$116/100+(MAX(0,AN19-'Inputs'!$C$115)-'Inputs'!$C$117)*'Inputs'!$C$118/100),2) | AO20: =ROUND(IF(MAX(0,AO19-'Inputs'!$C$115)<='Inputs'!$C$117,MAX(0,AO19-'Inputs'!$C$115)*'Inputs'!$C$116/100,'Inputs'!$C$117*'Inputs'!$C$116/100+(MAX(0,AO19-'Inputs'!$C$115)-'Inputs'!$C$117)*'Inputs'!$C$118/100),2) | AP20: =ROUND(IF(MAX(0,AP19-'Inputs'!$C$115)<='Inputs'!$C$117,MAX(0,AP19-'Inputs'!$C$115)*'Inputs'!$C$116/100,'Inputs'!$C$117*'Inputs'!$C$116/100+(MAX(0,AP19-'Inputs'!$C$115)-'Inputs'!$C$117)*'Inputs'!$C$118/100),2) | AQ20: =ROUND(IF(MAX(0,AQ19-'Inputs'!$C$115)<='Inputs'!$C$117,MAX(0,AQ19-'Inputs'!$C$115)*'Inputs'!$C$116/100,'Inputs'!$C$117*'Inputs'!$C$116/100+(MAX(0,AQ19-'Inputs'!$C$115)-'Inputs'!$C$117)*'Inputs'!$C$118/100),2) | AR20: =ROUND(IF(MAX(0,AR19-'Inputs'!$C$115)<='Inputs'!$C$117,MAX(0,AR19-'Inputs'!$C$115)*'Inputs'!$C$116/100,'Inputs'!$C$117*'Inputs'!$C$116/100+(MAX(0,AR19-'Inputs'!$C$115)-'Inputs'!$C$117)*'Inputs'!$C$118/100),2) | AS20: =ROUND(IF(MAX(0,AS19-'Inputs'!$C$115)<='Inputs'!$C$117,MAX(0,AS19-'Inputs'!$C$115)*'Inputs'!$C$116/100,'Inputs'!$C$117*'Inputs'!$C$116/100+(MAX(0,AS19-'Inputs'!$C$115)-'Inputs'!$C$117)*'Inputs'!$C$118/100),2) | AT20: =ROUND(IF(MAX(0,AT19-'Inputs'!$C$115)<='Inputs'!$C$117,MAX(0,AT19-'Inputs'!$C$115)*'Inputs'!$C$116/100,'Inputs'!$C$117*'Inputs'!$C$116/100+(MAX(0,AT19-'Inputs'!$C$115)-'Inputs'!$C$117)*'Inputs'!$C$118/100),2) | ... BB20: =ROUND(IF(MAX(0,BB19-'Inputs'!$C$115)<='Inputs'!$C$117,MAX(0,BB19-'Inputs'!$C$115)*'Inputs'!$C$116/100,'Inputs'!$C$117*'Inputs'!$C$116/100+(MAX(0,BB19-'Inputs'!$C$115)-'Inputs'!$C$117)*'Inputs'!$C$118/100),2) | BD20: =ROUND(IF(MAX(0,BD19-'Inputs'!$C$115)<='Inputs'!$C$117,MAX(0,BD19-'Inputs'!$C$115)*'Inputs'!$C$116/100,'Inputs'!$C$117*'Inputs'!$C$116/100+(MAX(0,BD19-'Inputs'!$C$115)-'Inputs'!$C$117)*'Inputs'!$C$118/100),2) | BE20: =ROUND(IF(MAX(0,BE19-'Inputs'!$C$115)<='Inputs'!$C$117,MAX(0,BE19-'Inputs'!$C$115)*'Inputs'!$C$116/100,'Inputs'!$C$117*'Inputs'!$C$116/100+(MAX(0,BE19-'Inputs'!$C$115)-'Inputs'!$C$117)*'Inputs'!$C$118/100),2) | BF20: =ROUND(IF(MAX(0,BF19-'Inputs'!$C$115)<='Inputs'!$C$117,MAX(0,BF19-'Inputs'!$C$115)*'Inputs'!$C$116/100,'Inputs'!$C$117*'Inputs'!$C$116/100+(MAX(0,BF19-'Inputs'!$C$115)-'Inputs'!$C$117)*'Inputs'!$C$118/100),2) | BG20: =ROUND(IF(MAX(0,BG19-'Inputs'!$C$115)<='Inputs'!$C$117,MAX(0,BG19-'Inputs'!$C$115)*'Inputs'!$C$116/100,'Inputs'!$C$117*'Inputs'!$C$116/100+(MAX(0,BG19-'Inputs'!$C$115)-'Inputs'!$C$117)*'Inputs'!$C$118/100),2) | BH20: =ROUND(IF(MAX(0,BH19-'Inputs'!$C$115)<='Inputs'!$C$117,MAX(0,BH19-'Inputs'!$C$115)*'Inputs'!$C$116/100,'Inputs'!$C$117*'Inputs'!$C$116/100+(MAX(0,BH19-'Inputs'!$C$115)-'Inputs'!$C$117)*'Inputs'!$C$118/100),2) | BI20: =ROUND(IF(MAX(0,BI19-'Inputs'!$C$115)<='Inputs'!$C$117,MAX(0,BI19-'Inputs'!$C$115)*'Inputs'!$C$116/100,'Inputs'!$C$117*'Inputs'!$C$116/100+(MAX(0,BI19-'Inputs'!$C$115)-'Inputs'!$C$117)*'Inputs'!$C$118/100),2) | BJ20: =ROUND(IF(MAX(0,BJ19-'Inputs'!$C$115)<='Inputs'!$C$117,MAX(0,BJ19-'Inputs'!$C$115)*'Inputs'!$C$116/100,'Inputs'!$C$117*'Inputs'!$C$116/100+(MAX(0,BJ19-'Inputs'!$C$115)-'Inputs'!$C$117)*'Inputs'!$C$118/100),2) | BK20: =ROUND(IF(MAX(0,BK19-'Inputs'!$C$115)<='Inputs'!$C$117,MAX(0,BK19-'Inputs'!$C$115)*'Inputs'!$C$116/100,'Inputs'!$C$117*'Inputs'!$C$116/100+(MAX(0,BK19-'Inputs'!$C$115)-'Inputs'!$C$117)*'Inputs'!$C$118/100),2) | ... BS20: =ROUND(IF(MAX(0,BS19-'Inputs'!$C$115)<='Inputs'!$C$117,MAX(0,BS19-'Inputs'!$C$115)*'Inputs'!$C$116/100,'Inputs'!$C$117*'Inputs'!$C$116/100+(MAX(0,BS19-'Inputs'!$C$115)-'Inputs'!$C$117)*'Inputs'!$C$118/100),2)
B21: avg | C21: =IF(C19>0,C20/C19,0) | E21: =IF(E19>0,E20/E19,0) | F21: =IF(F19>0,F20/F19,0) | G21: =IF(G19>0,G20/G19,0) | H21: =IF(H19>0,H20/H19,0) | I21: =IF(I19>0,I20/I19,0) | J21: =IF(J19>0,J20/J19,0) | K21: =IF(K19>0,K20/K19,0) | L21: =IF(L19>0,L20/L19,0) | ... T21: =IF(T19>0,T20/T19,0) | V21: =IF(V19>0,V20/V19,0) | W21: =IF(W19>0,W20/W19,0) | X21: =IF(X19>0,X20/X19,0) | Y21: =IF(Y19>0,Y20/Y19,0) | Z21: =IF(Z19>0,Z20/Z19,0) | AA21: =IF(AA19>0,AA20/AA19,0) | AB21: =IF(AB19>0,AB20/AB19,0) | AC21: =IF(AC19>0,AC20/AC19,0) | ... AK21: =IF(AK19>0,AK20/AK19,0) | AM21: =IF(AM19>0,AM20/AM19,0) | AN21: =IF(AN19>0,AN20/AN19,0) | AO21: =IF(AO19>0,AO20/AO19,0) | AP21: =IF(AP19>0,AP20/AP19,0) | AQ21: =IF(AQ19>0,AQ20/AQ19,0) | AR21: =IF(AR19>0,AR20/AR19,0) | AS21: =IF(AS19>0,AS20/AS19,0) | AT21: =IF(AT19>0,AT20/AT19,0) | ... BB21: =IF(BB19>0,BB20/BB19,0) | BD21: =IF(BD19>0,BD20/BD19,0) | BE21: =IF(BE19>0,BE20/BE19,0) | BF21: =IF(BF19>0,BF20/BF19,0) | BG21: =IF(BG19>0,BG20/BG19,0) | BH21: =IF(BH19>0,BH20/BH19,0) | BI21: =IF(BI19>0,BI20/BI19,0) | BJ21: =IF(BJ19>0,BJ20/BJ19,0) | BK21: =IF(BK19>0,BK20/BK19,0) | ... BS21: =IF(BS19>0,BS20/BS19,0)
B22: dNamed | C22: =SUMPRODUCT('Inputs'!$R$59:$R$70,ROUND(C21*('Inputs'!$D$59:$D$70-('Inputs'!$P$59:$P$70=C5)*C14),2)) | E22: =SUMPRODUCT('Inputs'!$R$59:$R$70,ROUND(E21*('Inputs'!$D$59:$D$70-('Inputs'!$P$59:$P$70=E5)*E14),2)) | F22: =SUMPRODUCT('Inputs'!$R$59:$R$70,ROUND(F21*('Inputs'!$D$59:$D$70-('Inputs'!$P$59:$P$70=F5)*F14),2)) | G22: =SUMPRODUCT('Inputs'!$R$59:$R$70,ROUND(G21*('Inputs'!$D$59:$D$70-('Inputs'!$P$59:$P$70=G5)*G14),2)) | H22: =SUMPRODUCT('Inputs'!$R$59:$R$70,ROUND(H21*('Inputs'!$D$59:$D$70-('Inputs'!$P$59:$P$70=H5)*H14),2)) | I22: =SUMPRODUCT('Inputs'!$R$59:$R$70,ROUND(I21*('Inputs'!$D$59:$D$70-('Inputs'!$P$59:$P$70=I5)*I14),2)) | J22: =SUMPRODUCT('Inputs'!$R$59:$R$70,ROUND(J21*('Inputs'!$D$59:$D$70-('Inputs'!$P$59:$P$70=J5)*J14),2)) | K22: =SUMPRODUCT('Inputs'!$R$59:$R$70,ROUND(K21*('Inputs'!$D$59:$D$70-('Inputs'!$P$59:$P$70=K5)*K14),2)) | L22: =SUMPRODUCT('Inputs'!$R$59:$R$70,ROUND(L21*('Inputs'!$D$59:$D$70-('Inputs'!$P$59:$P$70=L5)*L14),2)) | ... T22: =SUMPRODUCT('Inputs'!$R$59:$R$70,ROUND(T21*('Inputs'!$D$59:$D$70-('Inputs'!$P$59:$P$70=T5)*T14),2)) | V22: =SUMPRODUCT('Inputs'!$R$59:$R$70,ROUND(V21*('Inputs'!$D$59:$D$70-('Inputs'!$P$59:$P$70=V5)*V14),2)) | W22: =SUMPRODUCT('Inputs'!$R$59:$R$70,ROUND(W21*('Inputs'!$D$59:$D$70-('Inputs'!$P$59:$P$70=W5)*W14),2)) | X22: =SUMPRODUCT('Inputs'!$R$59:$R$70,ROUND(X21*('Inputs'!$D$59:$D$70-('Inputs'!$P$59:$P$70=X5)*X14),2)) | Y22: =SUMPRODUCT('Inputs'!$R$59:$R$70,ROUND(Y21*('Inputs'!$D$59:$D$70-('Inputs'!$P$59:$P$70=Y5)*Y14),2)) | Z22: =SUMPRODUCT('Inputs'!$R$59:$R$70,ROUND(Z21*('Inputs'!$D$59:$D$70-('Inputs'!$P$59:$P$70=Z5)*Z14),2)) | AA22: =SUMPRODUCT('Inputs'!$R$59:$R$70,ROUND(AA21*('Inputs'!$D$59:$D$70-('Inputs'!$P$59:$P$70=AA5)*AA14),2)) | AB22: =SUMPRODUCT('Inputs'!$R$59:$R$70,ROUND(AB21*('Inputs'!$D$59:$D$70-('Inputs'!$P$59:$P$70=AB5)*AB14),2)) | AC22: =SUMPRODUCT('Inputs'!$R$59:$R$70,ROUND(AC21*('Inputs'!$D$59:$D$70-('Inputs'!$P$59:$P$70=AC5)*AC14),2)) | ... AK22: =SUMPRODUCT('Inputs'!$R$59:$R$70,ROUND(AK21*('Inputs'!$D$59:$D$70-('Inputs'!$P$59:$P$70=AK5)*AK14),2)) | AM22: =SUMPRODUCT('Inputs'!$R$59:$R$70,ROUND(AM21*('Inputs'!$D$59:$D$70-('Inputs'!$P$59:$P$70=AM5)*AM14),2)) | AN22: =SUMPRODUCT('Inputs'!$R$59:$R$70,ROUND(AN21*('Inputs'!$D$59:$D$70-('Inputs'!$P$59:$P$70=AN5)*AN14),2)) | AO22: =SUMPRODUCT('Inputs'!$R$59:$R$70,ROUND(AO21*('Inputs'!$D$59:$D$70-('Inputs'!$P$59:$P$70=AO5)*AO14),2)) | AP22: =SUMPRODUCT('Inputs'!$R$59:$R$70,ROUND(AP21*('Inputs'!$D$59:$D$70-('Inputs'!$P$59:$P$70=AP5)*AP14),2)) | AQ22: =SUMPRODUCT('Inputs'!$R$59:$R$70,ROUND(AQ21*('Inputs'!$D$59:$D$70-('Inputs'!$P$59:$P$70=AQ5)*AQ14),2)) | AR22: =SUMPRODUCT('Inputs'!$R$59:$R$70,ROUND(AR21*('Inputs'!$D$59:$D$70-('Inputs'!$P$59:$P$70=AR5)*AR14),2)) | AS22: =SUMPRODUCT('Inputs'!$R$59:$R$70,ROUND(AS21*('Inputs'!$D$59:$D$70-('Inputs'!$P$59:$P$70=AS5)*AS14),2)) | AT22: =SUMPRODUCT('Inputs'!$R$59:$R$70,ROUND(AT21*('Inputs'!$D$59:$D$70-('Inputs'!$P$59:$P$70=AT5)*AT14),2)) | ... BB22: =SUMPRODUCT('Inputs'!$R$59:$R$70,ROUND(BB21*('Inputs'!$D$59:$D$70-('Inputs'!$P$59:$P$70=BB5)*BB14),2)) | BD22: =SUMPRODUCT('Inputs'!$R$59:$R$70,ROUND(BD21*('Inputs'!$D$59:$D$70-('Inputs'!$P$59:$P$70=BD5)*BD14),2)) | BE22: =SUMPRODUCT('Inputs'!$R$59:$R$70,ROUND(BE21*('Inputs'!$D$59:$D$70-('Inputs'!$P$59:$P$70=BE5)*BE14),2)) | BF22: =SUMPRODUCT('Inputs'!$R$59:$R$70,ROUND(BF21*('Inputs'!$D$59:$D$70-('Inputs'!$P$59:$P$70=BF5)*BF14),2)) | BG22: =SUMPRODUCT('Inputs'!$R$59:$R$70,ROUND(BG21*('Inputs'!$D$59:$D$70-('Inputs'!$P$59:$P$70=BG5)*BG14),2)) | BH22: =SUMPRODUCT('Inputs'!$R$59:$R$70,ROUND(BH21*('Inputs'!$D$59:$D$70-('Inputs'!$P$59:$P$70=BH5)*BH14),2)) | BI22: =SUMPRODUCT('Inputs'!$R$59:$R$70,ROUND(BI21*('Inputs'!$D$59:$D$70-('Inputs'!$P$59:$P$70=BI5)*BI14),2)) | BJ22: =SUMPRODUCT('Inputs'!$R$59:$R$70,ROUND(BJ21*('Inputs'!$D$59:$D$70-('Inputs'!$P$59:$P$70=BJ5)*BJ14),2)) | BK22: =SUMPRODUCT('Inputs'!$R$59:$R$70,ROUND(BK21*('Inputs'!$D$59:$D$70-('Inputs'!$P$59:$P$70=BK5)*BK14),2)) | ... BS22: =SUMPRODUCT('Inputs'!$R$59:$R$70,ROUND(BS21*('Inputs'!$D$59:$D$70-('Inputs'!$P$59:$P$70=BS5)*BS14),2))
B23: dHeir | C23: =SUMPRODUCT(ROUND(C21*'Inputs'!$S$22:$S$39,2)) | E23: =SUMPRODUCT(ROUND(E21*'Inputs'!$S$22:$S$39,2)) | F23: =SUMPRODUCT(ROUND(F21*'Inputs'!$S$22:$S$39,2)) | G23: =SUMPRODUCT(ROUND(G21*'Inputs'!$S$22:$S$39,2)) | H23: =SUMPRODUCT(ROUND(H21*'Inputs'!$S$22:$S$39,2)) | I23: =SUMPRODUCT(ROUND(I21*'Inputs'!$S$22:$S$39,2)) | J23: =SUMPRODUCT(ROUND(J21*'Inputs'!$S$22:$S$39,2)) | K23: =SUMPRODUCT(ROUND(K21*'Inputs'!$S$22:$S$39,2)) | L23: =SUMPRODUCT(ROUND(L21*'Inputs'!$S$22:$S$39,2)) | ... T23: =SUMPRODUCT(ROUND(T21*'Inputs'!$S$22:$S$39,2)) | V23: =SUMPRODUCT(ROUND(V21*'Inputs'!$S$22:$S$39,2)) | W23: =SUMPRODUCT(ROUND(W21*'Inputs'!$S$22:$S$39,2)) | X23: =SUMPRODUCT(ROUND(X21*'Inputs'!$S$22:$S$39,2)) | Y23: =SUMPRODUCT(ROUND(Y21*'Inputs'!$S$22:$S$39,2)) | Z23: =SUMPRODUCT(ROUND(Z21*'Inputs'!$S$22:$S$39,2)) | AA23: =SUMPRODUCT(ROUND(AA21*'Inputs'!$S$22:$S$39,2)) | AB23: =SUMPRODUCT(ROUND(AB21*'Inputs'!$S$22:$S$39,2)) | AC23: =SUMPRODUCT(ROUND(AC21*'Inputs'!$S$22:$S$39,2)) | ... AK23: =SUMPRODUCT(ROUND(AK21*'Inputs'!$S$22:$S$39,2)) | AM23: =SUMPRODUCT(ROUND(AM21*'Inputs'!$S$22:$S$39,2)) | AN23: =SUMPRODUCT(ROUND(AN21*'Inputs'!$S$22:$S$39,2)) | AO23: =SUMPRODUCT(ROUND(AO21*'Inputs'!$S$22:$S$39,2)) | AP23: =SUMPRODUCT(ROUND(AP21*'Inputs'!$S$22:$S$39,2)) | AQ23: =SUMPRODUCT(ROUND(AQ21*'Inputs'!$S$22:$S$39,2)) | AR23: =SUMPRODUCT(ROUND(AR21*'Inputs'!$S$22:$S$39,2)) | AS23: =SUMPRODUCT(ROUND(AS21*'Inputs'!$S$22:$S$39,2)) | AT23: =SUMPRODUCT(ROUND(AT21*'Inputs'!$S$22:$S$39,2)) | ... BB23: =SUMPRODUCT(ROUND(BB21*'Inputs'!$S$22:$S$39,2)) | BD23: =SUMPRODUCT(ROUND(BD21*'Inputs'!$S$22:$S$39,2)) | BE23: =SUMPRODUCT(ROUND(BE21*'Inputs'!$S$22:$S$39,2)) | BF23: =SUMPRODUCT(ROUND(BF21*'Inputs'!$S$22:$S$39,2)) | BG23: =SUMPRODUCT(ROUND(BG21*'Inputs'!$S$22:$S$39,2)) | BH23: =SUMPRODUCT(ROUND(BH21*'Inputs'!$S$22:$S$39,2)) | BI23: =SUMPRODUCT(ROUND(BI21*'Inputs'!$S$22:$S$39,2)) | BJ23: =SUMPRODUCT(ROUND(BJ21*'Inputs'!$S$22:$S$39,2)) | BK23: =SUMPRODUCT(ROUND(BK21*'Inputs'!$S$22:$S$39,2)) | ... BS23: =SUMPRODUCT(ROUND(BS21*'Inputs'!$S$22:$S$39,2))
B24: dX | C24: =IF(OR(C3=1,C3=2),ROUND(C21*C7,2)+ROUND(C21*C8,2)+ROUND(C21*C9,2)+ROUND(C21*C10,2)+ROUND(C21*C11,2)+ROUND(C21*C12,2)+ROUND(C21*C13,2),IF(C3=3,ROUND(C21*C14,2),0)) | E24: =IF(OR(E3=1,E3=2),ROUND(E21*E7,2)+ROUND(E21*E8,2)+ROUND(E21*E9,2)+ROUND(E21*E10,2)+ROUND(E21*E11,2)+ROUND(E21*E12,2)+ROUND(E21*E13,2),IF(E3=3,ROUND(E21*E14,2),0)) | F24: =IF(OR(F3=1,F3=2),ROUND(F21*F7,2)+ROUND(F21*F8,2)+ROUND(F21*F9,2)+ROUND(F21*F10,2)+ROUND(F21*F11,2)+ROUND(F21*F12,2)+ROUND(F21*F13,2),IF(F3=3,ROUND(F21*F14,2),0)) | G24: =IF(OR(G3=1,G3=2),ROUND(G21*G7,2)+ROUND(G21*G8,2)+ROUND(G21*G9,2)+ROUND(G21*G10,2)+ROUND(G21*G11,2)+ROUND(G21*G12,2)+ROUND(G21*G13,2),IF(G3=3,ROUND(G21*G14,2),0)) | H24: =IF(OR(H3=1,H3=2),ROUND(H21*H7,2)+ROUND(H21*H8,2)+ROUND(H21*H9,2)+ROUND(H21*H10,2)+ROUND(H21*H11,2)+ROUND(H21*H12,2)+ROUND(H21*H13,2),IF(H3=3,ROUND(H21*H14,2),0)) | I24: =IF(OR(I3=1,I3=2),ROUND(I21*I7,2)+ROUND(I21*I8,2)+ROUND(I21*I9,2)+ROUND(I21*I10,2)+ROUND(I21*I11,2)+ROUND(I21*I12,2)+ROUND(I21*I13,2),IF(I3=3,ROUND(I21*I14,2),0)) | J24: =IF(OR(J3=1,J3=2),ROUND(J21*J7,2)+ROUND(J21*J8,2)+ROUND(J21*J9,2)+ROUND(J21*J10,2)+ROUND(J21*J11,2)+ROUND(J21*J12,2)+ROUND(J21*J13,2),IF(J3=3,ROUND(J21*J14,2),0)) | K24: =IF(OR(K3=1,K3=2),ROUND(K21*K7,2)+ROUND(K21*K8,2)+ROUND(K21*K9,2)+ROUND(K21*K10,2)+ROUND(K21*K11,2)+ROUND(K21*K12,2)+ROUND(K21*K13,2),IF(K3=3,ROUND(K21*K14,2),0)) | L24: =IF(OR(L3=1,L3=2),ROUND(L21*L7,2)+ROUND(L21*L8,2)+ROUND(L21*L9,2)+ROUND(L21*L10,2)+ROUND(L21*L11,2)+ROUND(L21*L12,2)+ROUND(L21*L13,2),IF(L3=3,ROUND(L21*L14,2),0)) | ... T24: =IF(OR(T3=1,T3=2),ROUND(T21*T7,2)+ROUND(T21*T8,2)+ROUND(T21*T9,2)+ROUND(T21*T10,2)+ROUND(T21*T11,2)+ROUND(T21*T12,2)+ROUND(T21*T13,2),IF(T3=3,ROUND(T21*T14,2),0)) | V24: =IF(OR(V3=1,V3=2),ROUND(V21*V7,2)+ROUND(V21*V8,2)+ROUND(V21*V9,2)+ROUND(V21*V10,2)+ROUND(V21*V11,2)+ROUND(V21*V12,2)+ROUND(V21*V13,2),IF(V3=3,ROUND(V21*V14,2),0)) | W24: =IF(OR(W3=1,W3=2),ROUND(W21*W7,2)+ROUND(W21*W8,2)+ROUND(W21*W9,2)+ROUND(W21*W10,2)+ROUND(W21*W11,2)+ROUND(W21*W12,2)+ROUND(W21*W13,2),IF(W3=3,ROUND(W21*W14,2),0)) | X24: =IF(OR(X3=1,X3=2),ROUND(X21*X7,2)+ROUND(X21*X8,2)+ROUND(X21*X9,2)+ROUND(X21*X10,2)+ROUND(X21*X11,2)+ROUND(X21*X12,2)+ROUND(X21*X13,2),IF(X3=3,ROUND(X21*X14,2),0)) | Y24: =IF(OR(Y3=1,Y3=2),ROUND(Y21*Y7,2)+ROUND(Y21*Y8,2)+ROUND(Y21*Y9,2)+ROUND(Y21*Y10,2)+ROUND(Y21*Y11,2)+ROUND(Y21*Y12,2)+ROUND(Y21*Y13,2),IF(Y3=3,ROUND(Y21*Y14,2),0)) | Z24: =IF(OR(Z3=1,Z3=2),ROUND(Z21*Z7,2)+ROUND(Z21*Z8,2)+ROUND(Z21*Z9,2)+ROUND(Z21*Z10,2)+ROUND(Z21*Z11,2)+ROUND(Z21*Z12,2)+ROUND(Z21*Z13,2),IF(Z3=3,ROUND(Z21*Z14,2),0)) | AA24: =IF(OR(AA3=1,AA3=2),ROUND(AA21*AA7,2)+ROUND(AA21*AA8,2)+ROUND(AA21*AA9,2)+ROUND(AA21*AA10,2)+ROUND(AA21*AA11,2)+ROUND(AA21*AA12,2)+ROUND(AA21*AA13,2),IF(AA3=3,ROUND(AA21*AA14,2),0)) | AB24: =IF(OR(AB3=1,AB3=2),ROUND(AB21*AB7,2)+ROUND(AB21*AB8,2)+ROUND(AB21*AB9,2)+ROUND(AB21*AB10,2)+ROUND(AB21*AB11,2)+ROUND(AB21*AB12,2)+ROUND(AB21*AB13,2),IF(AB3=3,ROUND(AB21*AB14,2),0)) | AC24: =IF(OR(AC3=1,AC3=2),ROUND(AC21*AC7,2)+ROUND(AC21*AC8,2)+ROUND(AC21*AC9,2)+ROUND(AC21*AC10,2)+ROUND(AC21*AC11,2)+ROUND(AC21*AC12,2)+ROUND(AC21*AC13,2),IF(AC3=3,ROUND(AC21*AC14,2),0)) | ... AK24: =IF(OR(AK3=1,AK3=2),ROUND(AK21*AK7,2)+ROUND(AK21*AK8,2)+ROUND(AK21*AK9,2)+ROUND(AK21*AK10,2)+ROUND(AK21*AK11,2)+ROUND(AK21*AK12,2)+ROUND(AK21*AK13,2),IF(AK3=3,ROUND(AK21*AK14,2),0)) | AM24: =IF(OR(AM3=1,AM3=2),ROUND(AM21*AM7,2)+ROUND(AM21*AM8,2)+ROUND(AM21*AM9,2)+ROUND(AM21*AM10,2)+ROUND(AM21*AM11,2)+ROUND(AM21*AM12,2)+ROUND(AM21*AM13,2),IF(AM3=3,ROUND(AM21*AM14,2),0)) | AN24: =IF(OR(AN3=1,AN3=2),ROUND(AN21*AN7,2)+ROUND(AN21*AN8,2)+ROUND(AN21*AN9,2)+ROUND(AN21*AN10,2)+ROUND(AN21*AN11,2)+ROUND(AN21*AN12,2)+ROUND(AN21*AN13,2),IF(AN3=3,ROUND(AN21*AN14,2),0)) | AO24: =IF(OR(AO3=1,AO3=2),ROUND(AO21*AO7,2)+ROUND(AO21*AO8,2)+ROUND(AO21*AO9,2)+ROUND(AO21*AO10,2)+ROUND(AO21*AO11,2)+ROUND(AO21*AO12,2)+ROUND(AO21*AO13,2),IF(AO3=3,ROUND(AO21*AO14,2),0)) | AP24: =IF(OR(AP3=1,AP3=2),ROUND(AP21*AP7,2)+ROUND(AP21*AP8,2)+ROUND(AP21*AP9,2)+ROUND(AP21*AP10,2)+ROUND(AP21*AP11,2)+ROUND(AP21*AP12,2)+ROUND(AP21*AP13,2),IF(AP3=3,ROUND(AP21*AP14,2),0)) | AQ24: =IF(OR(AQ3=1,AQ3=2),ROUND(AQ21*AQ7,2)+ROUND(AQ21*AQ8,2)+ROUND(AQ21*AQ9,2)+ROUND(AQ21*AQ10,2)+ROUND(AQ21*AQ11,2)+ROUND(AQ21*AQ12,2)+ROUND(AQ21*AQ13,2),IF(AQ3=3,ROUND(AQ21*AQ14,2),0)) | AR24: =IF(OR(AR3=1,AR3=2),ROUND(AR21*AR7,2)+ROUND(AR21*AR8,2)+ROUND(AR21*AR9,2)+ROUND(AR21*AR10,2)+ROUND(AR21*AR11,2)+ROUND(AR21*AR12,2)+ROUND(AR21*AR13,2),IF(AR3=3,ROUND(AR21*AR14,2),0)) | AS24: =IF(OR(AS3=1,AS3=2),ROUND(AS21*AS7,2)+ROUND(AS21*AS8,2)+ROUND(AS21*AS9,2)+ROUND(AS21*AS10,2)+ROUND(AS21*AS11,2)+ROUND(AS21*AS12,2)+ROUND(AS21*AS13,2),IF(AS3=3,ROUND(AS21*AS14,2),0)) | AT24: =IF(OR(AT3=1,AT3=2),ROUND(AT21*AT7,2)+ROUND(AT21*AT8,2)+ROUND(AT21*AT9,2)+ROUND(AT21*AT10,2)+ROUND(AT21*AT11,2)+ROUND(AT21*AT12,2)+ROUND(AT21*AT13,2),IF(AT3=3,ROUND(AT21*AT14,2),0)) | ... BB24: =IF(OR(BB3=1,BB3=2),ROUND(BB21*BB7,2)+ROUND(BB21*BB8,2)+ROUND(BB21*BB9,2)+ROUND(BB21*BB10,2)+ROUND(BB21*BB11,2)+ROUND(BB21*BB12,2)+ROUND(BB21*BB13,2),IF(BB3=3,ROUND(BB21*BB14,2),0)) | BD24: =IF(OR(BD3=1,BD3=2),ROUND(BD21*BD7,2)+ROUND(BD21*BD8,2)+ROUND(BD21*BD9,2)+ROUND(BD21*BD10,2)+ROUND(BD21*BD11,2)+ROUND(BD21*BD12,2)+ROUND(BD21*BD13,2),IF(BD3=3,ROUND(BD21*BD14,2),0)) | BE24: =IF(OR(BE3=1,BE3=2),ROUND(BE21*BE7,2)+ROUND(BE21*BE8,2)+ROUND(BE21*BE9,2)+ROUND(BE21*BE10,2)+ROUND(BE21*BE11,2)+ROUND(BE21*BE12,2)+ROUND(BE21*BE13,2),IF(BE3=3,ROUND(BE21*BE14,2),0)) | BF24: =IF(OR(BF3=1,BF3=2),ROUND(BF21*BF7,2)+ROUND(BF21*BF8,2)+ROUND(BF21*BF9,2)+ROUND(BF21*BF10,2)+ROUND(BF21*BF11,2)+ROUND(BF21*BF12,2)+ROUND(BF21*BF13,2),IF(BF3=3,ROUND(BF21*BF14,2),0)) | BG24: =IF(OR(BG3=1,BG3=2),ROUND(BG21*BG7,2)+ROUND(BG21*BG8,2)+ROUND(BG21*BG9,2)+ROUND(BG21*BG10,2)+ROUND(BG21*BG11,2)+ROUND(BG21*BG12,2)+ROUND(BG21*BG13,2),IF(BG3=3,ROUND(BG21*BG14,2),0)) | BH24: =IF(OR(BH3=1,BH3=2),ROUND(BH21*BH7,2)+ROUND(BH21*BH8,2)+ROUND(BH21*BH9,2)+ROUND(BH21*BH10,2)+ROUND(BH21*BH11,2)+ROUND(BH21*BH12,2)+ROUND(BH21*BH13,2),IF(BH3=3,ROUND(BH21*BH14,2),0)) | BI24: =IF(OR(BI3=1,BI3=2),ROUND(BI21*BI7,2)+ROUND(BI21*BI8,2)+ROUND(BI21*BI9,2)+ROUND(BI21*BI10,2)+ROUND(BI21*BI11,2)+ROUND(BI21*BI12,2)+ROUND(BI21*BI13,2),IF(BI3=3,ROUND(BI21*BI14,2),0)) | BJ24: =IF(OR(BJ3=1,BJ3=2),ROUND(BJ21*BJ7,2)+ROUND(BJ21*BJ8,2)+ROUND(BJ21*BJ9,2)+ROUND(BJ21*BJ10,2)+ROUND(BJ21*BJ11,2)+ROUND(BJ21*BJ12,2)+ROUND(BJ21*BJ13,2),IF(BJ3=3,ROUND(BJ21*BJ14,2),0)) | BK24: =IF(OR(BK3=1,BK3=2),ROUND(BK21*BK7,2)+ROUND(BK21*BK8,2)+ROUND(BK21*BK9,2)+ROUND(BK21*BK10,2)+ROUND(BK21*BK11,2)+ROUND(BK21*BK12,2)+ROUND(BK21*BK13,2),IF(BK3=3,ROUND(BK21*BK14,2),0)) | ... BS24: =IF(OR(BS3=1,BS3=2),ROUND(BS21*BS7,2)+ROUND(BS21*BS8,2)+ROUND(BS21*BS9,2)+ROUND(BS21*BS10,2)+ROUND(BS21*BS11,2)+ROUND(BS21*BS12,2)+ROUND(BS21*BS13,2),IF(BS3=3,ROUND(BS21*BS14,2),0))
B25: est | C25: =ROUND(C20-C22-C23-C24,2) | E25: =ROUND(E20-E22-E23-E24,2) | F25: =ROUND(F20-F22-F23-F24,2) | G25: =ROUND(G20-G22-G23-G24,2) | H25: =ROUND(H20-H22-H23-H24,2) | I25: =ROUND(I20-I22-I23-I24,2) | J25: =ROUND(J20-J22-J23-J24,2) | K25: =ROUND(K20-K22-K23-K24,2) | L25: =ROUND(L20-L22-L23-L24,2) | ... T25: =ROUND(T20-T22-T23-T24,2) | V25: =ROUND(V20-V22-V23-V24,2) | W25: =ROUND(W20-W22-W23-W24,2) | X25: =ROUND(X20-X22-X23-X24,2) | Y25: =ROUND(Y20-Y22-Y23-Y24,2) | Z25: =ROUND(Z20-Z22-Z23-Z24,2) | AA25: =ROUND(AA20-AA22-AA23-AA24,2) | AB25: =ROUND(AB20-AB22-AB23-AB24,2) | AC25: =ROUND(AC20-AC22-AC23-AC24,2) | ... AK25: =ROUND(AK20-AK22-AK23-AK24,2) | AM25: =ROUND(AM20-AM22-AM23-AM24,2) | AN25: =ROUND(AN20-AN22-AN23-AN24,2) | AO25: =ROUND(AO20-AO22-AO23-AO24,2) | AP25: =ROUND(AP20-AP22-AP23-AP24,2) | AQ25: =ROUND(AQ20-AQ22-AQ23-AQ24,2) | AR25: =ROUND(AR20-AR22-AR23-AR24,2) | AS25: =ROUND(AS20-AS22-AS23-AS24,2) | AT25: =ROUND(AT20-AT22-AT23-AT24,2) | ... BB25: =ROUND(BB20-BB22-BB23-BB24,2) | BD25: =ROUND(BD20-BD22-BD23-BD24,2) | BE25: =ROUND(BE20-BE22-BE23-BE24,2) | BF25: =ROUND(BF20-BF22-BF23-BF24,2) | BG25: =ROUND(BG20-BG22-BG23-BG24,2) | BH25: =ROUND(BH20-BH22-BH23-BH24,2) | BI25: =ROUND(BI20-BI22-BI23-BI24,2) | BJ25: =ROUND(BJ20-BJ22-BJ23-BJ24,2) | BK25: =ROUND(BK20-BK22-BK23-BK24,2) | ... BS25: =ROUND(BS20-BS22-BS23-BS24,2)
B26: need | C26: =ROUND('Workings'!$C$60-'Workings'!$C$46+C25,2) | E26: =ROUND('Workings'!$C$60-'Workings'!$C$46+E25,2) | F26: =ROUND('Workings'!$C$60-'Workings'!$C$46+F25,2) | G26: =ROUND('Workings'!$C$60-'Workings'!$C$46+G25,2) | H26: =ROUND('Workings'!$C$60-'Workings'!$C$46+H25,2) | I26: =ROUND('Workings'!$C$60-'Workings'!$C$46+I25,2) | J26: =ROUND('Workings'!$C$60-'Workings'!$C$46+J25,2) | K26: =ROUND('Workings'!$C$60-'Workings'!$C$46+K25,2) | L26: =ROUND('Workings'!$C$60-'Workings'!$C$46+L25,2) | ... T26: =ROUND('Workings'!$C$60-'Workings'!$C$46+T25,2) | V26: =ROUND('Workings'!$C$60-'Workings'!$C$46+V25,2) | W26: =ROUND('Workings'!$C$60-'Workings'!$C$46+W25,2) | X26: =ROUND('Workings'!$C$60-'Workings'!$C$46+X25,2) | Y26: =ROUND('Workings'!$C$60-'Workings'!$C$46+Y25,2) | Z26: =ROUND('Workings'!$C$60-'Workings'!$C$46+Z25,2) | AA26: =ROUND('Workings'!$C$60-'Workings'!$C$46+AA25,2) | AB26: =ROUND('Workings'!$C$60-'Workings'!$C$46+AB25,2) | AC26: =ROUND('Workings'!$C$60-'Workings'!$C$46+AC25,2) | ... AK26: =ROUND('Workings'!$C$60-'Workings'!$C$46+AK25,2) | AM26: =ROUND('Workings'!$C$60-'Workings'!$C$46+AM25,2) | AN26: =ROUND('Workings'!$C$60-'Workings'!$C$46+AN25,2) | AO26: =ROUND('Workings'!$C$60-'Workings'!$C$46+AO25,2) | AP26: =ROUND('Workings'!$C$60-'Workings'!$C$46+AP25,2) | AQ26: =ROUND('Workings'!$C$60-'Workings'!$C$46+AQ25,2) | AR26: =ROUND('Workings'!$C$60-'Workings'!$C$46+AR25,2) | AS26: =ROUND('Workings'!$C$60-'Workings'!$C$46+AS25,2) | AT26: =ROUND('Workings'!$C$60-'Workings'!$C$46+AT25,2) | ... BB26: =ROUND('Workings'!$C$60-'Workings'!$C$46+BB25,2) | BD26: =ROUND('Workings'!$C$60-'Workings'!$C$46+BD25,2) | BE26: =ROUND('Workings'!$C$60-'Workings'!$C$46+BE25,2) | BF26: =ROUND('Workings'!$C$60-'Workings'!$C$46+BF25,2) | BG26: =ROUND('Workings'!$C$60-'Workings'!$C$46+BG25,2) | BH26: =ROUND('Workings'!$C$60-'Workings'!$C$46+BH25,2) | BI26: =ROUND('Workings'!$C$60-'Workings'!$C$46+BI25,2) | BJ26: =ROUND('Workings'!$C$60-'Workings'!$C$46+BJ25,2) | BK26: =ROUND('Workings'!$C$60-'Workings'!$C$46+BK25,2) | ... BS26: =ROUND('Workings'!$C$60-'Workings'!$C$46+BS25,2)
B27: res | C27: =ROUND(MAX(0,'Workings'!$C$63-C26),2) | E27: =ROUND(MAX(0,'Workings'!$C$63-E26),2) | F27: =ROUND(MAX(0,'Workings'!$C$63-F26),2) | G27: =ROUND(MAX(0,'Workings'!$C$63-G26),2) | H27: =ROUND(MAX(0,'Workings'!$C$63-H26),2) | I27: =ROUND(MAX(0,'Workings'!$C$63-I26),2) | J27: =ROUND(MAX(0,'Workings'!$C$63-J26),2) | K27: =ROUND(MAX(0,'Workings'!$C$63-K26),2) | L27: =ROUND(MAX(0,'Workings'!$C$63-L26),2) | ... T27: =ROUND(MAX(0,'Workings'!$C$63-T26),2) | V27: =ROUND(MAX(0,'Workings'!$C$63-V26),2) | W27: =ROUND(MAX(0,'Workings'!$C$63-W26),2) | X27: =ROUND(MAX(0,'Workings'!$C$63-X26),2) | Y27: =ROUND(MAX(0,'Workings'!$C$63-Y26),2) | Z27: =ROUND(MAX(0,'Workings'!$C$63-Z26),2) | AA27: =ROUND(MAX(0,'Workings'!$C$63-AA26),2) | AB27: =ROUND(MAX(0,'Workings'!$C$63-AB26),2) | AC27: =ROUND(MAX(0,'Workings'!$C$63-AC26),2) | ... AK27: =ROUND(MAX(0,'Workings'!$C$63-AK26),2) | AM27: =ROUND(MAX(0,'Workings'!$C$63-AM26),2) | AN27: =ROUND(MAX(0,'Workings'!$C$63-AN26),2) | AO27: =ROUND(MAX(0,'Workings'!$C$63-AO26),2) | AP27: =ROUND(MAX(0,'Workings'!$C$63-AP26),2) | AQ27: =ROUND(MAX(0,'Workings'!$C$63-AQ26),2) | AR27: =ROUND(MAX(0,'Workings'!$C$63-AR26),2) | AS27: =ROUND(MAX(0,'Workings'!$C$63-AS26),2) | AT27: =ROUND(MAX(0,'Workings'!$C$63-AT26),2) | ... BB27: =ROUND(MAX(0,'Workings'!$C$63-BB26),2) | BD27: =ROUND(MAX(0,'Workings'!$C$63-BD26),2) | BE27: =ROUND(MAX(0,'Workings'!$C$63-BE26),2) | BF27: =ROUND(MAX(0,'Workings'!$C$63-BF26),2) | BG27: =ROUND(MAX(0,'Workings'!$C$63-BG26),2) | BH27: =ROUND(MAX(0,'Workings'!$C$63-BH26),2) | BI27: =ROUND(MAX(0,'Workings'!$C$63-BI26),2) | BJ27: =ROUND(MAX(0,'Workings'!$C$63-BJ26),2) | BK27: =ROUND(MAX(0,'Workings'!$C$63-BK26),2) | ... BS27: =ROUND(MAX(0,'Workings'!$C$63-BS26),2)
B28: pool | C28: =ROUND(C27+SUM('Inputs'!$Y$22:$Y$39),2) | E28: =ROUND(E27+SUM('Inputs'!$Y$22:$Y$39),2) | F28: =ROUND(F27+SUM('Inputs'!$Y$22:$Y$39),2) | G28: =ROUND(G27+SUM('Inputs'!$Y$22:$Y$39),2) | H28: =ROUND(H27+SUM('Inputs'!$Y$22:$Y$39),2) | I28: =ROUND(I27+SUM('Inputs'!$Y$22:$Y$39),2) | J28: =ROUND(J27+SUM('Inputs'!$Y$22:$Y$39),2) | K28: =ROUND(K27+SUM('Inputs'!$Y$22:$Y$39),2) | L28: =ROUND(L27+SUM('Inputs'!$Y$22:$Y$39),2) | ... T28: =ROUND(T27+SUM('Inputs'!$Y$22:$Y$39),2) | V28: =ROUND(V27+SUM('Inputs'!$Y$22:$Y$39),2) | W28: =ROUND(W27+SUM('Inputs'!$Y$22:$Y$39),2) | X28: =ROUND(X27+SUM('Inputs'!$Y$22:$Y$39),2) | Y28: =ROUND(Y27+SUM('Inputs'!$Y$22:$Y$39),2) | Z28: =ROUND(Z27+SUM('Inputs'!$Y$22:$Y$39),2) | AA28: =ROUND(AA27+SUM('Inputs'!$Y$22:$Y$39),2) | AB28: =ROUND(AB27+SUM('Inputs'!$Y$22:$Y$39),2) | AC28: =ROUND(AC27+SUM('Inputs'!$Y$22:$Y$39),2) | ... AK28: =ROUND(AK27+SUM('Inputs'!$Y$22:$Y$39),2) | AM28: =ROUND(AM27+SUM('Inputs'!$Y$22:$Y$39),2) | AN28: =ROUND(AN27+SUM('Inputs'!$Y$22:$Y$39),2) | AO28: =ROUND(AO27+SUM('Inputs'!$Y$22:$Y$39),2) | AP28: =ROUND(AP27+SUM('Inputs'!$Y$22:$Y$39),2) | AQ28: =ROUND(AQ27+SUM('Inputs'!$Y$22:$Y$39),2) | AR28: =ROUND(AR27+SUM('Inputs'!$Y$22:$Y$39),2) | AS28: =ROUND(AS27+SUM('Inputs'!$Y$22:$Y$39),2) | AT28: =ROUND(AT27+SUM('Inputs'!$Y$22:$Y$39),2) | ... BB28: =ROUND(BB27+SUM('Inputs'!$Y$22:$Y$39),2) | BD28: =ROUND(BD27+SUM('Inputs'!$Y$22:$Y$39),2) | BE28: =ROUND(BE27+SUM('Inputs'!$Y$22:$Y$39),2) | BF28: =ROUND(BF27+SUM('Inputs'!$Y$22:$Y$39),2) | BG28: =ROUND(BG27+SUM('Inputs'!$Y$22:$Y$39),2) | BH28: =ROUND(BH27+SUM('Inputs'!$Y$22:$Y$39),2) | BI28: =ROUND(BI27+SUM('Inputs'!$Y$22:$Y$39),2) | BJ28: =ROUND(BJ27+SUM('Inputs'!$Y$22:$Y$39),2) | BK28: =ROUND(BK27+SUM('Inputs'!$Y$22:$Y$39),2) | ... BS28: =ROUND(BS27+SUM('Inputs'!$Y$22:$Y$39),2)
B29: n | C29: =SUM('Inputs'!$L$89:$L$94) | E29: =SUM('Inputs'!$L$89:$L$94) | F29: =SUM('Inputs'!$L$89:$L$94) | G29: =SUM('Inputs'!$L$89:$L$94) | H29: =SUM('Inputs'!$L$89:$L$94) | I29: =SUM('Inputs'!$L$89:$L$94) | J29: =SUM('Inputs'!$L$89:$L$94) | K29: =SUM('Inputs'!$L$89:$L$94) | L29: =SUM('Inputs'!$L$89:$L$94) | ... T29: =SUM('Inputs'!$L$89:$L$94) | V29: =SUM('Inputs'!$L$89:$L$94) | W29: =SUM('Inputs'!$L$89:$L$94) | X29: =SUM('Inputs'!$L$89:$L$94) | Y29: =SUM('Inputs'!$L$89:$L$94) | Z29: =SUM('Inputs'!$L$89:$L$94) | AA29: =SUM('Inputs'!$L$89:$L$94) | AB29: =SUM('Inputs'!$L$89:$L$94) | AC29: =SUM('Inputs'!$L$89:$L$94) | ... AK29: =SUM('Inputs'!$L$89:$L$94) | AM29: =SUM('Inputs'!$L$89:$L$94) | AN29: =SUM('Inputs'!$L$89:$L$94) | AO29: =SUM('Inputs'!$L$89:$L$94) | AP29: =SUM('Inputs'!$L$89:$L$94) | AQ29: =SUM('Inputs'!$L$89:$L$94) | AR29: =SUM('Inputs'!$L$89:$L$94) | AS29: =SUM('Inputs'!$L$89:$L$94) | AT29: =SUM('Inputs'!$L$89:$L$94) | ... BB29: =SUM('Inputs'!$L$89:$L$94) | BD29: =SUM('Inputs'!$L$89:$L$94) | BE29: =SUM('Inputs'!$L$89:$L$94) | BF29: =SUM('Inputs'!$L$89:$L$94) | BG29: =SUM('Inputs'!$L$89:$L$94) | BH29: =SUM('Inputs'!$L$89:$L$94) | BI29: =SUM('Inputs'!$L$89:$L$94) | BJ29: =SUM('Inputs'!$L$89:$L$94) | BK29: =SUM('Inputs'!$L$89:$L$94) | ... BS29: =SUM('Inputs'!$L$89:$L$94)
B30: nt | C30: =SUM('Inputs'!$Q$89:$Q$94) | E30: =SUM('Inputs'!$Q$89:$Q$94) | F30: =SUM('Inputs'!$Q$89:$Q$94) | G30: =SUM('Inputs'!$Q$89:$Q$94) | H30: =SUM('Inputs'!$Q$89:$Q$94) | I30: =SUM('Inputs'!$Q$89:$Q$94) | J30: =SUM('Inputs'!$Q$89:$Q$94) | K30: =SUM('Inputs'!$Q$89:$Q$94) | L30: =SUM('Inputs'!$Q$89:$Q$94) | ... T30: =SUM('Inputs'!$Q$89:$Q$94) | V30: =SUM('Inputs'!$Q$89:$Q$94) | W30: =SUM('Inputs'!$Q$89:$Q$94) | X30: =SUM('Inputs'!$Q$89:$Q$94) | Y30: =SUM('Inputs'!$Q$89:$Q$94) | Z30: =SUM('Inputs'!$Q$89:$Q$94) | AA30: =SUM('Inputs'!$Q$89:$Q$94) | AB30: =SUM('Inputs'!$Q$89:$Q$94) | AC30: =SUM('Inputs'!$Q$89:$Q$94) | ... AK30: =SUM('Inputs'!$Q$89:$Q$94) | AM30: =SUM('Inputs'!$Q$89:$Q$94) | AN30: =SUM('Inputs'!$Q$89:$Q$94) | AO30: =SUM('Inputs'!$Q$89:$Q$94) | AP30: =SUM('Inputs'!$Q$89:$Q$94) | AQ30: =SUM('Inputs'!$Q$89:$Q$94) | AR30: =SUM('Inputs'!$Q$89:$Q$94) | AS30: =SUM('Inputs'!$Q$89:$Q$94) | AT30: =SUM('Inputs'!$Q$89:$Q$94) | ... BB30: =SUM('Inputs'!$Q$89:$Q$94) | BD30: =SUM('Inputs'!$Q$89:$Q$94) | BE30: =SUM('Inputs'!$Q$89:$Q$94) | BF30: =SUM('Inputs'!$Q$89:$Q$94) | BG30: =SUM('Inputs'!$Q$89:$Q$94) | BH30: =SUM('Inputs'!$Q$89:$Q$94) | BI30: =SUM('Inputs'!$Q$89:$Q$94) | BJ30: =SUM('Inputs'!$Q$89:$Q$94) | BK30: =SUM('Inputs'!$Q$89:$Q$94) | ... BS30: =SUM('Inputs'!$Q$89:$Q$94)
B31: resTo | C31: =IF('Inputs'!$C$14="Spouse","S",IF('Inputs'!$C$95="Not to the dependants","N","K")) | E31: =IF('Inputs'!$C$14="Spouse","S",IF('Inputs'!$C$95="Not to the dependants","N","K")) | F31: =IF('Inputs'!$C$14="Spouse","S",IF('Inputs'!$C$95="Not to the dependants","N","K")) | G31: =IF('Inputs'!$C$14="Spouse","S",IF('Inputs'!$C$95="Not to the dependants","N","K")) | H31: =IF('Inputs'!$C$14="Spouse","S",IF('Inputs'!$C$95="Not to the dependants","N","K")) | I31: =IF('Inputs'!$C$14="Spouse","S",IF('Inputs'!$C$95="Not to the dependants","N","K")) | J31: =IF('Inputs'!$C$14="Spouse","S",IF('Inputs'!$C$95="Not to the dependants","N","K")) | K31: =IF('Inputs'!$C$14="Spouse","S",IF('Inputs'!$C$95="Not to the dependants","N","K")) | L31: =IF('Inputs'!$C$14="Spouse","S",IF('Inputs'!$C$95="Not to the dependants","N","K")) | ... T31: =IF('Inputs'!$C$14="Spouse","S",IF('Inputs'!$C$95="Not to the dependants","N","K")) | V31: =IF('Inputs'!$C$14="Spouse","S",IF('Inputs'!$C$95="Not to the dependants","N","K")) | W31: =IF('Inputs'!$C$14="Spouse","S",IF('Inputs'!$C$95="Not to the dependants","N","K")) | X31: =IF('Inputs'!$C$14="Spouse","S",IF('Inputs'!$C$95="Not to the dependants","N","K")) | Y31: =IF('Inputs'!$C$14="Spouse","S",IF('Inputs'!$C$95="Not to the dependants","N","K")) | Z31: =IF('Inputs'!$C$14="Spouse","S",IF('Inputs'!$C$95="Not to the dependants","N","K")) | AA31: =IF('Inputs'!$C$14="Spouse","S",IF('Inputs'!$C$95="Not to the dependants","N","K")) | AB31: =IF('Inputs'!$C$14="Spouse","S",IF('Inputs'!$C$95="Not to the dependants","N","K")) | AC31: =IF('Inputs'!$C$14="Spouse","S",IF('Inputs'!$C$95="Not to the dependants","N","K")) | ... AK31: =IF('Inputs'!$C$14="Spouse","S",IF('Inputs'!$C$95="Not to the dependants","N","K")) | AM31: =IF('Inputs'!$C$14="Spouse","S",IF('Inputs'!$C$95="Not to the dependants","N","K")) | AN31: =IF('Inputs'!$C$14="Spouse","S",IF('Inputs'!$C$95="Not to the dependants","N","K")) | AO31: =IF('Inputs'!$C$14="Spouse","S",IF('Inputs'!$C$95="Not to the dependants","N","K")) | AP31: =IF('Inputs'!$C$14="Spouse","S",IF('Inputs'!$C$95="Not to the dependants","N","K")) | AQ31: =IF('Inputs'!$C$14="Spouse","S",IF('Inputs'!$C$95="Not to the dependants","N","K")) | AR31: =IF('Inputs'!$C$14="Spouse","S",IF('Inputs'!$C$95="Not to the dependants","N","K")) | AS31: =IF('Inputs'!$C$14="Spouse","S",IF('Inputs'!$C$95="Not to the dependants","N","K")) | AT31: =IF('Inputs'!$C$14="Spouse","S",IF('Inputs'!$C$95="Not to the dependants","N","K")) | ... BB31: =IF('Inputs'!$C$14="Spouse","S",IF('Inputs'!$C$95="Not to the dependants","N","K")) | BD31: =IF('Inputs'!$C$14="Spouse","S",IF('Inputs'!$C$95="Not to the dependants","N","K")) | BE31: =IF('Inputs'!$C$14="Spouse","S",IF('Inputs'!$C$95="Not to the dependants","N","K")) | BF31: =IF('Inputs'!$C$14="Spouse","S",IF('Inputs'!$C$95="Not to the dependants","N","K")) | BG31: =IF('Inputs'!$C$14="Spouse","S",IF('Inputs'!$C$95="Not to the dependants","N","K")) | BH31: =IF('Inputs'!$C$14="Spouse","S",IF('Inputs'!$C$95="Not to the dependants","N","K")) | BI31: =IF('Inputs'!$C$14="Spouse","S",IF('Inputs'!$C$95="Not to the dependants","N","K")) | BJ31: =IF('Inputs'!$C$14="Spouse","S",IF('Inputs'!$C$95="Not to the dependants","N","K")) | BK31: =IF('Inputs'!$C$14="Spouse","S",IF('Inputs'!$C$95="Not to the dependants","N","K")) | ... BS31: =IF('Inputs'!$C$14="Spouse","S",IF('Inputs'!$C$95="Not to the dependants","N","K"))
B32: resE | C32: =IF(C29=0,0,ROUNDDOWN(C28/C29,2)) | E32: =IF(E29=0,0,ROUNDDOWN(E28/E29,2)) | F32: =IF(F29=0,0,ROUNDDOWN(F28/F29,2)) | G32: =IF(G29=0,0,ROUNDDOWN(G28/G29,2)) | H32: =IF(H29=0,0,ROUNDDOWN(H28/H29,2)) | I32: =IF(I29=0,0,ROUNDDOWN(I28/I29,2)) | J32: =IF(J29=0,0,ROUNDDOWN(J28/J29,2)) | K32: =IF(K29=0,0,ROUNDDOWN(K28/K29,2)) | L32: =IF(L29=0,0,ROUNDDOWN(L28/L29,2)) | ... T32: =IF(T29=0,0,ROUNDDOWN(T28/T29,2)) | V32: =IF(V29=0,0,ROUNDDOWN(V28/V29,2)) | W32: =IF(W29=0,0,ROUNDDOWN(W28/W29,2)) | X32: =IF(X29=0,0,ROUNDDOWN(X28/X29,2)) | Y32: =IF(Y29=0,0,ROUNDDOWN(Y28/Y29,2)) | Z32: =IF(Z29=0,0,ROUNDDOWN(Z28/Z29,2)) | AA32: =IF(AA29=0,0,ROUNDDOWN(AA28/AA29,2)) | AB32: =IF(AB29=0,0,ROUNDDOWN(AB28/AB29,2)) | AC32: =IF(AC29=0,0,ROUNDDOWN(AC28/AC29,2)) | ... AK32: =IF(AK29=0,0,ROUNDDOWN(AK28/AK29,2)) | AM32: =IF(AM29=0,0,ROUNDDOWN(AM28/AM29,2)) | AN32: =IF(AN29=0,0,ROUNDDOWN(AN28/AN29,2)) | AO32: =IF(AO29=0,0,ROUNDDOWN(AO28/AO29,2)) | AP32: =IF(AP29=0,0,ROUNDDOWN(AP28/AP29,2)) | AQ32: =IF(AQ29=0,0,ROUNDDOWN(AQ28/AQ29,2)) | AR32: =IF(AR29=0,0,ROUNDDOWN(AR28/AR29,2)) | AS32: =IF(AS29=0,0,ROUNDDOWN(AS28/AS29,2)) | AT32: =IF(AT29=0,0,ROUNDDOWN(AT28/AT29,2)) | ... BB32: =IF(BB29=0,0,ROUNDDOWN(BB28/BB29,2)) | BD32: =IF(BD29=0,0,ROUNDDOWN(BD28/BD29,2)) | BE32: =IF(BE29=0,0,ROUNDDOWN(BE28/BE29,2)) | BF32: =IF(BF29=0,0,ROUNDDOWN(BF28/BF29,2)) | BG32: =IF(BG29=0,0,ROUNDDOWN(BG28/BG29,2)) | BH32: =IF(BH29=0,0,ROUNDDOWN(BH28/BH29,2)) | BI32: =IF(BI29=0,0,ROUNDDOWN(BI28/BI29,2)) | BJ32: =IF(BJ29=0,0,ROUNDDOWN(BJ28/BJ29,2)) | BK32: =IF(BK29=0,0,ROUNDDOWN(BK28/BK29,2)) | ... BS32: =IF(BS29=0,0,ROUNDDOWN(BS28/BS29,2))
B33: resL | C33: =ROUND(C28-C32*(C29-1),2) | E33: =ROUND(E28-E32*(E29-1),2) | F33: =ROUND(F28-F32*(F29-1),2) | G33: =ROUND(G28-G32*(G29-1),2) | H33: =ROUND(H28-H32*(H29-1),2) | I33: =ROUND(I28-I32*(I29-1),2) | J33: =ROUND(J28-J32*(J29-1),2) | K33: =ROUND(K28-K32*(K29-1),2) | L33: =ROUND(L28-L32*(L29-1),2) | ... T33: =ROUND(T28-T32*(T29-1),2) | V33: =ROUND(V28-V32*(V29-1),2) | W33: =ROUND(W28-W32*(W29-1),2) | X33: =ROUND(X28-X32*(X29-1),2) | Y33: =ROUND(Y28-Y32*(Y29-1),2) | Z33: =ROUND(Z28-Z32*(Z29-1),2) | AA33: =ROUND(AA28-AA32*(AA29-1),2) | AB33: =ROUND(AB28-AB32*(AB29-1),2) | AC33: =ROUND(AC28-AC32*(AC29-1),2) | ... AK33: =ROUND(AK28-AK32*(AK29-1),2) | AM33: =ROUND(AM28-AM32*(AM29-1),2) | AN33: =ROUND(AN28-AN32*(AN29-1),2) | AO33: =ROUND(AO28-AO32*(AO29-1),2) | AP33: =ROUND(AP28-AP32*(AP29-1),2) | AQ33: =ROUND(AQ28-AQ32*(AQ29-1),2) | AR33: =ROUND(AR28-AR32*(AR29-1),2) | AS33: =ROUND(AS28-AS32*(AS29-1),2) | AT33: =ROUND(AT28-AT32*(AT29-1),2) | ... BB33: =ROUND(BB28-BB32*(BB29-1),2) | BD33: =ROUND(BD28-BD32*(BD29-1),2) | BE33: =ROUND(BE28-BE32*(BE29-1),2) | BF33: =ROUND(BF28-BF32*(BF29-1),2) | BG33: =ROUND(BG28-BG32*(BG29-1),2) | BH33: =ROUND(BH28-BH32*(BH29-1),2) | BI33: =ROUND(BI28-BI32*(BI29-1),2) | BJ33: =ROUND(BJ28-BJ32*(BJ29-1),2) | BK33: =ROUND(BK28-BK32*(BK29-1),2) | ... BS33: =ROUND(BS28-BS32*(BS29-1),2)
B34: tpE | C34: =IF(C30=0,0,SUMPRODUCT('Inputs'!$Q$59:$Q$70,ROUNDDOWN((('Inputs'!$D$59:$D$70-('Inputs'!$P$59:$P$70=C5)*C14)-'Inputs'!$R$59:$R$70*ROUND(C21*('Inputs'!$D$59:$D$70-('Inputs'!$P$59:$P$70=C5)*C14),2))/C30,2))) | E34: =IF(E30=0,0,SUMPRODUCT('Inputs'!$Q$59:$Q$70,ROUNDDOWN((('Inputs'!$D$59:$D$70-('Inputs'!$P$59:$P$70=E5)*E14)-'Inputs'!$R$59:$R$70*ROUND(E21*('Inputs'!$D$59:$D$70-('Inputs'!$P$59:$P$70=E5)*E14),2))/E30,2))) | F34: =IF(F30=0,0,SUMPRODUCT('Inputs'!$Q$59:$Q$70,ROUNDDOWN((('Inputs'!$D$59:$D$70-('Inputs'!$P$59:$P$70=F5)*F14)-'Inputs'!$R$59:$R$70*ROUND(F21*('Inputs'!$D$59:$D$70-('Inputs'!$P$59:$P$70=F5)*F14),2))/F30,2))) | G34: =IF(G30=0,0,SUMPRODUCT('Inputs'!$Q$59:$Q$70,ROUNDDOWN((('Inputs'!$D$59:$D$70-('Inputs'!$P$59:$P$70=G5)*G14)-'Inputs'!$R$59:$R$70*ROUND(G21*('Inputs'!$D$59:$D$70-('Inputs'!$P$59:$P$70=G5)*G14),2))/G30,2))) | H34: =IF(H30=0,0,SUMPRODUCT('Inputs'!$Q$59:$Q$70,ROUNDDOWN((('Inputs'!$D$59:$D$70-('Inputs'!$P$59:$P$70=H5)*H14)-'Inputs'!$R$59:$R$70*ROUND(H21*('Inputs'!$D$59:$D$70-('Inputs'!$P$59:$P$70=H5)*H14),2))/H30,2))) | I34: =IF(I30=0,0,SUMPRODUCT('Inputs'!$Q$59:$Q$70,ROUNDDOWN((('Inputs'!$D$59:$D$70-('Inputs'!$P$59:$P$70=I5)*I14)-'Inputs'!$R$59:$R$70*ROUND(I21*('Inputs'!$D$59:$D$70-('Inputs'!$P$59:$P$70=I5)*I14),2))/I30,2))) | J34: =IF(J30=0,0,SUMPRODUCT('Inputs'!$Q$59:$Q$70,ROUNDDOWN((('Inputs'!$D$59:$D$70-('Inputs'!$P$59:$P$70=J5)*J14)-'Inputs'!$R$59:$R$70*ROUND(J21*('Inputs'!$D$59:$D$70-('Inputs'!$P$59:$P$70=J5)*J14),2))/J30,2))) | K34: =IF(K30=0,0,SUMPRODUCT('Inputs'!$Q$59:$Q$70,ROUNDDOWN((('Inputs'!$D$59:$D$70-('Inputs'!$P$59:$P$70=K5)*K14)-'Inputs'!$R$59:$R$70*ROUND(K21*('Inputs'!$D$59:$D$70-('Inputs'!$P$59:$P$70=K5)*K14),2))/K30,2))) | L34: =IF(L30=0,0,SUMPRODUCT('Inputs'!$Q$59:$Q$70,ROUNDDOWN((('Inputs'!$D$59:$D$70-('Inputs'!$P$59:$P$70=L5)*L14)-'Inputs'!$R$59:$R$70*ROUND(L21*('Inputs'!$D$59:$D$70-('Inputs'!$P$59:$P$70=L5)*L14),2))/L30,2))) | ... T34: =IF(T30=0,0,SUMPRODUCT('Inputs'!$Q$59:$Q$70,ROUNDDOWN((('Inputs'!$D$59:$D$70-('Inputs'!$P$59:$P$70=T5)*T14)-'Inputs'!$R$59:$R$70*ROUND(T21*('Inputs'!$D$59:$D$70-('Inputs'!$P$59:$P$70=T5)*T14),2))/T30,2))) | V34: =IF(V30=0,0,SUMPRODUCT('Inputs'!$Q$59:$Q$70,ROUNDDOWN((('Inputs'!$D$59:$D$70-('Inputs'!$P$59:$P$70=V5)*V14)-'Inputs'!$R$59:$R$70*ROUND(V21*('Inputs'!$D$59:$D$70-('Inputs'!$P$59:$P$70=V5)*V14),2))/V30,2))) | W34: =IF(W30=0,0,SUMPRODUCT('Inputs'!$Q$59:$Q$70,ROUNDDOWN((('Inputs'!$D$59:$D$70-('Inputs'!$P$59:$P$70=W5)*W14)-'Inputs'!$R$59:$R$70*ROUND(W21*('Inputs'!$D$59:$D$70-('Inputs'!$P$59:$P$70=W5)*W14),2))/W30,2))) | X34: =IF(X30=0,0,SUMPRODUCT('Inputs'!$Q$59:$Q$70,ROUNDDOWN((('Inputs'!$D$59:$D$70-('Inputs'!$P$59:$P$70=X5)*X14)-'Inputs'!$R$59:$R$70*ROUND(X21*('Inputs'!$D$59:$D$70-('Inputs'!$P$59:$P$70=X5)*X14),2))/X30,2))) | Y34: =IF(Y30=0,0,SUMPRODUCT('Inputs'!$Q$59:$Q$70,ROUNDDOWN((('Inputs'!$D$59:$D$70-('Inputs'!$P$59:$P$70=Y5)*Y14)-'Inputs'!$R$59:$R$70*ROUND(Y21*('Inputs'!$D$59:$D$70-('Inputs'!$P$59:$P$70=Y5)*Y14),2))/Y30,2))) | Z34: =IF(Z30=0,0,SUMPRODUCT('Inputs'!$Q$59:$Q$70,ROUNDDOWN((('Inputs'!$D$59:$D$70-('Inputs'!$P$59:$P$70=Z5)*Z14)-'Inputs'!$R$59:$R$70*ROUND(Z21*('Inputs'!$D$59:$D$70-('Inputs'!$P$59:$P$70=Z5)*Z14),2))/Z30,2))) | AA34: =IF(AA30=0,0,SUMPRODUCT('Inputs'!$Q$59:$Q$70,ROUNDDOWN((('Inputs'!$D$59:$D$70-('Inputs'!$P$59:$P$70=AA5)*AA14)-'Inputs'!$R$59:$R$70*ROUND(AA21*('Inputs'!$D$59:$D$70-('Inputs'!$P$59:$P$70=AA5)*AA14),2))/AA30,2))) | AB34: =IF(AB30=0,0,SUMPRODUCT('Inputs'!$Q$59:$Q$70,ROUNDDOWN((('Inputs'!$D$59:$D$70-('Inputs'!$P$59:$P$70=AB5)*AB14)-'Inputs'!$R$59:$R$70*ROUND(AB21*('Inputs'!$D$59:$D$70-('Inputs'!$P$59:$P$70=AB5)*AB14),2))/AB30,2))) | AC34: =IF(AC30=0,0,SUMPRODUCT('Inputs'!$Q$59:$Q$70,ROUNDDOWN((('Inputs'!$D$59:$D$70-('Inputs'!$P$59:$P$70=AC5)*AC14)-'Inputs'!$R$59:$R$70*ROUND(AC21*('Inputs'!$D$59:$D$70-('Inputs'!$P$59:$P$70=AC5)*AC14),2))/AC30,2))) | ... AK34: =IF(AK30=0,0,SUMPRODUCT('Inputs'!$Q$59:$Q$70,ROUNDDOWN((('Inputs'!$D$59:$D$70-('Inputs'!$P$59:$P$70=AK5)*AK14)-'Inputs'!$R$59:$R$70*ROUND(AK21*('Inputs'!$D$59:$D$70-('Inputs'!$P$59:$P$70=AK5)*AK14),2))/AK30,2))) | AM34: =IF(AM30=0,0,SUMPRODUCT('Inputs'!$Q$59:$Q$70,ROUNDDOWN((('Inputs'!$D$59:$D$70-('Inputs'!$P$59:$P$70=AM5)*AM14)-'Inputs'!$R$59:$R$70*ROUND(AM21*('Inputs'!$D$59:$D$70-('Inputs'!$P$59:$P$70=AM5)*AM14),2))/AM30,2))) | AN34: =IF(AN30=0,0,SUMPRODUCT('Inputs'!$Q$59:$Q$70,ROUNDDOWN((('Inputs'!$D$59:$D$70-('Inputs'!$P$59:$P$70=AN5)*AN14)-'Inputs'!$R$59:$R$70*ROUND(AN21*('Inputs'!$D$59:$D$70-('Inputs'!$P$59:$P$70=AN5)*AN14),2))/AN30,2))) | AO34: =IF(AO30=0,0,SUMPRODUCT('Inputs'!$Q$59:$Q$70,ROUNDDOWN((('Inputs'!$D$59:$D$70-('Inputs'!$P$59:$P$70=AO5)*AO14)-'Inputs'!$R$59:$R$70*ROUND(AO21*('Inputs'!$D$59:$D$70-('Inputs'!$P$59:$P$70=AO5)*AO14),2))/AO30,2))) | AP34: =IF(AP30=0,0,SUMPRODUCT('Inputs'!$Q$59:$Q$70,ROUNDDOWN((('Inputs'!$D$59:$D$70-('Inputs'!$P$59:$P$70=AP5)*AP14)-'Inputs'!$R$59:$R$70*ROUND(AP21*('Inputs'!$D$59:$D$70-('Inputs'!$P$59:$P$70=AP5)*AP14),2))/AP30,2))) | AQ34: =IF(AQ30=0,0,SUMPRODUCT('Inputs'!$Q$59:$Q$70,ROUNDDOWN((('Inputs'!$D$59:$D$70-('Inputs'!$P$59:$P$70=AQ5)*AQ14)-'Inputs'!$R$59:$R$70*ROUND(AQ21*('Inputs'!$D$59:$D$70-('Inputs'!$P$59:$P$70=AQ5)*AQ14),2))/AQ30,2))) | AR34: =IF(AR30=0,0,SUMPRODUCT('Inputs'!$Q$59:$Q$70,ROUNDDOWN((('Inputs'!$D$59:$D$70-('Inputs'!$P$59:$P$70=AR5)*AR14)-'Inputs'!$R$59:$R$70*ROUND(AR21*('Inputs'!$D$59:$D$70-('Inputs'!$P$59:$P$70=AR5)*AR14),2))/AR30,2))) | AS34: =IF(AS30=0,0,SUMPRODUCT('Inputs'!$Q$59:$Q$70,ROUNDDOWN((('Inputs'!$D$59:$D$70-('Inputs'!$P$59:$P$70=AS5)*AS14)-'Inputs'!$R$59:$R$70*ROUND(AS21*('Inputs'!$D$59:$D$70-('Inputs'!$P$59:$P$70=AS5)*AS14),2))/AS30,2))) | AT34: =IF(AT30=0,0,SUMPRODUCT('Inputs'!$Q$59:$Q$70,ROUNDDOWN((('Inputs'!$D$59:$D$70-('Inputs'!$P$59:$P$70=AT5)*AT14)-'Inputs'!$R$59:$R$70*ROUND(AT21*('Inputs'!$D$59:$D$70-('Inputs'!$P$59:$P$70=AT5)*AT14),2))/AT30,2))) | ... BB34: =IF(BB30=0,0,SUMPRODUCT('Inputs'!$Q$59:$Q$70,ROUNDDOWN((('Inputs'!$D$59:$D$70-('Inputs'!$P$59:$P$70=BB5)*BB14)-'Inputs'!$R$59:$R$70*ROUND(BB21*('Inputs'!$D$59:$D$70-('Inputs'!$P$59:$P$70=BB5)*BB14),2))/BB30,2))) | BD34: =IF(BD30=0,0,SUMPRODUCT('Inputs'!$Q$59:$Q$70,ROUNDDOWN((('Inputs'!$D$59:$D$70-('Inputs'!$P$59:$P$70=BD5)*BD14)-'Inputs'!$R$59:$R$70*ROUND(BD21*('Inputs'!$D$59:$D$70-('Inputs'!$P$59:$P$70=BD5)*BD14),2))/BD30,2))) | BE34: =IF(BE30=0,0,SUMPRODUCT('Inputs'!$Q$59:$Q$70,ROUNDDOWN((('Inputs'!$D$59:$D$70-('Inputs'!$P$59:$P$70=BE5)*BE14)-'Inputs'!$R$59:$R$70*ROUND(BE21*('Inputs'!$D$59:$D$70-('Inputs'!$P$59:$P$70=BE5)*BE14),2))/BE30,2))) | BF34: =IF(BF30=0,0,SUMPRODUCT('Inputs'!$Q$59:$Q$70,ROUNDDOWN((('Inputs'!$D$59:$D$70-('Inputs'!$P$59:$P$70=BF5)*BF14)-'Inputs'!$R$59:$R$70*ROUND(BF21*('Inputs'!$D$59:$D$70-('Inputs'!$P$59:$P$70=BF5)*BF14),2))/BF30,2))) | BG34: =IF(BG30=0,0,SUMPRODUCT('Inputs'!$Q$59:$Q$70,ROUNDDOWN((('Inputs'!$D$59:$D$70-('Inputs'!$P$59:$P$70=BG5)*BG14)-'Inputs'!$R$59:$R$70*ROUND(BG21*('Inputs'!$D$59:$D$70-('Inputs'!$P$59:$P$70=BG5)*BG14),2))/BG30,2))) | BH34: =IF(BH30=0,0,SUMPRODUCT('Inputs'!$Q$59:$Q$70,ROUNDDOWN((('Inputs'!$D$59:$D$70-('Inputs'!$P$59:$P$70=BH5)*BH14)-'Inputs'!$R$59:$R$70*ROUND(BH21*('Inputs'!$D$59:$D$70-('Inputs'!$P$59:$P$70=BH5)*BH14),2))/BH30,2))) | BI34: =IF(BI30=0,0,SUMPRODUCT('Inputs'!$Q$59:$Q$70,ROUNDDOWN((('Inputs'!$D$59:$D$70-('Inputs'!$P$59:$P$70=BI5)*BI14)-'Inputs'!$R$59:$R$70*ROUND(BI21*('Inputs'!$D$59:$D$70-('Inputs'!$P$59:$P$70=BI5)*BI14),2))/BI30,2))) | BJ34: =IF(BJ30=0,0,SUMPRODUCT('Inputs'!$Q$59:$Q$70,ROUNDDOWN((('Inputs'!$D$59:$D$70-('Inputs'!$P$59:$P$70=BJ5)*BJ14)-'Inputs'!$R$59:$R$70*ROUND(BJ21*('Inputs'!$D$59:$D$70-('Inputs'!$P$59:$P$70=BJ5)*BJ14),2))/BJ30,2))) | BK34: =IF(BK30=0,0,SUMPRODUCT('Inputs'!$Q$59:$Q$70,ROUNDDOWN((('Inputs'!$D$59:$D$70-('Inputs'!$P$59:$P$70=BK5)*BK14)-'Inputs'!$R$59:$R$70*ROUND(BK21*('Inputs'!$D$59:$D$70-('Inputs'!$P$59:$P$70=BK5)*BK14),2))/BK30,2))) | ... BS34: =IF(BS30=0,0,SUMPRODUCT('Inputs'!$Q$59:$Q$70,ROUNDDOWN((('Inputs'!$D$59:$D$70-('Inputs'!$P$59:$P$70=BS5)*BS14)-'Inputs'!$R$59:$R$70*ROUND(BS21*('Inputs'!$D$59:$D$70-('Inputs'!$P$59:$P$70=BS5)*BS14),2))/BS30,2)))
